Workbook
Name Time: 'B5'!$D$22

Sheet Profit & Loss
B2: Text for B/S P&L item | C2: 44562 | D2: 44593 | E2: 44621 | F2: 44652 | G2: 44682 | H2: 44713 | I2: 44743 | J2: 44774 | K2: 44805 | L2: 44835 | M2: 44866 | N2: 44896 | O2: YTD 2023 | P2: 44927 | Q2: 44958 | R2: 44986 | S2: 45017 | T2: 45047 | U2: 45078 | V2: 45108 | W2: 45139 | X2: 45170 | Y2: 45200 | Z2: 45231 | AA2: 45266 | AB2: YTD 2023 | AC2: 45292 | AD2: 45323 | AE2: 45352 | AF2: 45383 | AG2: 45413 | AH2: 45444 | AI2: 45474 | AJ2: 45505 | AK2: 45536 | AL2: 45566 | AM2: 45597 | AN2: 45632 | AO2: YTD 2024 | AP2: 45658 | AQ2: 45689 | AR2: 45717 | AS2: 45748 | AT2: 45778 | AU2: 45809 | AV2: 45839 | AW2: 45870 | AX2: 45901 | AY2: 45931 | AZ2: 45962 | BA2: 45997 | BB2: YTD 2025 | BC2: 46023 | BD2: 46054 | BE2: 46082 | BF2: 46113 | BG2: 46143 | BH2: 46174 | BI2: 46204 | BJ2: 46235 | BK2: 46266 | BL2: 46296 | BM2: 46327 | BN2: 46362 | BO2: YTD 2026
B3: Profit and loss statement | C3: 0
B4: 4010000000 Sales PP Unit | C4: -58033.76 | D4: 0 | E4: 0 | F4: 0 | G4: 0 | H4: 0 | I4: 0 | J4: -1217492.9 | K4: -1849798.6 | L4: -136363.64 | M4: -221153.84 | N4: 0 | O4: =SUBTOTAL(9,C4:N4) -> -3482842.7 | P4: -1198350.1 | Q4: -1198350.1 | R4: 0 | S4: -136486.49 | T4: -86094.19 | U4: 0 | V4: -117821.58 | W4: -1054772.7 | X4: -66754.87 | Y4: -2100761.9 | Z4: -1248566 | AA4: -1853156.9 | AB4: =SUM(P4:AA4) -> -9061114.9 | AC4: 0 | AD4: 0 | AE4: 0 | AF4: 0 | AG4: 0 | AH4: 0 | AI4: -141158.54 | AJ4: -51648.26 | AK4: 0 | AL4: -84326.76 | AM4: -1110193 | AN4: -2612066 | AO4: =SUM(AC4:AN4) -> -3999392.6 | AP4: 0 | AQ4: -332868.91 | AR4: =VLOOKUP(B4,'[1]Sheet1 (2)'!$B$2:$C$397,2,0) -> 0 | AS4: =VLOOKUP(B4,'[2]Sheet1 (2)'!$B$2:$C$404,2,0) -> 0 | AT4: -183257.62 | AU4: -50235.39 | AV4: 0 | AW4: 0 | AX4: 0 | AY4: 0 | AZ4: -151542.78 | BA4: -42078.01 | BB4: =SUM(AP4:BA4) -> -759982.71 | BC4: 0 | BD4: 0 | BE4: 0 | BF4: -115467.26 | BG4: 0 | BH4: 0 | BI4: 0 | BO4: =SUM(BC4:BN4) -> -115467.26
B5: 4010001000 Sales PP Discount | C5: 3837.96 | D5: 0 | E5: 0 | F5: 0 | G5: 0 | H5: 0 | I5: 0 | J5: 0 | K5: 0 | L5: 0 | M5: 0 | N5: 0 | O5: =SUBTOTAL(9,C5:N5) -> 3837.96 | P5: 0 | Q5: 0 | R5: 0 | S5: 0 | T5: 12445.54 | U5: 0 | V5: 3252.04 | W5: 0 | X5: 0 | Y5: 0 | Z5: 0 | AA5: 0 | AB5: =SUM(P5:AA5) -> 15697.58 | AC5: 0 | AD5: 0 | AE5: 0 | AF5: 0 | AG5: 0 | AH5: 0 | AI5: 0 | AJ5: 2898.26 | AK5: 0 | AL5: 0 | AM5: 0 | AN5: 0 | AO5: =SUM(AC5:AN5) -> 2898.26 | AP5: 0 | AQ5: 0 | AR5: 0 | AS5: 0 | AT5: 0 | AU5: 2818.98 | AV5: 0 | AW5: 0 | AX5: 0 | AY5: 0 | AZ5: 4536.79 | BA5: 0 | BB5: =SUM(AP5:BA5) -> 7355.77 | BC5: 0 | BD5: 0 | BE5: 0 | BF5: 0 | BG5: 0 | BH5: 0 | BI5: 0 | BO5: =SUM(BC5:BN5) -> 0
B6: 4010300100 Sales PP Attachment Accessories | J6: -21410.81 | K6: -19858.66 | L6: 0 | M6: 0 | N6: 0 | O6: =SUBTOTAL(9,C6:N6) -> -41269.47 | P6: -21649.88 | Q6: -21649.88 | R6: 0 | S6: 0 | T6: 0 | U6: 0 | V6: 0 | W6: 0 | X6: -9219.15 | Y6: 0 | Z6: 0 | AA6: 0 | AB6: =SUM(P6:AA6) -> -52518.91 | AC6: 0 | AD6: 0 | AE6: 0 | AF6: 0 | AG6: 0 | AH6: 0 | AI6: 0 | AJ6: 0 | AK6: 0 | AL6: -3571.33 | AM6: 0 | AN6: 0 | AO6: =SUM(AC6:AN6) -> -3571.33 | AP6: 0 | AQ6: -14692.07 | AR6: =VLOOKUP(B6,'[1]Sheet1 (2)'!$B$2:$C$397,2,0) -> 0 | AS6: =VLOOKUP(B6,'[2]Sheet1 (2)'!$B$2:$C$404,2,0) -> 0 | AT6: -1456.67 | AU6: 0 | AV6: 0 | AW6: 0 | AX6: 0 | AY6: 0 | AZ6: 0 | BA6: 0 | BB6: =SUM(AP6:BA6) -> -16148.74 | BC6: 0 | BD6: 0 | BE6: 0 | BF6: -2661.4 | BG6: 0 | BH6: 0 | BI6: 0 | BO6: =SUM(BC6:BN6) -> -2661.4
B7: 4010400000 Sales PP Power System Project | K7: -61497.45 | L7: 0 | M7: -77268.68 | N7: 0 | O7: =SUBTOTAL(9,C7:N7) -> -138766.13 | P7: 0 | Q7: 0 | R7: 0 | S7: 0 | T7: 0 | U7: 0 | V7: 0 | W7: 0 | X7: 0 | Y7: -528040 | Z7: 0 | AA7: 0 | AB7: =SUM(P7:AA7) -> -528040 | AC7: 0 | AD7: 0 | AE7: -694532.85 | AF7: 0 | AG7: 0 | AH7: 0 | AI7: 0 | AJ7: 0 | AK7: 0 | AL7: 0 | AM7: 0 | AN7: 0 | AO7: =SUM(AC7:AN7) -> -694532.85 | AP7: 0 | AQ7: 0 | AR7: 0 | AS7: 0 | AT7: 0 | AU7: 0 | AV7: -90391.32 | AW7: 0 | AX7: 0 | AY7: 0 | AZ7: 0 | BA7: 0 | BB7: =SUM(AP7:BA7) -> -90391.32 | BC7: 0 | BD7: 0 | BE7: -494355.44 | BF7: 0 | BG7: 0 | BH7: 0 | BI7: 0 | BO7: =SUM(BC7:BN7) -> -494355.44
B8: 4010401000 Sales PP Power System Accrual/Defferal | S8: 2597.52 | T8: 0 | U8: 0 | V8: 0 | W8: -331221.69 | X8: -132089.61 | Y8: 463311.3 | Z8: 0 | AA8: -565357.01 | AB8: =SUM(P8:AA8) -> -562759.49 | AC8: -17875.68 | AD8: -3003.32 | AE8: 586236.01 | AF8: 0 | AG8: 0 | AH8: 0 | AI8: 0 | AJ8: 0 | AK8: 0 | AL8: 0 | AM8: 0 | AN8: 0 | AO8: =SUM(AC8:AN8) -> 565357.01 | AP8: 0 | AQ8: 0 | AR8: 0 | AS8: 0 | AT8: 0 | AU8: 0 | AV8: 0 | AW8: 0 | AX8: 0 | AY8: 0 | AZ8: 0 | BA8: -435432.41 | BB8: =SUM(AP8:BA8) -> -435432.41 | BC8: -180.87 | BD8: -921.2 | BE8: 436534.48 | BF8: 0 | BG8: 0 | BH8: 0 | BI8: 0 | BO8: =SUM(BC8:BN8) -> 435432.41
B9: 4010402000 Sales PP Power System Acc Defferal | K9: 61497.45 | L9: 0 | M9: 77268.68 | N9: 0 | O9: =SUBTOTAL(9,C9:N9) -> 138766.13 | P9: -9.94 | Q9: -178.41 | R9: -230.87 | S9: 0 | T9: 0 | U9: 0 | V9: 0 | W9: -61497.45 | X9: 0 | Y9: 59878.98 | Z9: -1245.5 | AA9: -84409.3 | AB9: =SUM(P9:AA9) -> -87692.49 | AC9: -577.03 | AD9: -340.37 | AE9: 78698.37 | AF9: -4187.48 | AG9: -1673.57 | AH9: -103.61 | AI9: -1796.73 | AJ9: -18492.13 | AK9: -78.04 | AL9: -2131.98 | AM9: -1252.87 | AN9: -13888.03 | AO9: =SUM(AC9:AN9) -> 34176.53 | AP9: 0 | AQ9: -4207.88 | AR9: =VLOOKUP(B9,'[1]Sheet1 (2)'!$B$2:$C$397,2,0) -> -1534.87 | AS9: =VLOOKUP(B9,'[2]Sheet1 (2)'!$B$2:$C$404,2,0) -> -2172.28 | AT9: -2093.48 | AU9: -4424.91 | AV9: 88991.82 | AW9: 0 | AX9: -2599.3 | AY9: -2933.71 | AZ9: -45.69 | BA9: -90391.32 | BB9: =SUM(AP9:BA9) -> -21411.62 | BC9: 0 | BD9: -6304.41 | BE9: 45974.93 | BF9: -889.35 | BG9: 0 | BH9: -114.76 | BI9: -115.56 | BO9: =SUM(BC9:BN9) -> 38550.85
B10: 4010600000 Sales PP Attachment | AC10: 0 | AD10: 0 | AE10: 0 | AF10: 0 | AG10: 0 | AH10: 0 | AI10: 0 | AJ10: 0 | AK10: -39407.89 | AL10: 0 | AM10: 0 | AN10: 0 | AO10: =SUM(AC10:AN10) -> -39407.89 | AP10: 0 | AQ10: 0 | AR10: 0 | AS10: 0 | AT10: 0 | AU10: 0 | AV10: 0 | AW10: 0 | AX10: 0 | AY10: 0 | AZ10: 0 | BA10: 0 | BB10: =SUM(AP10:BA10) -> 0 | BC10: 0 | BD10: 0 | BE10: 0 | BF10: 0 | BG10: 0 | BH10: 0 | BI10: 0 | BO10: =SUM(BC10:BN10) -> 0
B11: 4011500000 IFRS 15 Prime Product | K11: -986368.35 | L11: 0 | M11: 0 | N11: 0 | O11: =SUBTOTAL(9,C11:N11) -> -986368.35 | P11: 0 | Q11: 0 | R11: 0 | S11: 0 | T11: 0 | U11: 0 | V11: 0 | W11: 0 | X11: -599.25 | Y11: -743.07 | Z11: -719.1 | AA11: -743.07 | AB11: =SUM(P11:AA11) -> -2804.49 | AC11: -743.07 | AD11: -695.13 | AE11: -743.07 | AF11: -719.09 | AG11: -743.07 | AH11: -719.09 | AI11: -141616.82 | AJ11: -743.06 | AK11: -119.85 | AL11: 0 | AM11: 0 | AN11: -431698.56 | AO11: =SUM(AC11:AN11) -> -578540.81 | AP11: 0 | AQ11: -331372.52 | AR11: =VLOOKUP(B11,'[1]Sheet1 (2)'!$B$2:$C$397,2,0) -> 0 | AS11: =VLOOKUP(B11,'[2]Sheet1 (2)'!$B$2:$C$404,2,0) -> 0 | AT11: 0 | AU11: 0 | AV11: 0 | AW11: 0 | AX11: 0 | AY11: 0 | AZ11: 0 | BA11: -41467.99 | BB11: =SUM(AP11:BA11) -> -372840.51 | BC11: 0 | BD11: 0 | BE11: 0 | BF11: -114656.9 | BG11: 0 | BH11: 0 | BI11: 0 | BO11: =SUM(BC11:BN11) -> -114656.9
B12: 4011500100 IFRS 15 Prime Product unit Adjustment | K12: 995141.34 | L12: 0 | M12: 0 | N12: 0 | O12: =SUBTOTAL(9,C12:N12) -> 995141.34 | P12: 0 | Q12: 0 | R12: 0 | S12: 0 | T12: 0 | U12: 0 | V12: 0 | W12: 0 | X12: 0 | Y12: 0 | Z12: 0 | AA12: 0 | AB12: =SUM(P12:AA12) -> 0 | AC12: 0 | AD12: 0 | AE12: 0 | AF12: 0 | AG12: 0 | AH12: 0 | AI12: 141158.54 | AJ12: 0 | AK12: 0 | AL12: 0 | AM12: 0 | AN12: 432546.01 | AO12: =SUM(AC12:AN12) -> 573704.55 | AP12: 0 | AQ12: 332868.9 | AR12: =VLOOKUP(B12,'[1]Sheet1 (2)'!$B$2:$C$397,2,0) -> 0 | AS12: =VLOOKUP(B12,'[2]Sheet1 (2)'!$B$2:$C$404,2,0) -> 0 | AT12: 0 | AU12: 0 | AV12: 0 | AW12: 0 | AX12: 0 | AY12: 0 | AZ12: 0 | BA12: 42078 | BB12: =SUM(AP12:BA12) -> 374946.9 | BC12: 0 | BD12: 0 | BE12: 0 | BF12: 115467.25 | BG12: 0 | BH12: 0 | BI12: 0 | BO12: =SUM(BC12:BN12) -> 115467.25
B13: PRIME PRODUCT | C13: =SUM(C4:C12) -> -54195.8 | D13: =SUM(D4:D12) -> 0 | E13: =SUM(E4:E12) -> 0 | F13: =SUM(F4:F12) -> 0 | G13: =SUM(G4:G12) -> 0 | H13: =SUM(H4:H12) -> 0 | I13: =SUM(I4:I12) -> 0 | J13: =SUM(J4:J12) -> -1238903.7 | ... N13: =SUM(N4:N12) -> 0 | O13: =SUM(C13:N13) -> -3511501.2 | P13: =SUM(P4:P12) -> -1220009.9 | Q13: =SUM(Q4:Q12) -> -1220178.4 | R13: =SUM(R4:R12) -> -230.87 | S13: =SUM(S4:S12) -> -133888.97 | T13: =SUM(T4:T12) -> -73648.65 | U13: =SUM(U4:U12) -> 0 | V13: =SUM(V4:V12) -> -114569.54 | W13: =SUM(W4:W12) -> -1447491.9 | ... BO13: =SUM(BO4:BO12) -> -137690.49
B14: 4020100101 Sales Parts Through Counter | C14: -4673022.8 | D14: -4680697.2 | E14: -5357309.4 | F14: -4581013.4 | G14: -5610312.7 | H14: -6382204.7 | I14: -5446430.7 | J14: -3544566.2 | K14: -8781431.1 | L14: -7534841.5 | M14: -9220274.5 | N14: -9671792.2 | O14: =SUBTOTAL(9,C14:N14) -> -75483896 | P14: -6903467.4 | Q14: -4489216.9 | R14: -10302351 | S14: -5795173.8 | T14: -7515693.3 | U14: -5919972.3 | V14: -4809437 | W14: -5348221.4 | X14: -5246466.7 | Y14: -5095288.3 | Z14: -3434892.4 | AA14: -4609744.4 | AB14: =SUM(P14:AA14) -> -69469925 | AC14: -3769518.3 | AD14: -4610219 | AE14: -4865200.8 | AF14: -4198492.5 | AG14: -4920435.6 | AH14: -4315235.3 | AI14: -4831902 | AJ14: -1415125 | AK14: -9517097.1 | AL14: -4666708.2 | AM14: -4005350.7 | AN14: -3626109.2 | AO14: =SUM(AC14:AN14) -> -54741394 | AP14: -3289691.5 | AQ14: -3228428.6 | AR14: =VLOOKUP(B14,'[1]Sheet1 (2)'!$B$2:$C$397,2,0) -> -2208403.6 | AS14: =VLOOKUP(B14,'[2]Sheet1 (2)'!$B$2:$C$404,2,0) -> -2528704.8 | AT14: -3558221.2 | AU14: -3456846.2 | AV14: -2911914.2 | AW14: -2993312.9 | AX14: -2743175.7 | AY14: -3154594.6 | AZ14: -3907670 | BA14: -2873619.1 | BB14: =SUM(AP14:BA14) -> -36854582 | BC14: -2857496.4 | BD14: -3903125.1 | BE14: -3737634.2 | BF14: -3148686.3 | BG14: -2414605 | BH14: -2861914.5 | BI14: -3199594.6 | BO14: =SUM(BC14:BN14) -> -22123056
B15: 4020100202 Sales Parts Through Service Flat Rate | C15: -9457.29 | D15: -11473.07 | E15: 0 | F15: -33227.21 | G15: -65960.17 | H15: -798391.47 | I15: -17949.05 | J15: 0 | K15: 0 | L15: 0 | M15: 0 | N15: -1101488.4 | O15: =SUBTOTAL(9,C15:N15) -> -2037946.7 | P15: 0 | Q15: -571752.83 | R15: -791010.66 | S15: -276689.37 | T15: -748037.33 | U15: -888742.45 | V15: -592512.15 | W15: -617667.03 | X15: -658056.78 | Y15: -783989.16 | Z15: -726585.07 | AA15: -1203804.5 | AB15: =SUM(P15:AA15) -> -7858847.3 | AC15: -409997.09 | AD15: -1520295 | AE15: -760184.13 | AF15: -938457.36 | AG15: -1392552.4 | AH15: -1141536.9 | AI15: -1251075.3 | AJ15: -1101877 | AK15: -1527652.1 | AL15: -1132959.5 | AM15: -1137260.4 | AN15: -1523606.1 | AO15: =SUM(AC15:AN15) -> -13837453 | AP15: -941238.03 | AQ15: -1119248.1 | AR15: =VLOOKUP(B15,'[1]Sheet1 (2)'!$B$2:$C$397,2,0) -> -743599.4 | AS15: =VLOOKUP(B15,'[2]Sheet1 (2)'!$B$2:$C$404,2,0) -> -561730.55 | AT15: -690693.76 | AU15: -248781.28 | AV15: -38895.8 | AW15: -287623.57 | AX15: -659890.02 | AY15: -191804.31 | AZ15: -35922.93 | BA15: -534368.93 | BB15: =SUM(AP15:BA15) -> -6053796.6 | BC15: -320423.9 | BD15: -198045.15 | BE15: -420995.6 | BF15: -258893.01 | BG15: -596968.85 | BH15: -514855.07 | BI15: -290891.26 | BO15: =SUM(BC15:BN15) -> -2601072.8
B16: 4020100206 Sales Parts Through Service Flat Rate Variance | C16: 0.01 | D16: 471.93 | E16: 0 | F16: -0.01 | G16: 23587.1 | H16: 33038.42 | I16: 133.07 | J16: 0 | K16: 0 | L16: 0 | M16: 0 | N16: 46421.01 | O16: =SUBTOTAL(9,C16:N16) -> 103651.53 | P16: 0 | Q16: 35871.76 | R16: 60591.39 | S16: 45319.51 | T16: 15489.23 | U16: 13652.22 | V16: 18775.66 | W16: 33418.68 | X16: 1832.8 | Y16: -18355.27 | Z16: -7959.88 | AA16: -4046.58 | AB16: =SUM(P16:AA16) -> 194589.52 | AC16: 8411.52 | AD16: 29341.59 | AE16: 19588.35 | AF16: 11149.11 | AG16: 33841.64 | AH16: -39894.09 | AI16: -6494.88 | AJ16: 3380.39 | AK16: -22645.63 | AL16: -20370.16 | AM16: -23745.23 | AN16: -4585.62 | AO16: =SUM(AC16:AN16) -> -12023.01 | AP16: 946.4 | AQ16: -28576.87 | AR16: =VLOOKUP(B16,'[1]Sheet1 (2)'!$B$2:$C$397,2,0) -> -6310.54 | AS16: =VLOOKUP(B16,'[2]Sheet1 (2)'!$B$2:$C$404,2,0) -> 60475.36 | AT16: 14437.56 | AU16: 48.85 | AV16: 5369.78 | AW16: -4392.48 | AX16: -903.63 | AY16: -714.44 | AZ16: -613.78 | BA16: 1663.86 | BB16: =SUM(AP16:BA16) -> 41430.07 | BC16: -5876.67 | BD16: -1102.18 | BE16: -903.92 | BF16: 22575.88 | BG16: -12340.37 | BH16: -13127.59 | BI16: 5928.33 | BO16: =SUM(BC16:BN16) -> -4846.52
B17: 4020400101 Sales Parts Through Counter CORE | C17: -49623.57 | D17: -39159.6 | E17: -57552.92 | F17: -318317.4 | G17: -112916.5 | H17: -45099.88 | I17: -28251.79 | J17: -37039.66 | K17: -63609.83 | L17: -36077.2 | M17: -65520.64 | N17: -61358.9 | O17: =SUBTOTAL(9,C17:N17) -> -914527.89 | P17: -119266.71 | Q17: -87590.32 | R17: -66817.8 | S17: -58517.07 | T17: -48568.27 | U17: -61179.96 | V17: -50416.13 | W17: -29133.99 | X17: -24755.82 | Y17: -16331.08 | Z17: -5046.25 | AA17: -3970.72 | AB17: =SUM(P17:AA17) -> -571594.12 | AC17: -11477.09 | AD17: -162.03 | AE17: -4471.36 | AF17: -5976.62 | AG17: -723.7 | AH17: 0 | AI17: -13110.72 | AJ17: -6808.54 | AK17: -1289.54 | AL17: 0 | AM17: -65.17 | AN17: -1053.06 | AO17: =SUM(AC17:AN17) -> -45137.83 | AP17: 0 | AQ17: -1042.11 | AR17: =VLOOKUP(B17,'[1]Sheet1 (2)'!$B$2:$C$397,2,0) -> -1191.1 | AS17: =VLOOKUP(B17,'[2]Sheet1 (2)'!$B$2:$C$404,2,0) -> -1770.54 | AT17: -85425.21 | AU17: -85609.27 | AV17: -189341.33 | AW17: -128227.88 | AX17: -96785.03 | AY17: -176305.86 | AZ17: -200441.27 | BA17: -135232.25 | BB17: =SUM(AP17:BA17) -> -1101371.9 | BC17: -123857.75 | BD17: -150909.48 | BE17: -160529.64 | BF17: -204842.37 | BG17: -102099.91 | BH17: -110298.9 | BI17: -158473.97 | BO17: =SUM(BC17:BN17) -> -1011012
B18: 4020400202 Sales Parts Through Service CORE Flat Rate | P18: 0 | Q18: 0 | R18: 0 | S18: 0 | T18: 0 | U18: 0 | V18: 0 | W18: -2235.37 | X18: 0 | Y18: 0 | Z18: 0 | AA18: 0 | AB18: =SUM(P18:AA18) -> -2235.37 | AC18: 0 | AD18: 0 | AE18: 0 | AF18: 0 | AG18: -17970.59 | AH18: 0 | AI18: 0 | AJ18: -2855.7 | AK18: 0 | AL18: 0 | AM18: 0 | AN18: 0 | AO18: =SUM(AC18:AN18) -> -20826.29 | AP18: 0 | AQ18: 1638.89 | AR18: =VLOOKUP(B18,'[1]Sheet1 (2)'!$B$2:$C$397,2,0) -> 6532.28 | AS18: =VLOOKUP(B18,'[2]Sheet1 (2)'!$B$2:$C$404,2,0) -> 0 | AT18: 0 | AU18: 0 | AV18: 0 | AW18: 0 | AX18: 0 | AY18: 0 | AZ18: 0 | BA18: -3045.22 | BB18: =SUM(AP18:BA18) -> 5125.95 | BC18: 0 | BD18: -1327.38 | BE18: -813.73 | BF18: 0 | BG18: 0 | BH18: 0 | BI18: 0 | BO18: =SUM(BC18:BN18) -> -2141.11
B19: 4020500100 Sales Parts SOS Bottle | C19: -27.12 | D19: -7.59 | E19: -65.33 | F19: -11.75 | G19: -26.78 | H19: -32.69 | I19: -44.99 | J19: -28.09 | K19: -53.36 | L19: -91.36 | M19: -64.11 | N19: -114.99 | O19: =SUBTOTAL(9,C19:N19) -> -568.16 | P19: -47.33 | Q19: -32.64 | R19: -75.89 | S19: 0 | T19: -36.6 | U19: -43.11 | V19: -66.17 | W19: -41.55 | X19: 0 | Y19: -34.21 | Z19: -38.56 | AA19: -3.64 | AB19: =SUM(P19:AA19) -> -419.7 | AC19: -3.64 | AD19: -59.49 | AE19: -4.79 | AF19: -36.33 | AG19: -28.55 | AH19: -1.73 | AI19: -4.8 | AJ19: 0 | AK19: 0 | AL19: -6.26 | AM19: -0.93 | AN19: 0 | AO19: =SUM(AC19:AN19) -> -146.52 | AP19: 0 | AQ19: -22.01 | AR19: =VLOOKUP(B19,'[1]Sheet1 (2)'!$B$2:$C$397,2,0) -> -56.63 | AS19: =VLOOKUP(B19,'[2]Sheet1 (2)'!$B$2:$C$404,2,0) -> -30.18 | AT19: -20.35 | AU19: -12.81 | AV19: -59.29 | AW19: 0 | AX19: -8.29 | AY19: -25.33 | AZ19: -6.55 | BA19: -39.35 | BB19: =SUM(AP19:BA19) -> -280.79 | BC19: -37.62 | BD19: -65.1 | BE19: -2.88 | BF19: -11.08 | BG19: -8.32 | BH19: -6.56 | BI19: -7.57 | BO19: =SUM(BC19:BN19) -> -139.13
B20: 4020500107 Sales Parts SOS Lab Bottle Actual Discount | BC20: 0 | BD20: 0 | BE20: 0.02 | BF20: 0 | BG20: 0.02 | BH20: 0 | BI20: 0 | BO20: =SUM(BC20:BN20) -> 0.04
B21: 4020500101 Sales Parts Through Counter USED Parts | C21: -133950.59 | D21: 0 | E21: -16032.99 | F21: 0 | G21: 0 | H21: -81729.26 | I21: 0 | J21: -60946.7 | K21: -23529.41 | L21: 0 | M21: 0 | N21: 0 | O21: =SUBTOTAL(9,C21:N21) -> -316188.95 | P21: 0 | Q21: 0 | R21: 0 | S21: 0 | T21: 0 | U21: 0 | V21: -43333.33 | W21: 0 | X21: -93567.84 | Y21: -6354.77 | Z21: 0 | AA21: 0 | AB21: =SUM(P21:AA21) -> -143255.94 | AC21: -40134.31 | AD21: 0 | AE21: -39126.74 | AF21: 0 | AG21: 0 | AH21: 0 | AI21: 0 | AJ21: 0 | AK21: 0 | AL21: 0 | AM21: 0 | AN21: 0 | AO21: =SUM(AC21:AN21) -> -79261.05 | AP21: 0 | AQ21: 0 | AR21: 0 | AS21: 0 | AT21: 0 | AU21: 0 | AV21: 0 | AW21: 0 | AX21: 0 | AY21: 0 | AZ21: 0 | BA21: 0 | BB21: =SUM(AP21:BA21) -> 0 | BC21: 0 | BD21: 0 | BE21: 0 | BF21: 0 | BG21: 0 | BH21: 0 | BI21: 0 | BO21: =SUM(BC21:BN21) -> 0
B22: 4020500200 Sales Digital Subscription | AC22: 0 | AD22: 0 | AE22: 0 | AF22: 0 | AG22: 0 | AH22: 0 | AI22: 0 | AJ22: 0 | AK22: 0 | AL22: 0 | AM22: 0 | AN22: -287.43 | AO22: =SUM(AC22:AN22) -> -287.43 | AP22: 0 | AQ22: -197.62 | AR22: =VLOOKUP(B22,'[1]Sheet1 (2)'!$B$2:$C$397,2,0) -> 0 | AS22: =VLOOKUP(B22,'[2]Sheet1 (2)'!$B$2:$C$404,2,0) -> -190.12 | AT22: 0 | AU22: -1580.47 | AV22: -1652.29 | AW22: -8573.97 | AX22: -1018.13 | AY22: 0 | AZ22: 0 | BA22: -4152.28 | BB22: =SUM(AP22:BA22) -> -17364.88 | BC22: -202.57 | BD22: -4502.57 | BE22: 0 | BF22: 0 | BG22: 0 | BH22: -190.87 | BI22: 0 | BO22: =SUM(BC22:BN22) -> -4896.01
B23: 4020500202 Sales Parts Through Service USED Parts Flat Rate | AP23: 0 | AQ23: 0 | AR23: 0 | AS23: 0 | AT23: 0 | AU23: 0 | AV23: 0 | AW23: 0 | AX23: 0 | AY23: -1701.72 | AZ23: 0 | BA23: 0 | BB23: =SUM(AP23:BA23) -> -1701.72 | BC23: 0 | BD23: 0 | BE23: 0 | BF23: 0 | BG23: 0 | BH23: 0 | BI23: 0 | BO23: =SUM(BC23:BN23) -> 0
B24: 4020800101 Sales Parts Through Counter PEX Product Parts | C24: 0 | D24: -146463.94 | E24: -132542.74 | F24: 0 | G24: -28126.87 | H24: -69398.4 | I24: -954.34 | J24: -76275.5 | K24: -44571.94 | L24: 0 | M24: 0 | N24: -127667.63 | O24: =SUBTOTAL(9,C24:N24) -> -626001.36 | P24: -78516.34 | Q24: -30570.01 | R24: -114206.9 | S24: 0 | T24: -43713.19 | U24: -117856.39 | V24: -259288.66 | W24: -244737.6 | X24: -110060.45 | Y24: -31584.62 | Z24: 0 | AA24: 0 | AB24: =SUM(P24:AA24) -> -1030534.2 | AC24: 0 | AD24: -1554.55 | AE24: 0 | AF24: 0 | AG24: 0 | AH24: 0 | AI24: 0 | AJ24: 0 | AK24: 0 | AL24: 0 | AM24: 0 | AN24: 0 | AO24: =SUM(AC24:AN24) -> -1554.55 | AP24: 0 | AQ24: 0 | AR24: 0 | AS24: 0 | AT24: 0 | AU24: 0 | AV24: 0 | AW24: -120541.99 | AX24: 0 | AY24: -127715.57 | AZ24: -40296.13 | BA24: -49714.79 | BB24: =SUM(AP24:BA24) -> -338268.48 | BC24: -38723.75 | BD24: -328281.16 | BE24: -117641.99 | BF24: 0 | BG24: 0 | BH24: -107312.64 | BI24: -84405.15 | BO24: =SUM(BC24:BN24) -> -676364.69
B25: 4020800102 Sales Parts Through Counter PEX Core Parts | E25: -146097.83 | F25: 0 | G25: -78051.36 | H25: -225704.97 | I25: -5014.74 | J25: -274453.04 | K25: -187389.62 | L25: 0 | M25: 0 | N25: -139899.91 | O25: =SUBTOTAL(9,C25:N25) -> -1056611.5 | P25: -296751.67 | Q25: -87722.95 | R25: -79761.93 | S25: 0 | T25: -137011.11 | U25: -459214.92 | V25: -285787.04 | W25: -194987.98 | X25: -171197.51 | Y25: -91000.64 | Z25: 0 | AA25: 0 | AB25: =SUM(P25:AA25) -> -1803435.7 | AC25: 0 | AD25: -4480.61 | AE25: 0 | AF25: 0 | AG25: 0 | AH25: 0 | AI25: 0 | AJ25: 0 | AK25: 0 | AL25: 0 | AM25: 0 | AN25: 0 | AO25: =SUM(AC25:AN25) -> -4480.61 | AP25: 0 | AQ25: 0 | AR25: 0 | AS25: 0 | AT25: 0 | AU25: 0 | AV25: 0 | AW25: -77387.89 | AX25: 0 | AY25: -115550.41 | AZ25: -93804.87 | BA25: -128383.74 | BB25: =SUM(AP25:BA25) -> -415126.91 | BC25: -160539.47 | BD25: -536484.91 | BE25: -75526.1 | BF25: 0 | BG25: 0 | BH25: -25564.29 | BI25: -108647.07 | BO25: =SUM(BC25:BN25) -> -906761.84
B26: 4020900100 Sales Parts Freight Charges | C26: -1606.18 | D26: 33.87 | E26: -559.24 | F26: 0 | G26: -7534.06 | H26: -5017.58 | I26: -8809.04 | J26: -1976.3 | K26: -25501.38 | L26: -1979.22 | M26: -13400.78 | N26: -5059.83 | O26: =SUBTOTAL(9,C26:N26) -> -71409.74 | P26: -2512.26 | Q26: -4124.26 | R26: -2637.59 | S26: -2490.86 | T26: -5382.71 | U26: -13070.08 | V26: -9445.06 | W26: -1580.52 | X26: -1155.56 | Y26: -2695.67 | Z26: -11384.86 | AA26: -3499.61 | AB26: =SUM(P26:AA26) -> -59979.04 | AC26: -1057.15 | AD26: -2963.04 | AE26: -2809.91 | AF26: 0 | AG26: 0 | AH26: 0 | AI26: -3119.73 | AJ26: -4515.1 | AK26: 0 | AL26: -3231.44 | AM26: 0 | AN26: -1689.1 | AO26: =SUM(AC26:AN26) -> -19385.47 | AP26: 0 | AQ26: 0 | AR26: 0 | AS26: 0 | AT26: 0 | AU26: 0 | AV26: -22565.33 | AW26: -1144.96 | AX26: -3230.02 | AY26: -1790.38 | AZ26: -524.94 | BA26: -1905.65 | BB26: =SUM(AP26:BA26) -> -31161.28 | BC26: -3363.51 | BD26: -3328.96 | BE26: -911.29 | BF26: -3877.9 | BG26: 0 | BH26: -0.49 | BI26: 0 | BO26: =SUM(BC26:BN26) -> -11482.15
B27: 4021000101 Sales Parts Discount TPCP | C27: 12361.59 | D27: 7910.82 | E27: 14657.85 | F27: 12518.9 | G27: 19923.82 | H27: 14121.07 | I27: 13118.59 | J27: 16632.26 | K27: 23059.51 | L27: 23028.07 | M27: 28250.49 | N27: 21187.63 | O27: =SUBTOTAL(9,C27:N27) -> 206770.6 | P27: 15005.41 | Q27: 22721.86 | R27: 13784.98 | S27: 29478 | T27: 32816.67 | U27: 54645.62 | V27: 45858.54 | W27: 15563.63 | X27: 5529.32 | Y27: 15321.41 | Z27: 10925.44 | AA27: 10197.14 | AB27: =SUM(P27:AA27) -> 271848.02 | AC27: 15071.25 | AD27: 13600.84 | AE27: 5104.28 | AF27: 8076.63 | AG27: 10457.46 | AH27: 8971.38 | AI27: 5817.46 | AJ27: 11901.63 | AK27: 7057.07 | AL27: 6233.64 | AM27: 4866.37 | AN27: 8138.19 | AO27: =SUM(AC27:AN27) -> 105296.2 | AP27: 9021.43 | AQ27: 11122.69 | AR27: =VLOOKUP(B27,'[1]Sheet1 (2)'!$B$2:$C$397,2,0) -> 5074.75 | AS27: =VLOOKUP(B27,'[2]Sheet1 (2)'!$B$2:$C$404,2,0) -> 4441.29 | AT27: 9235.4 | AU27: 7939.36 | AV27: 981.06 | AW27: 1405.87 | AX27: 5999.24 | AY27: 6912.83 | AZ27: 13230.5 | BA27: 0 | BB27: =SUM(AP27:BA27) -> 75364.42 | BC27: 0 | BD27: 0 | BE27: 0 | BF27: 0 | BG27: 0 | BH27: 0 | BI27: 0 | BO27: =SUM(BC27:BN27) -> 0
B28: 4021000101 SLS Parts Discount | AP28: 0 | AQ28: 0 | AR28: 0 | AS28: 0 | AT28: 0 | AU28: 0 | AV28: 0 | AW28: 0 | AX28: 0 | AY28: 0 | AZ28: 0 | BA28: 3138.87 | BB28: =SUM(AP28:BA28) -> 3138.87 | BC28: 2783.65 | BD28: 7904.59 | BE28: 2659.14 | BF28: 2498.68 | BG28: 1246.69 | BH28: 5493.79 | BI28: 4707.63 | BO28: =SUM(BC28:BN28) -> 27294.17
B29: 4021000201 Sales PS Parts Discount Thru Service | BC29: 0 | BD29: 0 | BE29: 0 | BF29: 0 | BG29: 0 | BH29: 1189.84 | BI29: 10048.03 | BO29: =SUM(BC29:BN29) -> 11237.87
B30: 4021000202 Sales PS Parts Variance Discount Thru Service | BC30: 0 | BD30: 0 | BE30: 0 | BF30: 0 | BG30: 0 | BH30: -916.48 | BI30: -5122.87 | BO30: =SUM(BC30:BN30) -> -6039.35
B31: 4021400103 Sales Parts PEX Fee | C31: 0 | D31: -9916.38 | E31: -6223.35 | F31: 0 | G31: -2283.41 | H31: -6346.31 | I31: -128.37 | J31: -7542.56 | K31: -4988.42 | L31: 0 | M31: 0 | N31: -5754.14 | O31: =SUBTOTAL(9,C31:N31) -> -43182.94 | P31: -8070.29 | Q31: -2543.94 | R31: -4171.37 | S31: 0 | T31: -3886.54 | U31: -10293.56 | V31: -11608.78 | W31: -9654.85 | X31: -5989.53 | Y31: -2446.92 | Z31: 0 | AA31: 0 | AB31: =SUM(P31:AA31) -> -58665.78 | AC31: 0 | AD31: -129.79 | AE31: 0 | AF31: 0 | AG31: 0 | AH31: 0 | AI31: 0 | AJ31: 0 | AK31: 0 | AL31: 0 | AM31: 0 | AN31: 0 | AO31: =SUM(AC31:AN31) -> -129.79 | AP31: 0 | AQ31: 0 | AR31: 0 | AS31: 0 | AT31: 0 | AU31: 0 | AV31: 0 | AW31: -4256.56 | AX31: 0 | AY31: -5231.53 | AZ31: -2883.89 | BA31: -3830.08 | BB31: =SUM(AP31:BA31) -> -16202.06 | BC31: -4285.22 | BD31: -18597.12 | BE31: -4154.15 | BF31: 0 | BG31: 0 | BH31: -2857.57 | BI31: -4019.3 | BO31: =SUM(BC31:BN31) -> -33913.36
B32: 4021500002 IFRS 15 Preventive Maintenance Parts | AC32: 0 | AD32: 0 | AE32: 0 | AF32: 0 | AG32: 0 | AH32: 0 | AI32: -284.79 | AJ32: 0 | AK32: 0 | AL32: 0 | AM32: 0 | AN32: -847.45 | AO32: =SUM(AC32:AN32) -> -1132.24 | AP32: 0 | AQ32: -1496.38 | AR32: =VLOOKUP(B32,'[1]Sheet1 (2)'!$B$2:$C$397,2,0) -> 0 | AS32: =VLOOKUP(B32,'[2]Sheet1 (2)'!$B$2:$C$404,2,0) -> 0 | AT32: 0 | AU32: 0 | AV32: 0 | AW32: 0 | AX32: 0 | AY32: 0 | AZ32: 0 | BA32: 0 | BB32: =SUM(AP32:BA32) -> -1496.38 | BC32: 0 | BD32: 0 | BE32: 0 | BF32: 0 | BG32: -810.35 | BH32: 0 | BI32: 0 | BO32: =SUM(BC32:BN32) -> -810.35
B33: 4021900101 Sales Parts Discount PSWEB | AC33: 0 | AD33: 0 | AE33: 0 | AF33: 0 | AG33: 0 | AH33: 0 | AI33: 0 | AJ33: 0 | AK33: 35.65 | AL33: 53.56 | AM33: 13.19 | AN33: 23.02 | AO33: =SUM(AC33:AN33) -> 125.42 | AP33: 18.79 | AQ33: 44.24 | AR33: =VLOOKUP(B33,'[1]Sheet1 (2)'!$B$2:$C$397,2,0) -> 141.56 | AS33: =VLOOKUP(B33,'[2]Sheet1 (2)'!$B$2:$C$404,2,0) -> 0 | AT33: 0 | AU33: 0 | AV33: 0 | AW33: 0 | AX33: 0 | AY33: 0.88 | AZ33: 0 | BA33: 0 | BB33: =SUM(AP33:BA33) -> 205.47 | BC33: 0 | BD33: 0 | BE33: 0 | BF33: 26.71 | BG33: 195.29 | BH33: 223.68 | BI33: 136.82 | BO33: =SUM(BC33:BN33) -> 582.5
B34: PARTS | C34: =SUM(C14:C31) -> -4855325.9 | D34: =SUM(D14:D31) -> -4879301.2 | E34: =SUM(E14:E31) -> -5701726 | F34: =SUM(F14:F31) -> -4920050.9 | G34: =SUM(G14:G31) -> -5861700.9 | H34: =SUM(H14:H31) -> -7566765.8 | I34: =SUM(I14:I31) -> -5494331.4 | J34: =SUM(J14:J31) -> -3986195.8 | ... N34: =SUM(N14:N31) -> -11045527 | O34: =SUM(C34:N34) -> -80239911 | P34: =SUM(P14:P31) -> -7393626.5 | Q34: =SUM(Q14:Q31) -> -5214960.2 | R34: =SUM(R14:R31) -> -11286657 | S34: =SUM(S14:S31) -> -6058073.6 | T34: =SUM(T14:T31) -> -8454023.2 | U34: =SUM(U14:U31) -> -7402074.9 | V34: =SUM(V14:V31) -> -5997260.1 | W34: =SUM(W14:W31) -> -6399278 | ... AB34: =SUM(AB14:AB31) -> -80532455 | AC34: =SUM(AC14:AC33) -> -4208704.8 | AD34: =SUM(AD14:AD33) -> -6096921.1 | AE34: =SUM(AE14:AE33) -> -5647105.1 | AF34: =SUM(AF14:AF33) -> -5123737.1 | AG34: =SUM(AG14:AG33) -> -6287411.8 | AH34: =SUM(AH14:AH33) -> -5487696.7 | AI34: =SUM(AI14:AI33) -> -6100174.8 | AJ34: =SUM(AJ14:AJ33) -> -2515899.4 | ... BO34: =SUM(BO14:BO33) -> -27343421
B35: 4030100201 Sales Service Flat Rate Variance Labor | C35: 31846.94 | D35: 59663.84 | E35: 44742.37 | F35: 42026.98 | G35: 48183.68 | H35: 43164.95 | I35: 34372.74 | J35: 23829.84 | K35: 57103.92 | L35: 45849.41 | M35: 77523.22 | N35: 77079.18 | O35: =SUBTOTAL(9,C35:N35) -> 585387.07 | P35: 43908.8 | Q35: 119715.77 | R35: 72926.97 | S35: 72185.61 | T35: 108249.35 | U35: 46936.7 | V35: 51600.81 | W35: 64095.13 | X35: 61696.39 | Y35: 39141.78 | Z35: 92582.77 | AA35: 34358.07 | AB35: =SUM(P35:AA35) -> 807398.15 | AC35: 29745.78 | AD35: 55257.16 | AE35: 97014.8 | AF35: 57182.3 | AG35: 56365.7 | AH35: 33655.21 | AI35: 43873.9 | AJ35: 50375.43 | AK35: 28524.41 | AL35: 17681.36 | AM35: 14770.25 | AN35: 27262.83 | AO35: =SUM(AC35:AN35) -> 511709.13 | AP35: 17613.93 | AQ35: 11656.76 | AR35: =VLOOKUP(B35,'[1]Sheet1 (2)'!$B$2:$C$397,2,0) -> 4358.16 | AS35: =VLOOKUP(B35,'[2]Sheet1 (2)'!$B$2:$C$404,2,0) -> -1291.12 | AT35: 10501.78 | AU35: 6588.53 | AV35: 12745.36 | AW35: 15685.59 | AX35: 5873.45 | AY35: 17945.96 | AZ35: 7166.39 | BA35: 6613.86 | BB35: =SUM(AP35:BA35) -> 115458.65 | BC35: 9814.29 | BD35: 12753.37 | BE35: 12154.83 | BF35: 19206.33 | BG35: 11442.95 | BH35: 4610.83 | BI35: 17761.82 | BO35: =SUM(BC35:BN35) -> 87744.42
B36: 4030100203 Sales Service Flat Rate PO | C36: -31894.21 | D36: -22016.68 | E36: -52919.64 | F36: -12641.32 | G36: -21749.51 | H36: -32159.08 | I36: -13967.74 | J36: -15083.77 | K36: -33449.21 | L36: -14500.52 | M36: -6041.52 | N36: -12749.61 | O36: =SUBTOTAL(9,C36:N36) -> -269172.81 | P36: -32874.71 | Q36: -15225.67 | R36: -14717.32 | S36: -13475.84 | T36: -46575.53 | U36: -29545.3 | V36: -38803.51 | W36: -54144.06 | X36: -199400.81 | Y36: -63183.99 | Z36: -338046.03 | AA36: -151714.25 | AB36: =SUM(P36:AA36) -> -997707.02 | AC36: -167937.03 | AD36: -104356.62 | AE36: -265912.97 | AF36: -61026.2 | AG36: -136315.74 | AH36: -76824.56 | AI36: -149562.52 | AJ36: -52157.69 | AK36: -34385.64 | AL36: -105166.07 | AM36: -69384.34 | AN36: -33909.57 | AO36: =SUM(AC36:AN36) -> -1256938.9 | AP36: -50314.69 | AQ36: -47815.94 | AR36: =VLOOKUP(B36,'[1]Sheet1 (2)'!$B$2:$C$397,2,0) -> -39258.93 | AS36: =VLOOKUP(B36,'[2]Sheet1 (2)'!$B$2:$C$404,2,0) -> -20925.3 | AT36: -27564.71 | AU36: -47839.19 | AV36: -20649.18 | AW36: -34252.04 | AX36: -22267.16 | AY36: -30937.03 | AZ36: -6587.03 | BA36: -14850.79 | BB36: =SUM(AP36:BA36) -> -363261.99 | BC36: -31026.23 | BD36: -7204.93 | BE36: -14873.51 | BF36: -12027.55 | BG36: -26250.2 | BH36: -60172.5 | BI36: -18082.59 | BO36: =SUM(BC36:BN36) -> -169637.51
B37: 4030100204 Sales Service Flat Rate Supplies | C37: -17785.87 | D37: -12577.46 | E37: -16307.3 | F37: -15183.13 | G37: -14338.32 | H37: -15619.6 | I37: -15764.43 | J37: -17881 | K37: -77866.97 | L37: -17190.91 | M37: -15926.47 | N37: -134889.41 | O37: =SUBTOTAL(9,C37:N37) -> -371330.87 | P37: -13117.64 | Q37: -20447.88 | R37: -19643.37 | S37: -12209.82 | T37: -16510.9 | U37: -12897.8 | V37: -19330.15 | W37: -15338.58 | X37: -36634.52 | Y37: -20429.06 | Z37: -14100.55 | AA37: -28071.32 | AB37: =SUM(P37:AA37) -> -228731.59 | AC37: -18715.17 | AD37: -19512.62 | AE37: -21918.62 | AF37: -16822.83 | AG37: -23728.14 | AH37: -15665.56 | AI37: -25787.42 | AJ37: -21644.43 | AK37: -19917.19 | AL37: -11046.31 | AM37: -13789.73 | AN37: -23302.83 | AO37: =SUM(AC37:AN37) -> -231850.85 | AP37: -14557.94 | AQ37: -11299.85 | AR37: =VLOOKUP(B37,'[1]Sheet1 (2)'!$B$2:$C$397,2,0) -> -12595.3 | AS37: =VLOOKUP(B37,'[2]Sheet1 (2)'!$B$2:$C$404,2,0) -> -7720.27 | AT37: -14634.66 | AU37: -12810.19 | AV37: -13826.27 | AW37: -23694.38 | AX37: -9042.42 | AY37: -19405.15 | AZ37: -10440.85 | BA37: -8756.01 | BB37: =SUM(AP37:BA37) -> -158783.29 | BC37: -5068.22 | BD37: -6452.22 | BE37: -14078.82 | BF37: -6231.79 | BG37: -27681.16 | BH37: -21935.28 | BI37: -15849.09 | BO37: =SUM(BC37:BN37) -> -97296.58
B38: 4030100207 Sales Service Flat Rate Labor | C38: -222549.26 | D38: -264855.62 | E38: -340217.35 | F38: -309508.72 | G38: -342248.44 | H38: -371958.97 | I38: -316944.91 | J38: -378600.79 | K38: -384713.05 | L38: -351961.85 | M38: -397561.73 | N38: -484740.4 | O38: =SUBTOTAL(9,C38:N38) -> -4165861.1 | P38: -254050.96 | Q38: -505881.88 | R38: -416477.36 | S38: -294969.41 | T38: -451854.31 | U38: -265682.66 | V38: -328291.83 | W38: -277719.49 | X38: -314272.65 | Y38: -421847.53 | Z38: -371903.91 | AA38: -361777.89 | AB38: =SUM(P38:AA38) -> -4264729.9 | AC38: -262742.52 | AD38: -332131.61 | AE38: -457419.5 | AF38: -226187.86 | AG38: -287418.81 | AH38: -254188.41 | AI38: -296017.72 | AJ38: -378888.77 | AK38: -287651.9 | AL38: -303249.7 | AM38: -220361.47 | AN38: -399454.23 | AO38: =SUM(AC38:AN38) -> -3705712.5 | AP38: -173289.42 | AQ38: -144949.05 | AR38: =VLOOKUP(B38,'[1]Sheet1 (2)'!$B$2:$C$397,2,0) -> -189179.68 | AS38: =VLOOKUP(B38,'[2]Sheet1 (2)'!$B$2:$C$404,2,0) -> -101423.86 | AT38: -220243.71 | AU38: -181794.12 | AV38: -303558.69 | AW38: -274893.71 | AX38: -207164.88 | AY38: -291547.89 | AZ38: -229493.8 | BA38: -231282.8 | BB38: =SUM(AP38:BA38) -> -2548821.6 | BC38: -147581.68 | BD38: -239202 | BE38: -196315.47 | BF38: -229059.36 | BG38: -183935.98 | BH38: -162440.51 | BI38: -275285.37 | BO38: =SUM(BC38:BN38) -> -1433820.4
B39: 4030100208 Sales Service Flat Rate Variance Misc. | C39: 4.93 | D39: 10160.01 | E39: 10899.29 | F39: 0.04 | G39: 1117.82 | H39: -1239.7 | I39: 563.53 | J39: 5962.17 | K39: 53302.79 | L39: 1111.79 | M39: -1.32 | N39: -284.93 | O39: =SUBTOTAL(9,C39:N39) -> 81596.42 | P39: 3361.41 | Q39: 2121.98 | R39: 239.53 | S39: 12027.73 | T39: 43039.79 | U39: 14460.91 | V39: 22587.5 | W39: 10505.94 | X39: 10463.01 | Y39: 19702.51 | Z39: 43023.67 | AA39: 10064.88 | AB39: =SUM(P39:AA39) -> 191598.86 | AC39: 13552.41 | AD39: 10832.3 | AE39: 27141.43 | AF39: 3926.67 | AG39: 11785.81 | AH39: 9395.16 | AI39: 10813.85 | AJ39: 3886.53 | AK39: 10050.22 | AL39: 31572.85 | AM39: 21144.88 | AN39: 7033 | AO39: =SUM(AC39:AN39) -> 161135.11 | AP39: 428.17 | AQ39: 211.46 | AR39: =VLOOKUP(B39,'[1]Sheet1 (2)'!$B$2:$C$397,2,0) -> 8038.69 | AS39: =VLOOKUP(B39,'[2]Sheet1 (2)'!$B$2:$C$404,2,0) -> 6940.56 | AT39: 1445.93 | AU39: -465.37 | AV39: -175.39 | AW39: 520.25 | AX39: -1434.56 | AY39: 1250.24 | AZ39: -925.23 | BA39: -2420.47 | BB39: =SUM(AP39:BA39) -> 13414.28 | BC39: -1245.41 | BD39: -1012.49 | BE39: -902.26 | BF39: -1720.5 | BG39: -1202.64 | BH39: -4528.15 | BI39: -412.53 | BO39: =SUM(BC39:BN39) -> -11023.98
B40: 4030500100 Sales Service SOS Lab Analysist | C40: 0 | E40: -228.71 | F40: -22.86 | G40: 0 | H40: -111.83 | I40: -189.38 | J40: -289.61 | K40: -241.25 | L40: -216.55 | M40: -474.22 | N40: -489.2 | O40: =SUBTOTAL(9,C40:N40) -> -2263.61 | P40: -316.02 | Q40: -294.07 | R40: -704.48 | S40: 0 | T40: -335.27 | U40: -486.56 | V40: -708.1 | W40: -419.71 | X40: 0 | Y40: -332.75 | Z40: -133.01 | AA40: -43.89 | AB40: =SUM(P40:AA40) -> -3773.86 | AC40: -22.34 | AD40: -696.85 | AE40: -57.63 | AF40: -437.84 | AG40: -344.59 | AH40: -10.96 | AI40: -57.55 | AJ40: 0 | AK40: 0 | AL40: -93.83 | AM40: -11.23 | AN40: 0 | AO40: =SUM(AC40:AN40) -> -1732.82 | AP40: 0 | AQ40: -202.21 | AR40: =VLOOKUP(B40,'[1]Sheet1 (2)'!$B$2:$C$397,2,0) -> -541.46 | AS40: =VLOOKUP(B40,'[2]Sheet1 (2)'!$B$2:$C$404,2,0) -> -296.63 | AT40: -205.66 | AU40: -120.1 | AV40: -556.87 | AW40: 0 | AX40: -113.59 | AY40: -284.47 | AZ40: -96.25 | BA40: -385.64 | BB40: =SUM(AP40:BA40) -> -2802.88 | BC40: -381.35 | BD40: -378.52 | BE40: -28.11 | BF40: -107.04 | BG40: -109.46 | BH40: -162.09 | BI40: -76.43 | BO40: =SUM(BC40:BN40) -> -1243
B41: 4030500107 Sales Service SOS Lab Actual Discount | BC41: 0 | BD41: 0 | BE41: 0.23 | BF41: 0 | BG41: 0.8 | BH41: 0 | BI41: 0 | BO41: =SUM(BC41:BN41) -> 1.03
B42: 4031500003 IFRS 15 Service SOS Lab | C42: 0 | E42: -142.18 | F42: 0 | G42: 0 | H42: 0 | I42: 0 | J42: 0 | K42: 0 | L42: 0 | M42: 0 | N42: 0 | O42: =SUBTOTAL(9,C42:N42) -> -142.18 | P42: 0 | Q42: 0 | R42: 0 | S42: 0 | T42: 0 | U42: 0 | V42: 0 | W42: 0 | X42: 0 | Y42: 0 | Z42: 0 | AA42: 0 | AB42: =SUM(P42:AA42) -> 0 | AC42: 0 | AD42: 0 | AE42: 0 | AF42: 0 | AG42: 0 | AH42: 0 | AI42: 0 | AJ42: 0 | AK42: 0 | AL42: 0 | AM42: 0 | AN42: 0 | AO42: =SUM(AC42:AN42) -> 0 | AP42: 0 | AQ42: 0 | AR42: 0 | AS42: 0 | AT42: 0 | AU42: 0 | AV42: 0 | AW42: 0 | AX42: 0 | AY42: 0 | AZ42: -1921.06 | BA42: 0 | BB42: =SUM(AP42:BA42) -> -1921.06 | BC42: 0 | BD42: 0 | BE42: 0 | BF42: 0 | BG42: 0 | BH42: 0 | BI42: 0 | BO42: =SUM(BC42:BN42) -> 0
B43: 4031500006 IFRS 15 Product Support Adjustment | C43: 5.01 | D43: 0 | E43: 0 | F43: 0 | G43: 0 | H43: 0 | I43: 0 | J43: 0 | K43: 0 | L43: 0 | M43: 0 | N43: 0 | O43: =SUBTOTAL(9,C43:N43) -> 5.01 | P43: 0 | Q43: 0 | R43: 0 | S43: 0 | T43: 0 | U43: 0 | V43: 0 | W43: 0 | X43: 0 | Y43: 0 | Z43: 0 | AA43: 0 | AB43: =SUM(P43:AA43) -> 0 | AC43: 0 | AD43: 0 | AE43: 0 | AF43: 0 | AG43: 0 | AH43: 0 | AI43: 0 | AJ43: 0 | AK43: 0 | AL43: 0 | AM43: 0 | AN43: 0 | AO43: =SUM(AC43:AN43) -> 0 | AP43: 0 | AQ43: 0 | AR43: 0 | AS43: 0 | AT43: 0 | AU43: 0 | AV43: 0 | AW43: 0 | AX43: 0 | AY43: 0 | AZ43: 0 | BA43: 0 | BB43: =SUM(AP43:BA43) -> 0 | BC43: 0 | BD43: 0 | BE43: 0 | BF43: 0 | BG43: 0 | BH43: 0 | BI43: 0 | BO43: =SUM(BC43:BN43) -> 0
B44: SERVICE | C44: =SUM(C35:C43) -> -240372.46 | D44: =SUM(D35:D43) -> -229625.91 | E44: =SUM(E35:E43) -> -354173.52 | F44: =SUM(F35:F43) -> -295329.01 | G44: =SUM(G35:G43) -> -329034.77 | H44: =SUM(H35:H43) -> -377924.23 | I44: =SUM(I35:I43) -> -311930.19 | J44: =SUM(J35:J43) -> -382063.16 | ... N44: =SUM(N35:N43) -> -556074.37 | O44: =SUM(C44:N44) -> -4141782.1 | P44: =SUM(P35:P43) -> -253089.12 | Q44: =SUM(Q35:Q43) -> -420011.75 | R44: =SUM(R35:R43) -> -378376.03 | S44: =SUM(S35:S43) -> -236441.73 | T44: =SUM(T35:T43) -> -363986.87 | U44: =SUM(U35:U43) -> -247214.71 | V44: =SUM(V35:V43) -> -312945.28 | W44: =SUM(W35:W43) -> -273020.77 | ... BO44: =SUM(BO35:BO43) -> -1625276
B45: 4050000000 Sales RUE Unit | C45: -646517.02 | D45: -497231.19 | E45: -422286.24 | F45: -710397.23 | G45: -622676.49 | H45: -657472.39 | I45: -801128.19 | J45: -819768.26 | K45: -744768.28 | L45: -676705.45 | M45: -636570.28 | N45: -707252.32 | O45: =SUBTOTAL(9,C45:N45) -> -7942773.3 | P45: -682335.86 | Q45: -1007091.2 | R45: -561112.53 | S45: -579084.34 | T45: -956090.15 | U45: -844983.73 | V45: -941176.54 | W45: -905313.58 | X45: -855190.47 | Y45: -769552.89 | Z45: -738836.28 | AA45: -1537494.8 | AB45: =SUM(P45:AA45) -> -10378262 | AC45: -1136676.5 | AD45: -765162.5 | AE45: -739828.37 | AF45: -663639.7 | AG45: -946491.54 | AH45: -1569265.5 | AI45: -1079587.9 | AJ45: -687028.59 | AK45: -610391.36 | AL45: -831287.01 | AM45: -821366.88 | AN45: -711319.55 | AO45: =SUM(AC45:AN45) -> -10562045 | AP45: -909451.37 | AQ45: -742755.76 | AR45: =VLOOKUP(B45,'[1]Sheet1 (2)'!$B$2:$C$397,2,0) -> -666391.56 | AS45: =VLOOKUP(B45,'[2]Sheet1 (2)'!$B$2:$C$404,2,0) -> -690659.01 | AT45: -651199.11 | AU45: -1282941.5 | AV45: -942252.29 | AW45: -1102077.3 | AX45: -665228.84 | AY45: -640175.42 | AZ45: -688599.64 | BA45: -628259.83 | BB45: =SUM(AP45:BA45) -> -9609991.6 | BC45: -825030.16 | BD45: -491556.48 | BE45: -505631.66 | BF45: -505791.15 | BG45: -482511.54 | BH45: -413805.71 | BI45: -482450.9 | BO45: =SUM(BC45:BN45) -> -3706777.6
B46: 4051500000 IFRS 15 Sales RUE Used Equipment | L46: -130731.18 | M46: -229.08 | N46: -236.72 | O46: =SUBTOTAL(9,C46:N46) -> -131196.98 | P46: -236.72 | Q46: -198.54 | R46: 0 | S46: 0 | T46: 0 | U46: 0 | V46: 0 | W46: 0 | X46: 0 | Y46: 0 | Z46: 0 | AA46: -58186.2 | AB46: =SUM(P46:AA46) -> -58621.46 | AC46: 0 | AD46: 0 | AE46: 0 | AF46: 0 | AG46: 0 | AH46: 0 | AI46: 0 | AJ46: 0 | AK46: 0 | AL46: 0 | AM46: 0 | AN46: -51236.07 | AO46: =SUM(AC46:AN46) -> -51236.07 | AP46: 0 | AQ46: 0 | AR46: 0 | AS46: 0 | AT46: 0 | AU46: 0 | AV46: 0 | AW46: 0 | AX46: -77507.59 | AY46: -99.04 | AZ46: 0 | BA46: 0 | BB46: =SUM(AP46:BA46) -> -77606.63 | BC46: 0 | BD46: 0 | BE46: 0 | BF46: 0 | BG46: 0 | BH46: 0 | BI46: 0 | BO46: =SUM(BC46:BN46) -> 0
B47: 4051500100 IFRS 15 Sales RUE Used Equipment Adjustment | L47: 131632.24 | M47: 0 | N47: 0 | O47: =SUBTOTAL(9,C47:N47) -> 131632.24 | P47: 0 | Q47: 0 | R47: 0 | S47: 0 | T47: 0 | U47: 0 | V47: 0 | W47: 0 | X47: 0 | Y47: 0 | Z47: 0 | AA47: 58186.2 | AB47: =SUM(P47:AA47) -> 58186.2 | AC47: 0 | AD47: 0 | AE47: 0 | AF47: 0 | AG47: 0 | AH47: 0 | AI47: 0 | AJ47: 0 | AK47: 0 | AL47: 0 | AM47: 0 | AN47: 51236.07 | AO47: =SUM(AC47:AN47) -> 51236.07 | AP47: 0 | AQ47: 0 | AR47: 0 | AS47: 0 | AT47: 0 | AU47: 0 | AV47: 0 | AW47: 0 | AX47: 77606.63 | AY47: 0 | AZ47: 0 | BA47: 0 | BB47: =SUM(AP47:BA47) -> 77606.63 | BC47: 0 | BD47: 0 | BE47: 0 | BF47: 0 | BG47: 0 | BH47: 0 | BI47: 0 | BO47: =SUM(BC47:BN47) -> 0
B48: RUE | C48: =SUM(C45:C47) -> -646517.02 | D48: =SUM(D45:D47) -> -497231.19 | E48: =SUM(E45:E47) -> -422286.24 | F48: =SUM(F45:F47) -> -710397.23 | G48: =SUM(G45:G47) -> -622676.49 | H48: =SUM(H45:H47) -> -657472.39 | I48: =SUM(I45:I47) -> -801128.19 | J48: =SUM(J45:J47) -> -819768.26 | ... N48: =SUM(N45:N47) -> -707489.04 | O48: =SUM(C48:N48) -> -7942338.1 | P48: =SUM(P45:P47) -> -682572.58 | Q48: =SUM(Q45:Q47) -> -1007289.7 | R48: =SUM(R45:R47) -> -561112.53 | S48: =SUM(S45:S47) -> -579084.34 | T48: =SUM(T45:T47) -> -956090.15 | U48: =SUM(U45:U47) -> -844983.73 | V48: =SUM(V45:V47) -> -941176.54 | W48: =SUM(W45:W47) -> -905313.58 | ... BO48: =SUM(BO45:BO47) -> -3706777.6
B49: 4040000101 Sales MARC Billing | C49: -52009.78 | D49: -28577.48 | E49: -229866.02 | F49: -43904.64 | G49: -25125.12 | H49: -77176.99 | I49: -50082.4 | J49: -98850.02 | K49: -27240.91 | L49: -164113.96 | M49: -72788.11 | N49: -200334.59 | O49: =SUBTOTAL(9,C49:N49) -> -1070070 | P49: -40869.92 | Q49: -46227.78 | R49: -38828.33 | S49: -88183.13 | T49: -76436.14 | U49: -44287.93 | V49: -54220.92 | W49: -104933.64 | X49: -94205.49 | Y49: -63051.05 | Z49: -121631.22 | AA49: -78368.49 | AB49: =SUM(P49:AA49) -> -851244.04 | AC49: -44791.65 | AD49: -135512.77 | AE49: -56898.2 | AF49: -200379.7 | AG49: -42458.76 | AH49: -186147.15 | AI49: -57324.28 | AJ49: -111976.17 | AK49: -18346.81 | AL49: -102416.94 | AM49: -184898.8 | AN49: -42433.72 | AO49: =SUM(AC49:AN49) -> -1183585 | AP49: -20988.88 | AQ49: -43196.46 | AR49: =VLOOKUP(B49,'[1]Sheet1 (2)'!$B$2:$C$397,2,0) -> -35582.21 | AS49: =VLOOKUP(B49,'[2]Sheet1 (2)'!$B$2:$C$404,2,0) -> -106400.55 | AT49: -37199.36 | AU49: -69795.81 | AV49: -267626.28 | AW49: -103854.37 | AX49: -60141.51 | AY49: -70712.86 | AZ49: -142763.39 | BA49: -127339.99 | BB49: =SUM(AP49:BA49) -> -1085601.7 | BC49: -160229.37 | BD49: -45247.13 | BE49: -85074.6 | BF49: -331693.62 | BG49: -25688.67 | BH49: -249536.33 | BI49: -120159.08 | BO49: =SUM(BC49:BN49) -> -1017628.8
B50: MARC | C50: =SUM(C49) -> -52009.78 | D50: =SUM(D49) -> -28577.48 | E50: =SUM(E49) -> -229866.02 | F50: =SUM(F49) -> -43904.64 | G50: =SUM(G49) -> -25125.12 | H50: =SUM(H49) -> -77176.99 | I50: =SUM(I49) -> -50082.4 | J50: =SUM(J49) -> -98850.02 | ... N50: =SUM(N49) -> -200334.59 | O50: =SUM(C50:N50) -> -1070070 | P50: =SUM(P49) -> -40869.92 | Q50: =SUM(Q49) -> -46227.78 | R50: =SUM(R49) -> -38828.33 | S50: =SUM(S49) -> -88183.13 | T50: =SUM(T49) -> -76436.14 | U50: =SUM(U49) -> -44287.93 | V50: =SUM(V49) -> -54220.92 | W50: =SUM(W49) -> -104933.64 | ... BO50: =SUM(BO49) -> -1017628.8
B51: TOTAL REVENUE | C51: =C50+C48+C44+C34+C13 -> -5848421 | D51: =D50+D48+D44+D34+D13 -> -5634735.8 | E51: =E50+E48+E44+E34+E13 -> -6708051.8 | F51: =F50+F48+F44+F34+F13 -> -5969681.8 | G51: =G50+G48+G44+G34+G13 -> -6838537.3 | H51: =H50+H48+H44+H34+H13 -> -8679339.4 | I51: =I50+I48+I44+I34+I13 -> -6657472.2 | J51: =J50+J48+J44+J34+J13 -> -6525780.9 | ... N51: =N50+N48+N44+N34+N13 -> -12509425 | O51: =SUM(C51:N51) -> -96905603 | P51: =P50+P48+P44+P34+P13 -> -9590168.1 | Q51: =Q50+Q48+Q44+Q34+Q13 -> -7908667.9 | R51: =R50+R48+R44+R34+R13 -> -12265205 | S51: =S50+S48+S44+S34+S13 -> -7095671.7 | T51: =T50+T48+T44+T34+T13 -> -9924185 | U51: =U50+U48+U44+U34+U13 -> -8538561.3 | V51: =V50+V48+V44+V34+V13 -> -7420172.4 | W51: =W50+W48+W44+W34+W13 -> -9130037.9 | ... BO51: =BO50+BO48+BO44+BO34+BO13 -> -33830794
B52: 5010000000 COGS PP Unit | C52: 35994.63 | D52: 0 | E52: 0 | F52: 0 | G52: 350.56 | H52: 0 | I52: 0 | J52: 980203.65 | K52: 1351771.9 | L52: 119269.53 | M52: 152016.34 | N52: 433.56 | O52: =SUBTOTAL(9,C52:N52) -> 2640040.2 | P52: 1541010.5 | Q52: 842702.86 | R52: 0 | S52: 83246.28 | T52: 55578.8 | U52: 853.06 | V52: 72816.8 | W52: -91.49 | X52: 87556.58 | Y52: 3024.95 | Z52: 884.48 | AA52: 101309.86 | AB52: =SUM(P52:AA52) -> 2788892.7 | AC52: 9136.03 | AD52: 488.24 | AE52: 30.2 | AF52: 381.89 | AG52: 0 | AH52: 328.98 | AI52: 101612.94 | AJ52: 31852.56 | AK52: 0 | AL52: 68921.71 | AM52: 1235.86 | AN52: 318613.97 | AO52: =SUM(AC52:AN52) -> 532602.38 | AP52: 0 | AQ52: 296685.36 | AR52: =VLOOKUP(B52,'[1]Sheet1 (2)'!$B$2:$C$397,2,0) -> 0 | AS52: =VLOOKUP(B52,'[2]Sheet1 (2)'!$B$2:$C$404,2,0) -> 0 | AT52: 139074.85 | AU52: 35027.44 | AV52: 948.52 | AW52: 0 | AX52: 1351.88 | AY52: 2527.79 | AZ52: 107182.84 | BA52: 47452.97 | BB52: =SUM(AP52:BA52) -> 630251.65 | BC52: 0 | BD52: 400.5 | BE52: 5283.5 | BF52: 97627.57 | BG52: 0 | BH52: 0 | BI52: 0 | BO52: =SUM(BC52:BN52) -> 103311.57
B53: 5010300100 COGS PP Attachment Accessories | J53: 20484.94 | K53: 13784.74 | L53: 0 | M53: 0 | N53: 0 | O53: =SUBTOTAL(9,C53:N53) -> 34269.68 | P53: 19021.95 | Q53: 19350.3 | R53: 0 | S53: 0 | T53: 0 | U53: 0 | V53: 0 | W53: 0 | X53: 8915.43 | Y53: 1407.16 | Z53: 0 | AA53: 0 | AB53: =SUM(P53:AA53) -> 48694.84 | AC53: 0 | AD53: 0 | AE53: 0 | AF53: 0 | AG53: 0 | AH53: 0 | AI53: 0 | AJ53: 0 | AK53: 0 | AL53: 1745.32 | AM53: 0 | AN53: 0 | AO53: =SUM(AC53:AN53) -> 1745.32 | AP53: 0 | AQ53: 8815.14 | AR53: =VLOOKUP(B53,'[1]Sheet1 (2)'!$B$2:$C$397,2,0) -> 0 | AS53: =VLOOKUP(B53,'[2]Sheet1 (2)'!$B$2:$C$404,2,0) -> 0 | AT53: 692.93 | AU53: 243.26 | AV53: 0 | AW53: 0 | AX53: 0 | AY53: 0 | AZ53: 0 | BA53: 60.13 | BB53: =SUM(AP53:BA53) -> 9811.46 | BC53: 0 | BD53: 0 | BE53: 0 | BF53: 1931.77 | BG53: 0 | BH53: 0 | BI53: 0 | BO53: =SUM(BC53:BN53) -> 1931.77
B54: 5010400000 COGS PP Over/Under (COGS After Sales) | AC54: 0 | AD54: 0 | AE54: 0 | AF54: 0 | AG54: 0 | AH54: 0 | AI54: 0 | AJ54: 0 | AK54: 0 | AL54: 0 | AM54: 0 | AN54: 5830 | AO54: =SUM(AC54:AN54) -> 5830 | AP54: 0 | AQ54: 0 | AR54: 0 | AS54: 0 | AT54: 0 | AU54: 0 | AV54: 0 | AW54: -813.72 | AX54: 0 | AY54: 0 | AZ54: 0 | BA54: 0 | BB54: =SUM(AP54:BA54) -> -813.72 | BC54: 0 | BD54: 0 | BE54: 0 | BF54: 0 | BG54: 0 | BH54: 0 | BI54: 0 | BO54: =SUM(BC54:BN54) -> 0
B55: 5010500100 COGS PP Power System Project Core | P55: 0 | Q55: 0 | R55: 0 | S55: 0 | T55: 0 | U55: 0 | V55: 0 | W55: 338700.38 | X55: 109827.94 | Y55: 0 | Z55: 0 | AA55: 624894.64 | AB55: =SUM(P55:AA55) -> 1073423 | AC55: 11894.65 | AD55: 904.78 | AE55: 27478.09 | AF55: 1035.28 | AG55: 0 | AH55: 0 | AI55: 839.82 | AJ55: 0 | AK55: 0 | AL55: 0 | AM55: 0 | AN55: 0 | AO55: =SUM(AC55:AN55) -> 42152.62 | AP55: 0 | AQ55: 1684 | AR55: =VLOOKUP(B55,'[1]Sheet1 (2)'!$B$2:$C$397,2,0) -> 628.29 | AS55: =VLOOKUP(B55,'[2]Sheet1 (2)'!$B$2:$C$404,2,0) -> 0 | AT55: 0 | AU55: 0 | AV55: 0 | AW55: 0 | AX55: 0 | AY55: 0 | AZ55: 0 | BA55: 449416.58 | BB55: =SUM(AP55:BA55) -> 451728.87 | BC55: 0 | BD55: 0 | BE55: 0 | BF55: 0 | BG55: 0 | BH55: 0 | BI55: 0 | BO55: =SUM(BC55:BN55) -> 0
B56: 5010500200 COGS PP Power System Project BOP | AC56: 0 | AD56: 0 | AE56: 0 | AF56: 0 | AG56: 0 | AH56: 0 | AI56: 0 | AJ56: 17049.26 | AK56: 0 | AL56: 0 | AM56: 0 | AN56: 0 | AO56: =SUM(AC56:AN56) -> 17049.26 | AP56: 0 | AQ56: 0 | AR56: 0 | AS56: 0 | AT56: 0 | AU56: 893.97 | AV56: 0 | AW56: 0 | AX56: 0 | AY56: 0 | AZ56: 0 | BA56: 0 | BB56: =SUM(AP56:BA56) -> 893.97 | BC56: 0 | BD56: 5435.76 | BE56: 5450.56 | BF56: 0 | BG56: 0 | BH56: 0 | BI56: 0 | BO56: =SUM(BC56:BN56) -> 10886.32
B57: 5010500300 COGS PP Power System Project Service | P57: 9.6 | Q57: 172.37 | R57: 223.05 | S57: 0 | T57: 0 | U57: 0 | V57: 0 | W57: 0 | X57: 0 | Y57: 0 | Z57: 0 | AA57: 0 | AB57: =SUM(P57:AA57) -> 405.02 | AC57: 0 | AD57: 0 | AE57: 0 | AF57: 260.71 | AG57: 337.01 | AH57: 89.33 | AI57: 234.57 | AJ57: 140.68 | AK57: 47.93 | AL57: 394.19 | AM57: 236.44 | AN57: 481.8 | AO57: =SUM(AC57:AN57) -> 2222.66 | AP57: 0 | AQ57: 74.98 | AR57: =VLOOKUP(B57,'[1]Sheet1 (2)'!$B$2:$C$397,2,0) -> 521.2 | AS57: =VLOOKUP(B57,'[2]Sheet1 (2)'!$B$2:$C$404,2,0) -> 823.1 | AT57: 716.89 | AU57: 83.57 | AV57: 0 | AW57: 0 | AX57: 806.87 | AY57: 2.01 | AZ57: 0 | BA57: 0 | BB57: =SUM(AP57:BA57) -> 3028.62 | BC57: 0 | BD57: 0 | BE57: 0 | BF57: 0 | BG57: 0 | BH57: 110.87 | BI57: 111.64 | BO57: =SUM(BC57:BN57) -> 222.51
B58: 5010600000 COGS PP Attachment | C58: 0 | D58: 70.9 | E58: 0 | F58: 0 | G58: 0 | H58: 0 | I58: 0 | J58: 0 | K58: 0 | L58: 0 | M58: 3506.84 | N58: 0 | O58: =SUBTOTAL(9,C58:N58) -> 3577.74 | P58: 0 | Q58: 2074.29 | R58: 3550.86 | S58: 0 | T58: 0 | U58: 0 | V58: 0 | W58: 668982.08 | X58: 1537.05 | Y58: 1987722.8 | Z58: 1194523.8 | AA58: 1590000 | AB58: =SUM(P58:AA58) -> 5448390.8 | AC58: 0 | AD58: 1523.46 | AE58: 0 | AF58: 0 | AG58: 0 | AH58: 768.18 | AI58: 0 | AJ58: 0 | AK58: 18096.5 | AL58: 0 | AM58: 811117.34 | AN58: 1621979.2 | AO58: =SUM(AC58:AN58) -> 2453484.6 | AP58: 379.27 | AQ58: 0 | AR58: =VLOOKUP(B58,'[1]Sheet1 (2)'!$B$2:$C$397,2,0) -> 204399.29 | AS58: =VLOOKUP(B58,'[2]Sheet1 (2)'!$B$2:$C$404,2,0) -> -404475.35 | AT58: 0 | AU58: 0 | AV58: 0 | AW58: 0 | AX58: 0 | AY58: 0 | AZ58: 15835.59 | BA58: 0 | BB58: =SUM(AP58:BA58) -> -183861.2 | BC58: 0 | BD58: 0 | BE58: 188.45 | BF58: 172.3 | BG58: 0 | BH58: 0 | BI58: 0 | BO58: =SUM(BC58:BN58) -> 360.75
B59: 5011001000 COGS PP International Freight Inbound | C59: 1700 | D59: 0 | E59: 0 | F59: 0 | G59: 0 | H59: 0 | I59: 0 | J59: 57103 | K59: 73816 | L59: 9281.78 | M59: 5099.18 | N59: 3986.78 | O59: =SUBTOTAL(9,C59:N59) -> 150986.74 | P59: 47559 | Q59: 54892 | R59: 0 | S59: 1532.62 | T59: 1041.67 | U59: 0 | V59: 927.86 | W59: 24772.3 | X59: 3090 | Y59: 59159.95 | Z59: 38210.58 | AA59: 56496.65 | AB59: =SUM(P59:AA59) -> 287682.63 | AC59: 1960 | AD59: 0 | AE59: 0 | AF59: 0 | AG59: 0 | AH59: 0 | AI59: 1827.43 | AJ59: 456.74 | AK59: 0 | AL59: 630 | AM59: 23332.82 | AN59: 49647.22 | AO59: =SUM(AC59:AN59) -> 77854.21 | AP59: 0 | AQ59: 5500 | AR59: =VLOOKUP(B59,'[1]Sheet1 (2)'!$B$2:$C$397,2,0) -> 0 | AS59: =VLOOKUP(B59,'[2]Sheet1 (2)'!$B$2:$C$404,2,0) -> 0 | AT59: 5523.07 | AU59: 456.74 | AV59: 0 | AW59: 0 | AX59: 0 | AY59: 0 | AZ59: 420.67 | BA59: 553.33 | BB59: =SUM(AP59:BA59) -> 12453.81 | BC59: 0 | BD59: 0 | BE59: 0 | BF59: 5779.8 | BG59: 0 | BH59: 0 | BI59: 0 | BO59: =SUM(BC59:BN59) -> 5779.8
B60: 5011002000 COGS PP Local Freight/Handling Inbound | C60: 687.98 | D60: 525.58 | E60: 0 | F60: 45.95 | G60: 0 | H60: 0 | I60: 0 | J60: 0 | K60: 9664.24 | L60: 1437.08 | M60: 11.52 | N60: 1273.67 | O60: =SUBTOTAL(9,C60:N60) -> 13646.02 | P60: 3187.83 | Q60: 3481.55 | R60: 42.12 | S60: 3841.3 | T60: 228.58 | U60: 98.96 | V60: 88.27 | W60: 4730 | X60: 1272.69 | Y60: 670.92 | Z60: 25066.35 | AA60: 13516.44 | AB60: =SUM(P60:AA60) -> 56225.01 | AC60: 51.15 | AD60: 1570.57 | AE60: 8.39 | AF60: 0 | AG60: 0 | AH60: 0 | AI60: 438.11 | AJ60: 198.83 | AK60: 0 | AL60: 0 | AM60: 410.73 | AN60: 1563.1 | AO60: =SUM(AC60:AN60) -> 4240.88 | AP60: 4276.74 | AQ60: 7362.82 | AR60: =VLOOKUP(B60,'[1]Sheet1 (2)'!$B$2:$C$397,2,0) -> 762.75 | AS60: =VLOOKUP(B60,'[2]Sheet1 (2)'!$B$2:$C$404,2,0) -> 1013.57 | AT60: 1655.52 | AU60: 128.33 | AV60: 49.14 | AW60: 308.86 | AX60: 0 | AY60: 0 | AZ60: 358.47 | BA60: 350.88 | BB60: =SUM(AP60:BA60) -> 16267.08 | BC60: 282.04 | BD60: 0 | BE60: 0 | BF60: 1557.33 | BG60: 0 | BH60: 0 | BI60: 0 | BO60: =SUM(BC60:BN60) -> 1839.37
B61: 5011003000 COGS PP Custom Duty | C61: 3744.15 | D61: 0 | E61: 0 | F61: 0 | G61: 0 | H61: 0 | I61: 0 | J61: 0 | K61: 98743.4 | L61: 7936.13 | M61: 45659.03 | N61: -18439.42 | O61: =SUBTOTAL(9,C61:N61) -> 137643.29 | P61: 158521.4 | Q61: 0 | R61: 0 | S61: 0 | T61: 5391.07 | U61: 0 | V61: 7088.11 | W61: 71103.18 | X61: 0 | Y61: 101827.7 | Z61: 61124.07 | AA61: 91996.67 | AB61: =SUM(P61:AA61) -> 497052.2 | AC61: 0 | AD61: 0 | AE61: 0 | AF61: 0 | AG61: 0 | AH61: 0 | AI61: 10128.67 | AJ61: 3068.76 | AK61: 0 | AL61: 3325.98 | AM61: 41711.7 | AN61: 93087.27 | AO61: =SUM(AC61:AN61) -> 151322.38 | AP61: 0 | AQ61: 26550.04 | AR61: =VLOOKUP(B61,'[1]Sheet1 (2)'!$B$2:$C$397,2,0) -> 0 | AS61: =VLOOKUP(B61,'[2]Sheet1 (2)'!$B$2:$C$404,2,0) -> 0 | AT61: 0 | AU61: 0 | AV61: 0 | AW61: 0 | AX61: 0 | AY61: 0 | AZ61: 5308.78 | BA61: 0 | BB61: =SUM(AP61:BA61) -> 31858.82 | BC61: 0 | BD61: 0 | BE61: 0 | BF61: 10330.39 | BG61: 0 | BH61: 0 | BI61: 0 | BO61: =SUM(BC61:BN61) -> 10330.39
B62: 5011004000 COGS PP UPA | C62: 0 | D62: 107.78 | E62: 0 | F62: 0 | G62: 52.94 | H62: 0 | I62: 0 | J62: 0 | K62: 114.94 | L62: 24669.54 | M62: 29657.93 | N62: 0 | O62: =SUBTOTAL(9,C62:N62) -> 54603.13 | P62: 7048.96 | Q62: 856.47 | R62: 0 | S62: 117.91 | T62: 118.04 | U62: 0 | V62: 229.32 | W62: 0 | X62: 284.9 | Y62: 0 | Z62: 0 | AA62: 224.52 | AB62: =SUM(P62:AA62) -> 8880.12 | AC62: 0 | AD62: 0 | AE62: 0 | AF62: 0 | AG62: 0 | AH62: 0 | AI62: 106.3 | AJ62: 106.9 | AK62: 0 | AL62: 220.36 | AM62: 0 | AN62: 323.64 | AO62: =SUM(AC62:AN62) -> 757.2 | AP62: 0 | AQ62: 241.95 | AR62: =VLOOKUP(B62,'[1]Sheet1 (2)'!$B$2:$C$397,2,0) -> 0 | AS62: =VLOOKUP(B62,'[2]Sheet1 (2)'!$B$2:$C$404,2,0) -> 0 | AT62: 146.88 | AU62: 106.83 | AV62: 0 | AW62: 0 | AX62: 0 | AY62: 0 | AZ62: 104.19 | BA62: 130.73 | BB62: =SUM(AP62:BA62) -> 730.58 | BC62: 0 | BD62: 0 | BE62: 0 | BF62: 124.69 | BG62: 0 | BH62: 0 | BI62: 0 | BO62: =SUM(BC62:BN62) -> 124.69
B63: 5011006000 COGS PP Insurance | C63: 54.02 | D63: 0 | E63: 0 | F63: 0 | G63: 0 | H63: 0 | I63: 0 | J63: 1178.8 | K63: 1817.66 | L63: 134.85 | M63: 219.63 | N63: 0 | O63: =SUBTOTAL(9,C63:N63) -> 3404.96 | P63: 1215.74 | Q63: 1253.93 | R63: 0 | S63: 135.73 | T63: 72.98 | U63: 0 | V63: 115.76 | W63: 1068.38 | X63: 67.46 | Y63: 2131.05 | Z63: 1289.98 | AA63: 1855.28 | AB63: =SUM(P63:AA63) -> 9206.29 | AC63: 0 | AD63: 0 | AE63: 0 | AF63: 0 | AG63: 0 | AH63: 0 | AI63: 57.32 | AJ63: 49.1 | AK63: 15.67 | AL63: 34.05 | AM63: 445.7 | AN63: 1047.89 | AO63: =SUM(AC63:AN63) -> 1649.73 | AP63: 0 | AQ63: 133.6 | AR63: =VLOOKUP(B63,'[1]Sheet1 (2)'!$B$2:$C$397,2,0) -> 0 | AS63: =VLOOKUP(B63,'[2]Sheet1 (2)'!$B$2:$C$404,2,0) -> 0 | AT63: 74.48 | AU63: 47.62 | AV63: 0 | AW63: 0 | AX63: 0 | AY63: 0 | AZ63: 58.77 | BA63: 16.76 | BB63: =SUM(AP63:BA63) -> 331.23 | BC63: 0 | BD63: 0 | BE63: 0 | BF63: 46.09 | BG63: 0 | BH63: 0 | BI63: 0 | BO63: =SUM(BC63:BN63) -> 46.09
B64: 5011007000 COGS PP Commissioning | C64: 0 | D64: 178.04 | E64: 98.79 | F64: 429.79 | G64: 0 | H64: 0 | I64: 0 | J64: 0 | K64: 127.32 | L64: 0 | M64: 68.8 | N64: 142.36 | O64: =SUBTOTAL(9,C64:N64) -> 1045.1 | P64: 0 | Q64: 0 | R64: 923.16 | S64: 39.68 | T64: 406.2 | U64: 0 | V64: 0 | W64: 1953.47 | X64: 665.96 | Y64: 517.02 | Z64: 3333.25 | AA64: 553.52 | AB64: =SUM(P64:AA64) -> 8392.26 | AC64: 145.99 | AD64: 1467.78 | AE64: 721.67 | AF64: 2153.81 | AG64: 1105.97 | AH64: 0 | AI64: 1821.98 | AJ64: 0 | AK64: 0 | AL64: 1444.04 | AM64: 830.17 | AN64: 1121.07 | AO64: =SUM(AC64:AN64) -> 10812.48 | AP64: 367.04 | AQ64: 2594.45 | AR64: =VLOOKUP(B64,'[1]Sheet1 (2)'!$B$2:$C$397,2,0) -> 253.73 | AS64: =VLOOKUP(B64,'[2]Sheet1 (2)'!$B$2:$C$404,2,0) -> 1533.89 | AT64: 1171.1 | AU64: 965.95 | AV64: 289.25 | AW64: 0 | AX64: 227.8 | AY64: 0 | AZ64: 192.35 | BA64: 218.01 | BB64: =SUM(AP64:BA64) -> 7813.57 | BC64: 156.83 | BD64: 880.94 | BE64: 0 | BF64: 123 | BG64: 0 | BH64: 143.84 | BI64: 0 | BO64: =SUM(BC64:BN64) -> 1304.61
B65: 5011008000 COGS PP Warranty | C65: 270.11 | D65: -763.87 | E65: -600.11 | F65: 0 | G65: 4.39 | H65: -26.47 | I65: -14.95 | J65: 6987.38 | K65: 9040.09 | L65: 539.4 | M65: 1098.17 | N65: 273.49 | O65: =SUBTOTAL(9,C65:N65) -> 16807.63 | P65: 7361.19 | Q65: 4225.25 | R65: -740.59 | S65: 545.82 | T65: 291.91 | U65: 0 | V65: 578.78 | W65: -2259.31 | X65: -1376.16 | Y65: 16343.28 | Z65: 9372.63 | AA65: 12233.39 | AB65: =SUM(P65:AA65) -> 46576.19 | AC65: 1590.64 | AD65: -1620 | AE65: 0 | AF65: 0 | AG65: 0 | AH65: 0 | AI65: 573.23 | AJ65: 196.41 | AK65: 195.92 | AL65: 425.56 | AM65: 5516.79 | AN65: -22067.48 | AO65: =SUM(AC65:AN65) -> -15188.93 | AP65: 2017.57 | AQ65: 1670.05 | AR65: =VLOOKUP(B65,'[1]Sheet1 (2)'!$B$2:$C$397,2,0) -> -20339.1 | AS65: =VLOOKUP(B65,'[2]Sheet1 (2)'!$B$2:$C$404,2,0) -> 0 | AT65: 930.97 | AU65: -352.44 | AV65: -192.88 | AW65: 0 | AX65: 0 | AY65: -941.69 | AZ65: -821.52 | BA65: 209.47 | BB65: =SUM(AP65:BA65) -> -17819.57 | BC65: -578.78 | BD65: -601.37 | BE65: -380.11 | BF65: 576.16 | BG65: 0 | BH65: -408.45 | BI65: 0 | BO65: =SUM(BC65:BN65) -> -1392.55
B66: 5011009000 COGS PP Miscellaneous | P66: 0 | Q66: 0 | R66: 0 | S66: 0 | T66: 0 | U66: 0 | V66: 0 | X66: 10001.47 | Y66: 0 | Z66: 0 | AA66: 0 | AB66: =SUM(P66:AA66) -> 10001.47 | AC66: 0 | AD66: 0 | AE66: 0 | AF66: 0 | AG66: 0 | AH66: 0 | AI66: 0 | AJ66: 0 | AK66: 0 | AL66: 0 | AM66: 0 | AN66: 0 | AO66: =SUM(AC66:AN66) -> 0 | AP66: 0 | AQ66: 0 | AR66: 0 | AS66: 0 | AT66: 0 | AU66: 0 | AV66: 0 | AW66: 0 | AX66: 0 | AY66: 0 | AZ66: 0 | BA66: 0 | BB66: =SUM(AP66:BA66) -> 0 | BC66: 0 | BD66: 0 | BE66: 0 | BF66: 0 | BG66: 0 | BH66: 0 | BI66: 0 | BO66: =SUM(BC66:BN66) -> 0
B67: 5011010000 COGS PP Local Freight/Handling Outbound | C67: 1027.45 | D67: 784.14 | E67: 0 | F67: 45.95 | G67: 0 | H67: 0 | I67: 0 | J67: 0 | K67: 20233.95 | L67: 444.86 | M67: 18615.6 | N67: 1666.56 | O67: =SUBTOTAL(9,C67:N67) -> 42818.51 | P67: 4835.87 | Q67: 3506.91 | R67: 1336.04 | S67: 332.92 | T67: 263.66 | U67: 0 | V67: 532.42 | W67: 5798.84 | X67: 1728.29 | Y67: 13927.44 | Z67: 9973.03 | AA67: 13017.82 | AB67: =SUM(P67:AA67) -> 55253.24 | AC67: 2559.18 | AD67: 0 | AE67: 0 | AF67: 0 | AG67: 0 | AH67: 0 | AI67: 129.84 | AJ67: 89.25 | AK67: 1230.01 | AL67: 1051.59 | AM67: 1432.1 | AN67: 16548.03 | AO67: =SUM(AC67:AN67) -> 23040 | AP67: 740.82 | AQ67: 5988.77 | AR67: =VLOOKUP(B67,'[1]Sheet1 (2)'!$B$2:$C$397,2,0) -> 16.82 | AS67: =VLOOKUP(B67,'[2]Sheet1 (2)'!$B$2:$C$404,2,0) -> 0 | AT67: 2554.32 | AU67: 170.74 | AV67: 0 | AW67: 0 | AX67: 0 | AY67: 0 | AZ67: 0 | BA67: 1584.32 | BB67: =SUM(AP67:BA67) -> 11055.79 | BC67: -526.22 | BD67: 0 | BE67: 0 | BF67: 952.49 | BG67: 1268.03 | BH67: 0 | BI67: 0 | BO67: =SUM(BC67:BN67) -> 1694.3
B68: 5011012000 COGS PP CAT Discount | P68: -653147.53 | Q68: 0 | R68: 63087.53 | S68: 0 | T68: 0 | U68: 0 | V68: 0 | W68: 0 | X68: -9923.62 | Y68: -325880.3 | Z68: -198716.11 | AA68: -266924 | AB68: =SUM(P68:AA68) -> -1391504 | AC68: -10179.53 | AD68: 0 | AE68: 0 | AF68: 0 | AG68: 0 | AH68: 0 | AI68: 0 | AJ68: 0 | AK68: 0 | AL68: -6160.67 | AM68: -130622.37 | AN68: -266108.82 | AO68: =SUM(AC68:AN68) -> -413071.39 | AP68: -3399.2 | AQ68: 0 | AR68: =VLOOKUP(B68,'[1]Sheet1 (2)'!$B$2:$C$397,2,0) -> -4451.44 | AS68: =VLOOKUP(B68,'[2]Sheet1 (2)'!$B$2:$C$404,2,0) -> -4451.9 | AT68: 0 | AU68: 0 | AV68: 0 | AW68: 0 | AX68: 0 | AY68: 0 | AZ68: 0 | BA68: -11168.52 | BB68: =SUM(AP68:BA68) -> -23471.06 | BC68: -332.91 | BD68: 0 | BE68: 0 | BF68: -3887.6 | BG68: 0 | BH68: -361.14 | BI68: 0 | BO68: =SUM(BC68:BN68) -> -4581.65
B69: 5011015000 COGS PP Marketing Program EPP | J69: 34962.43 | K69: 10624.89 | L69: 0 | M69: 0 | N69: 0 | O69: =SUBTOTAL(9,C69:N69) -> 45587.32 | P69: 11650 | Q69: 11650 | R69: -84.89 | S69: -30832.43 | T69: 0 | U69: 0 | V69: 0 | W69: 0 | X69: 0 | Y69: 0 | Z69: 0 | AA69: 0 | AB69: =SUM(P69:AA69) -> -7617.32 | AC69: 0 | AD69: 0 | AE69: 0 | AF69: 0 | AG69: 0 | AH69: 0 | AI69: 0 | AJ69: 0 | AK69: 0 | AL69: 0 | AM69: 0 | AN69: 0 | AO69: =SUM(AC69:AN69) -> 0 | AP69: 0 | AQ69: 0 | AR69: 0 | AS69: 0 | AT69: 0 | AU69: 0 | AV69: 0 | AW69: 0 | AX69: 0 | AY69: 0 | AZ69: 0 | BA69: 0 | BB69: =SUM(AP69:BA69) -> 0 | BC69: 0 | BD69: 0 | BE69: 0 | BF69: 0 | BG69: 0 | BH69: 0 | BI69: 0 | BO69: =SUM(BC69:BN69) -> 0
B70: 5011500001 IFRS 15 COGS EPP - Prime Product | K70: -10624.89 | L70: 0 | M70: 0 | N70: 0 | O70: =SUBTOTAL(9,C70:N70) -> -10624.89 | P70: 0 | Q70: 0 | R70: 0 | S70: 0 | T70: 0 | U70: 0 | V70: 0 | W70: 0 | X70: 725.74 | Y70: 899.93 | Z70: 870.89 | AA70: 899.92 | AB70: =SUM(P70:AA70) -> 3396.48 | AC70: 899.92 | AD70: 841.87 | AE70: 899.92 | AF70: 870.89 | AG70: 899.92 | AH70: 870.9 | AI70: 899.92 | AJ70: 899.92 | AK70: 145.15 | AL70: 0 | AM70: 0 | AN70: 0 | AO70: =SUM(AC70:AN70) -> 7228.41 | AP70: 0 | AQ70: 0 | AR70: 0 | AS70: 0 | AT70: 0 | AU70: 0 | AV70: 0 | AW70: 0 | AX70: 0 | AY70: 0 | AZ70: 0 | BA70: 0 | BB70: =SUM(AP70:BA70) -> 0 | BC70: 0 | BD70: 0 | BE70: 0 | BF70: 0 | BG70: 0 | BH70: 0 | BI70: 0 | BO70: =SUM(BC70:BN70) -> 0
B71: 5011014000 COGS PP Marketing Program Preventive Maintenance | AP71: 0 | AQ71: 0 | AR71: =VLOOKUP(B71,'[1]Sheet1 (2)'!$B$2:$C$397,2,0) -> -69.14 | AS71: =VLOOKUP(B71,'[2]Sheet1 (2)'!$B$2:$C$404,2,0) -> 0 | AT71: 0 | AU71: 0 | AV71: 0 | AW71: 0 | AX71: 0 | AY71: 0 | AZ71: 0 | BA71: 0 | BB71: =SUM(AP71:BA71) -> -69.14 | BC71: 0 | BD71: 0 | BE71: 0 | BF71: 0 | BG71: -20.18 | BH71: 0 | BI71: -16.08 | BO71: =SUM(BC71:BN71) -> -36.26
B72: 5012000000 COGS PP Unit Estimated | C72: 611.7 | D72: -1606.06 | E72: 0 | F72: 0 | G72: -350.56 | H72: 0 | I72: 0 | J72: -14.44 | K72: 12245.84 | L72: -22.56 | M72: 2280.41 | N72: -36688.82 | O72: =SUBTOTAL(9,C72:N72) -> -23544.49 | P72: 150.68 | Q72: -2299.41 | R72: -566.78 | S72: 0 | T72: 23914.94 | U72: 0 | V72: 812 | W72: 15597.92 | X72: -13789.92 | Y72: 0 | Z72: -2620 | AA72: 0 | AB72: =SUM(P72:AA72) -> 21199.43 | AC72: 0 | AD72: -2314.94 | AE72: 0 | AF72: 0 | AG72: 2717.14 | AH72: 0 | AI72: 5521.47 | AJ72: 0 | AK72: 0 | AL72: -5306.2 | AM72: 175.81 | AN72: 13767.48 | AO72: =SUM(AC72:AN72) -> 14560.76 | AP72: 0 | AQ72: -391.08 | AR72: =VLOOKUP(B72,'[1]Sheet1 (2)'!$B$2:$C$397,2,0) -> -13767.48 | AS72: =VLOOKUP(B72,'[2]Sheet1 (2)'!$B$2:$C$404,2,0) -> 0 | AT72: 0 | AU72: 0 | AV72: 0 | AW72: 0 | AX72: 0 | AY72: 0 | AZ72: 3000 | BA72: 190.42 | BB72: =SUM(AP72:BA72) -> -10968.14 | BC72: 0 | BD72: -3000 | BE72: -190.42 | BF72: 0 | BG72: 0 | BH72: 0 | BI72: 0 | BO72: =SUM(BC72:BN72) -> -3190.42
B73: 5012001000 COGS PP International Freight Inbound Estimated | C73: 0 | D73: -6177.34 | E73: 4203 | F73: 0 | G73: 0 | H73: 0 | I73: 0 | J73: 0 | K73: 0.37 | L73: 3881.45 | M73: -1649.46 | N73: -9975.97 | O73: =SUBTOTAL(9,C73:N73) -> -9717.95 | P73: -55.88 | Q73: 0 | R73: 0 | S73: 0 | T73: 7799.49 | U73: 0 | V73: 0 | W73: 2620 | X73: 0 | Y73: 0 | Z73: -2620 | AA73: 0 | AB73: =SUM(P73:AA73) -> 7743.61 | AC73: 0 | AD73: -680.93 | AE73: 0 | AF73: 0 | AG73: 680.93 | AH73: 0 | AI73: 0 | AJ73: 0 | AK73: 375 | AL73: 0 | AM73: 0 | AN73: -375 | AO73: =SUM(AC73:AN73) -> 0 | AP73: 0 | AQ73: 0 | AR73: 0 | AS73: 0 | AT73: 0 | AU73: 0 | AV73: 0 | AW73: 0 | AX73: 0 | AY73: 0 | AZ73: 0 | BA73: 0 | BB73: =SUM(AP73:BA73) -> 0 | BC73: 0 | BD73: 0 | BE73: 0 | BF73: 0 | BG73: 0 | BH73: 0 | BI73: 0 | BO73: =SUM(BC73:BN73) -> 0
B74: 5012002000 COGS PP Local Freight/Handling Inbound Estimated | C74: -195.89 | D74: -4888.6 | E74: 3833.02 | F74: 0 | G74: 0 | H74: 0 | I74: 0 | J74: 10257.33 | K74: 1088.86 | L74: 1310.32 | M74: -6675.3 | N74: -4307.7 | O74: =SUBTOTAL(9,C74:N74) -> 422.04 | P74: 10059.7 | Q74: 3097.83 | R74: 0 | S74: -10363.01 | T74: -3346.61 | U74: -98.96 | V74: 458.62 | W74: 2000.62 | X74: 6.19 | Y74: 19656.57 | Z74: -15468.48 | AA74: 4094.1 | AB74: =SUM(P74:AA74) -> 10096.57 | AC74: -5641.55 | AD74: -2245.98 | AE74: -4492.58 | AF74: 0 | AG74: 610.03 | AH74: 0 | AI74: 0 | AJ74: 0 | AK74: 180.97 | AL74: 399.13 | AM74: 8034.4 | AN74: 16190.05 | AO74: =SUM(AC74:AN74) -> 13034.47 | AP74: -4354.33 | AQ74: -10611.43 | AR74: =VLOOKUP(B74,'[1]Sheet1 (2)'!$B$2:$C$397,2,0) -> -9420.34 | AS74: =VLOOKUP(B74,'[2]Sheet1 (2)'!$B$2:$C$404,2,0) -> -418.45 | AT74: 0 | AU74: 0 | AV74: 0 | AW74: 0 | AX74: 0 | AY74: 0 | AZ74: 0 | BA74: 78.84 | BB74: =SUM(AP74:BA74) -> -24725.71 | BC74: -21.31 | BD74: 0 | BE74: -57.53 | BF74: 20.91 | BG74: 0 | BH74: 0 | BI74: -20.91 | BO74: =SUM(BC74:BN74) -> -78.84
B75: 5012003000 COGS PP Custom Duty Estimated | C75: 0 | D75: -60.88 | E75: 0 | F75: 0 | G75: 0 | H75: 0 | I75: 0 | J75: 0 | K75: 145.35 | L75: 13081.47 | M75: -13081.47 | N75: 3273.48 | O75: =SUBTOTAL(9,C75:N75) -> 3357.95 | P75: -4085.23 | Q75: 89369.76 | R75: 0 | S75: 12763.59 | T75: -88703.36 | U75: 0 | V75: -12395.6 | W75: 13.86 | X75: 0 | Y75: 137.31 | Z75: 397.59 | AA75: 230.82 | AB75: =SUM(P75:AA75) -> -2271.26 | AC75: -505.3 | AD75: -1731.71 | AE75: -230.82 | AF75: 0 | AG75: 1320.26 | AH75: 0 | AI75: 0 | AJ75: 0 | AK75: 925.65 | AL75: 151.61 | AM75: 0 | AN75: 19916.1 | AO75: =SUM(AC75:AN75) -> 19845.79 | AP75: -151.61 | AQ75: 0 | AR75: =VLOOKUP(B75,'[1]Sheet1 (2)'!$B$2:$C$397,2,0) -> -20841.75 | AS75: =VLOOKUP(B75,'[2]Sheet1 (2)'!$B$2:$C$404,2,0) -> 0 | AT75: 0 | AU75: 3960.93 | AV75: 0 | AW75: 0 | AX75: -3960.93 | AY75: 0 | AZ75: 0 | BA75: 0 | BB75: =SUM(AP75:BA75) -> -20993.36 | BC75: 0 | BD75: 0 | BE75: 0 | BF75: 0 | BG75: 0 | BH75: 0 | BI75: 0 | BO75: =SUM(BC75:BN75) -> 0
B76: 5012004000 COGS PP UPA Estimated | C76: 199.48 | D76: -66621.41 | E76: 65998.67 | F76: 0 | G76: -52.94 | H76: 0 | I76: 0 | J76: 63000 | K76: 2718.68 | L76: -24557.69 | M76: -38580.71 | N76: -3187.79 | O76: =SUBTOTAL(9,C76:N76) -> -1083.71 | P76: 0 | Q76: 0 | R76: 0 | S76: 0 | T76: 1507.09 | U76: 0 | V76: 1.4 | W76: 2000 | X76: 3.4 | Y76: -1.4 | Z76: -2003.4 | AA76: 135.48 | AB76: =SUM(P76:AA76) -> 1642.57 | AC76: 0 | AD76: -580 | AE76: -135.48 | AF76: 0 | AG76: 580 | AH76: 0 | AI76: 0 | AJ76: 0 | AK76: 776.7 | AL76: 0 | AM76: 0 | AN76: -776.7 | AO76: =SUM(AC76:AN76) -> -135.48 | AP76: 0 | AQ76: 0 | AR76: 0 | AS76: 0 | AT76: 0 | AU76: 0 | AV76: 0 | AW76: 0 | AX76: 0 | AY76: 0 | AZ76: 0.11 | BA76: 0.57 | BB76: =SUM(AP76:BA76) -> 0.68 | BC76: 0 | BD76: -0.11 | BE76: -0.57 | BF76: 0 | BG76: 0 | BH76: 0 | BI76: 0 | BO76: =SUM(BC76:BN76) -> -0.68
B77: 5012007000 COGS PP Commissioning Estimated | C77: 1000 | D77: -2955.09 | E77: 0 | F77: 0 | G77: 0 | H77: 2970.7 | I77: -2970.7 | J77: 0 | K77: 1128.68 | L77: 1256 | M77: 1931.2 | N77: -1205.81 | O77: =SUBTOTAL(9,C77:N77) -> 1154.98 | P77: -78.59 | Q77: 284.4 | R77: -0.29 | S77: 1216.32 | T77: 849.8 | U77: 0 | V77: 2512 | W77: -1216.32 | X77: -327.64 | Y77: 0 | Z77: 0 | AA77: 112.37 | AB77: =SUM(P77:AA77) -> 3352.05 | AC77: -430.1 | AD77: -3139.13 | AE77: 0 | AF77: 0 | AG77: 0 | AH77: 0 | AI77: 716.68 | AJ77: 733.84 | AK77: 0 | AL77: -2512 | AM77: 0 | AN77: 2984.37 | AO77: =SUM(AC77:AN77) -> -1646.34 | AP77: -240.62 | AQ77: -448.65 | AR77: =VLOOKUP(B77,'[1]Sheet1 (2)'!$B$2:$C$397,2,0) -> -931.13 | AS77: =VLOOKUP(B77,'[2]Sheet1 (2)'!$B$2:$C$404,2,0) -> 0 | AT77: 0 | AU77: 713.56 | AV77: 0 | AW77: 0 | AX77: 0 | AY77: -446.01 | AZ77: -78.15 | BA77: -218.01 | BB77: =SUM(AP77:BA77) -> -1649.01 | BC77: 0 | BD77: 0 | BE77: -2571.13 | BF77: -123 | BG77: 0 | BH77: 0 | BI77: 0 | BO77: =SUM(BC77:BN77) -> -2694.13
B78: 5012010000 COGS PP Local Freight/Handling Outbond Estimated | C78: 536.68 | D78: -992.38 | E78: 0 | F78: 0 | G78: 0 | H78: 0 | I78: 0 | J78: 30286.71 | K78: 8529.23 | L78: 1160.48 | M78: -30232.67 | N78: -9359.49 | O78: =SUBTOTAL(9,C78:N78) -> -71.44 | P78: -514.86 | Q78: 406.78 | R78: -460.82 | S78: 255.34 | T78: -62.39 | U78: 0 | V78: -126.11 | W78: 1806.06 | X78: -1872.9 | Y78: 4839.91 | Z78: 1339.73 | AA78: 5664.2 | AB78: =SUM(P78:AA78) -> 11274.94 | AC78: -6806.31 | AD78: -1932.51 | AE78: -3105.02 | AF78: 0 | AG78: 0 | AH78: 0 | AI78: 86.56 | AJ78: 101.94 | AK78: 0 | AL78: -71.22 | AM78: 4813.76 | AN78: -1346.28 | AO78: =SUM(AC78:AN78) -> -8259.08 | AP78: -585.18 | AQ78: 393.9 | AR78: =VLOOKUP(B78,'[1]Sheet1 (2)'!$B$2:$C$397,2,0) -> -1656.26 | AS78: =VLOOKUP(B78,'[2]Sheet1 (2)'!$B$2:$C$404,2,0) -> 0 | AT78: -1533 | AU78: 12.2 | AV78: 0 | AW78: -204.22 | AX78: -12.2 | AY78: 0 | AZ78: 0 | BA78: 23.78 | BB78: =SUM(AP78:BA78) -> -3560.98 | BC78: 0 | BD78: 0 | BE78: -23.78 | BF78: 1322.76 | BG78: -1268.03 | BH78: 0 | BI78: -54.73 | BO78: =SUM(BC78:BN78) -> -23.78
B79: 5012013000 COGS PP Marketing Program Voucher Estimated | C79: 0 | D79: -21104.46 | E79: 21104.46 | F79: 0 | G79: 0 | H79: 0 | I79: 0 | J79: 0 | K79: 0 | L79: 0 | M79: 0 | N79: 0 | O79: =SUBTOTAL(9,C79:N79) -> 0 | P79: 0 | Q79: 0 | R79: 0 | S79: 0 | T79: 0 | U79: 0 | V79: 0 | W79: 0 | X79: 0 | Y79: 0 | Z79: 0 | AA79: 0 | AB79: =SUM(P79:AA79) -> 0 | AC79: 0 | AD79: 0 | AE79: 0 | AF79: 0 | AG79: 0 | AH79: 0 | AI79: 0 | AJ79: 0 | AK79: 0 | AL79: 0 | AM79: 0 | AN79: 0 | AO79: =SUM(AC79:AN79) -> 0 | AP79: 0 | AQ79: 0 | AR79: 0 | AS79: 0 | AT79: 0 | AU79: 0 | AV79: 0 | AW79: 0 | AX79: 0 | AY79: 0 | AZ79: 0 | BA79: 0 | BB79: =SUM(AP79:BA79) -> 0 | BC79: 0 | BD79: 0 | BE79: 0 | BF79: 0 | BG79: 0 | BH79: 0 | BI79: 0 | BO79: =SUM(BC79:BN79) -> 0
B80: 5012014000 COGS PP Marketing Program PM Estimated | C80: 200 | D80: -600 | E80: 0 | F80: 0 | G80: 0 | H80: 600 | I80: -600 | J80: 0 | K80: 0 | L80: 0 | M80: 0 | N80: 0 | O80: =SUBTOTAL(9,C80:N80) -> -400 | P80: 2356.24 | Q80: 2364.81 | R80: 0 | S80: 0 | T80: 0 | U80: 0 | V80: 0 | W80: 0 | X80: 565.21 | Y80: 0 | Z80: 0 | AA80: 205.19 | AB80: =SUM(P80:AA80) -> 5491.45 | AC80: 0 | AD80: 0 | AE80: 0 | AF80: -2356.24 | AG80: -2364.81 | AH80: 0 | AI80: 0 | AJ80: 0 | AK80: 0 | AL80: 506.49 | AM80: -565.21 | AN80: 0 | AO80: =SUM(AC80:AN80) -> -4779.77 | AP80: 0 | AQ80: 0 | AR80: =VLOOKUP(B80,'[1]Sheet1 (2)'!$B$2:$C$397,2,0) -> 1145.28 | AS80: =VLOOKUP(B80,'[2]Sheet1 (2)'!$B$2:$C$404,2,0) -> 0 | AT80: 876.05 | AU80: 0 | AV80: 0 | AW80: -69.14 | AX80: 0 | AY80: -506.49 | AZ80: 0 | BA80: 0 | BB80: =SUM(AP80:BA80) -> 1445.7 | BC80: -876.05 | BD80: 0 | BE80: 0 | BF80: 0 | BG80: 14.25 | BH80: -14.25 | BI80: 0 | BO80: =SUM(BC80:BN80) -> -876.05
B81: COS PRIME PRODUCT | C81: =SUM(C52:C80) -> 45830.31 | D81: =SUM(D52:D80) -> -104103.65 | E81: =SUM(E52:E80) -> 94637.83 | F81: =SUM(F52:F80) -> 521.69 | G81: =SUM(G52:G80) -> 4.39 | H81: =SUM(H52:H80) -> 3544.23 | I81: =SUM(I52:I80) -> -3585.65 | J81: =SUM(J52:J80) -> 1204449.8 | ... N81: =SUM(N52:N80) -> -72115.1 | O81: =SUM(C81:N81) -> 3103922.8 | P81: =SUM(P52:P80) -> 1156106.6 | Q81: =SUM(Q52:Q80) -> 1037390.1 | R81: =SUM(R52:R80) -> 67309.39 | S81: =SUM(S52:S80) -> 62832.07 | T81: =SUM(T52:T80) -> 5351.87 | U81: =SUM(U52:U80) -> 853.06 | V81: =SUM(V52:V80) -> 73639.63 | W81: =SUM(W52:W80) -> 1137580 | ... BO81: =SUM(BO52:BO80) -> 124957.81
B82: 5020100101 COGS Parts Through Counter | C82: 3184835.6 | D82: 3183621 | E82: 3656982.4 | F82: 3041108.4 | G82: 3803618.8 | H82: 4895571.2 | I82: 3826961.5 | J82: 2560284.7 | K82: 6341438.1 | L82: 5483608.5 | M82: 6796169.7 | N82: 7112953.3 | O82: =SUBTOTAL(9,C82:N82) -> 53887153 | P82: 4599898.2 | Q82: 2965898.5 | R82: 6622098.5 | S82: 3765594.1 | T82: 4981808.6 | U82: 3992528.3 | V82: 3408756 | W82: 3951722.2 | X82: 3947988.9 | Y82: 4076447.7 | Z82: 2693818.1 | AA82: 3613016.3 | AB82: =SUM(P82:AA82) -> 48619575 | AC82: 2730594.5 | AD82: 3355008.6 | AE82: 3621610 | AF82: 2924269.9 | AG82: 3528144.9 | AH82: 3117663.7 | AI82: 3261956.1 | AJ82: 1022859.3 | AK82: 5962635.3 | AL82: 3524605.8 | AM82: 3076585.7 | AN82: 2788930.4 | AO82: =SUM(AC82:AN82) -> 38914864 | AP82: 2490591.2 | AQ82: 2463137 | AR82: =VLOOKUP(B82,'[1]Sheet1 (2)'!$B$2:$C$397,2,0) -> 1752616 | AS82: =VLOOKUP(B82,'[2]Sheet1 (2)'!$B$2:$C$404,2,0) -> 1717305.5 | AT82: 2445087.5 | AU82: 2406889.3 | AV82: 2029562.8 | AW82: 2078132.4 | AX82: 1936129.8 | AY82: 2203714 | AZ82: 2727682.4 | BA82: 2025448 | BB82: =SUM(AP82:BA82) -> 26276296 | BC82: 2115353.8 | BD82: 2879112.5 | BE82: 2817465.5 | BF82: 2324080.5 | BG82: 1838100 | BH82: 2208410.1 | BI82: 2308117.3 | BO82: =SUM(BC82:BN82) -> 16490640
B83: 5020100202 COGS Parts Through Service Flat Rate | C83: 7169.99 | D83: 3165.23 | E83: 0 | F83: 18821.76 | G83: 29025.56 | H83: 721501.9 | I83: 11447.32 | J83: 52.78 | K83: 267.19 | L83: 7856.33 | M83: 217.08 | N83: 1245943.8 | O83: =SUBTOTAL(9,C83:N83) -> 2045468.9 | P83: 0 | Q83: 330889.19 | R83: 485781.97 | S83: 226218.27 | T83: 471028.04 | U83: 543287.67 | V83: 387814.71 | W83: 435838.77 | X83: 480959.59 | Y83: 575650.32 | Z83: 548313.62 | AA83: 938920.71 | AB83: =SUM(P83:AA83) -> 5424702.9 | AC83: 285469.72 | AD83: 1049819.1 | AE83: 529870.03 | AF83: 663922.03 | AG83: 932254.4 | AH83: 777619.45 | AI83: 826152.29 | AJ83: 684234.15 | AK83: 911759.39 | AL83: 728908.86 | AM83: 816616.9 | AN83: 1141366.3 | AO83: =SUM(AC83:AN83) -> 9347992.6 | AP83: 688671.31 | AQ83: 796962.98 | AR83: =VLOOKUP(B83,'[1]Sheet1 (2)'!$B$2:$C$397,2,0) -> 550369.31 | AS83: =VLOOKUP(B83,'[2]Sheet1 (2)'!$B$2:$C$404,2,0) -> 356439.04 | AT83: 442978.69 | AU83: 171911.36 | AV83: 23506.51 | AW83: 186182.53 | AX83: 445704.88 | AY83: 124165.3 | AZ83: 23047.06 | BA83: 351675.4 | BB83: =SUM(AP83:BA83) -> 4161614.4 | BC83: 221636.28 | BD83: 129110.88 | BE83: 284884.71 | BF83: 157666.76 | BG83: 415577.52 | BH83: 224183.79 | BI83: 186580.95 | BO83: =SUM(BC83:BN83) -> 1619640.9
B84: 5020400101 COGS Parts Through Counter CORE | C84: 28211.14 | D84: 20608.37 | E84: 29290.35 | F84: 277204.52 | G84: 79989.27 | H84: 52200.45 | I84: 31217.17 | J84: 34765.75 | K84: 42212.78 | L84: 22773.31 | M84: 52971.78 | N84: 65077.53 | O84: =SUBTOTAL(9,C84:N84) -> 736522.42 | P84: 78719.26 | Q84: 63572.58 | R84: 72886.97 | S84: 59423.12 | T84: 28248.19 | U84: 46785.3 | V84: 27370.61 | W84: 33190.63 | X84: 18508.58 | Y84: 9204.83 | Z84: 2957.39 | AA84: 3118.1 | AB84: =SUM(P84:AA84) -> 443985.56 | AC84: 8367.83 | AD84: 126.31 | AE84: 2709.05 | AF84: 3485.31 | AG84: 379.07 | AH84: 0 | AI84: 15346.22 | AJ84: 3474.97 | AK84: -356.7 | AL84: 5.13 | AM84: 599.22 | AN84: 1348.03 | AO84: =SUM(AC84:AN84) -> 35484.44 | AP84: 0 | AQ84: 1971.62 | AR84: =VLOOKUP(B84,'[1]Sheet1 (2)'!$B$2:$C$397,2,0) -> 1847.58 | AS84: =VLOOKUP(B84,'[2]Sheet1 (2)'!$B$2:$C$404,2,0) -> 879.82 | AT84: 126460.04 | AU84: 81961.83 | AV84: 105335.75 | AW84: 161104.34 | AX84: 90436.92 | AY84: 106960.69 | AZ84: 165135.13 | BA84: 152647.59 | BB84: =SUM(AP84:BA84) -> 994741.31 | BC84: 112614.35 | BD84: 122939.11 | BE84: 132808.48 | BF84: 185678.89 | BG84: 19756.9 | BH84: 192365.34 | BI84: 139069.13 | BO84: =SUM(BC84:BN84) -> 905232.2
B85: 5020500100 COGS Parts SOS Bottle | C85: 18.08 | D85: 5.18 | E85: 43.38 | F85: 7.84 | G85: 17.95 | H85: 21.72 | I85: 29.94 | J85: 19.13 | K85: 36.48 | L85: 62.04 | M85: 41.72 | N85: 75.52 | O85: =SUBTOTAL(9,C85:N85) -> 378.98 | P85: 29.4 | Q85: 18.6 | R85: 45.26 | S85: 0.62 | T85: 21.9 | U85: 27.28 | V85: 41.48 | W85: 27.06 | X85: 0 | Y85: 22.36 | Z85: 25.35 | AA85: 2.4 | AB85: =SUM(P85:AA85) -> 261.71 | AC85: 2.34 | AD85: 37.66 | AE85: 3 | AF85: 23.4 | AG85: 17.98 | AH85: 1.11 | AI85: 2.85 | AJ85: 91.28 | AK85: 0 | AL85: 4.32 | AM85: 0.6 | AN85: 0 | AO85: =SUM(AC85:AN85) -> 184.54 | AP85: 0 | AQ85: 0 | AR85: 0 | AS85: =VLOOKUP(B85,'[2]Sheet1 (2)'!$B$2:$C$404,2,0) -> 4 | AT85: 0 | AU85: 0 | AV85: 1.56 | AW85: 0 | AX85: 35.8 | AY85: 46.87 | AZ85: 23.53 | BA85: 44.34 | BB85: =SUM(AP85:BA85) -> 156.1 | BC85: 33.95 | BD85: 42.41 | BE85: 1.6 | BF85: 10.03 | BG85: 7.83 | BH85: 5.41 | BI85: 5.86 | BO85: =SUM(BC85:BN85) -> 107.09
B86: 5020500101 COGS Parts Through Counter USED Parts | C86: 8746 | D86: 0 | E86: 1025.21 | F86: 0 | G86: 0 | H86: 3182.65 | I86: 0 | J86: 4560.57 | K86: 998.56 | L86: 0 | M86: 0 | N86: 0 | O86: =SUBTOTAL(9,C86:N86) -> 18512.99 | P86: 0 | Q86: 0 | R86: 0 | S86: 0 | T86: 0 | U86: 0 | V86: 2313.39 | W86: 0 | X86: 3361.75 | Y86: 698.1 | Z86: 0 | AA86: 0 | AB86: =SUM(P86:AA86) -> 6373.24 | AC86: 3110.51 | AD86: 0 | AE86: 3172.71 | AF86: 0 | AG86: 0 | AH86: 0 | AI86: 0 | AJ86: 0 | AK86: 0 | AL86: 0 | AM86: 0 | AN86: 0 | AO86: =SUM(AC86:AN86) -> 6283.22 | AP86: 0 | AQ86: 0 | AR86: 0 | AS86: 0 | AT86: 0 | AU86: 0 | AV86: 0 | AW86: 0 | AX86: 0 | AY86: 0 | AZ86: 0 | BA86: 0 | BB86: =SUM(AP86:BA86) -> 0 | BC86: 0 | BD86: 0 | BE86: 0 | BF86: 0 | BG86: 0 | BH86: 0 | BI86: 0 | BO86: =SUM(BC86:BN86) -> 0
B87: 5020500200 COGS Digital Subscription | C87: 0 | D87: 0 | E87: 0 | F87: 0 | G87: 0 | H87: 0 | I87: 0 | J87: 0 | K87: 0 | L87: 0 | M87: 0 | N87: 0 | O87: 0 | P87: 0 | Q87: 0 | R87: 0 | S87: 0 | T87: 0 | U87: 0 | V87: 0 | W87: 0 | X87: 0 | Y87: 0 | Z87: 0 | AA87: 0 | AB87: 0 | AC87: 0 | AD87: 0 | AE87: 0 | AF87: 0 | AG87: 0 | AH87: 0 | AI87: 0 | AJ87: 0 | AK87: 0 | AL87: 0 | AM87: 0 | AN87: 0 | AO87: 0 | AP87: 0 | AQ87: 194.66 | AR87: =VLOOKUP(B87,'[1]Sheet1 (2)'!$B$2:$C$397,2,0) -> 0 | AS87: =VLOOKUP(B87,'[2]Sheet1 (2)'!$B$2:$C$404,2,0) -> 187.27 | AT87: 0 | AU87: 1556.8 | AV87: 1627.52 | AW87: 8445.73 | AX87: 1002.86 | AY87: 0 | AZ87: 0 | BA87: 4090.02 | BB87: =SUM(AP87:BA87) -> 17104.86 | BC87: 199.54 | BD87: 4435.02 | BE87: 1801.7 | BF87: 0 | BG87: 14.28 | BH87: 188.02 | BI87: -113.7 | BO87: =SUM(BC87:BN87) -> 6524.86
B88: 5020600101 COGS Parts Adjustment | C88: -21923.22 | D88: 101066.29 | E88: -34949.38 | F88: -136252.24 | G88: -70648.54 | H88: -44363.21 | I88: 4666.44 | J88: -284738.15 | K88: -63292.66 | L88: -45875.62 | M88: -32258.71 | N88: -53412.03 | O88: =SUBTOTAL(9,C88:N88) -> -681981.03 | P88: -78041.74 | Q88: -37843.45 | R88: -145155.13 | S88: -24034.02 | T88: -31744.77 | U88: -17924.76 | V88: -32622.64 | W88: -31421.04 | X88: -643.28 | Y88: 75866.46 | Z88: -111900.1 | AA88: -216712.69 | AB88: =SUM(P88:AA88) -> -652177.16 | AC88: -113739.42 | AD88: -110912.07 | AE88: -208495.08 | AF88: -130640.22 | AG88: -110006.47 | AH88: -19249.04 | AI88: -6824.05 | AJ88: -79009.99 | AK88: -40250.79 | AL88: -15596.96 | AM88: -39857.27 | AN88: -102603.71 | AO88: =SUM(AC88:AN88) -> -977185.07 | AP88: -136761.58 | AQ88: -70437.8 | AR88: =VLOOKUP(B88,'[1]Sheet1 (2)'!$B$2:$C$397,2,0) -> -61679.82 | AS88: =VLOOKUP(B88,'[2]Sheet1 (2)'!$B$2:$C$404,2,0) -> -75591.07 | AT88: -90458.16 | AU88: -28003.1 | AV88: -49701.63 | AW88: -58057.48 | AX88: -74340.52 | AY88: -61697.9 | AZ88: 78406.55 | BA88: 1802316.4 | BB88: =SUM(AP88:BA88) -> 1173993.9 | BC88: -70758.42 | BD88: -66469.12 | BE88: -73045.97 | BF88: -10052.13 | BG88: -247815.22 | BH88: -109049.69 | BI88: -101601.54 | BO88: =SUM(BC88:BN88) -> -678792.09
B89: 5020600301 COGS Parts Adjustment - ITR3A | C89: -107667 | D89: -85420.57 | E89: -24377.04 | F89: -36190.44 | G89: -133408.86 | H89: -787999.78 | I89: -273767.12 | J89: -175076.19 | K89: -318446.35 | L89: -199194.04 | M89: -316686.38 | N89: -563238.9 | O89: =SUBTOTAL(9,C89:N89) -> -3021472.7 | P89: -224426.59 | Q89: -142337.08 | R89: -212571.65 | S89: -248951.48 | T89: -300600.94 | U89: -12446.64 | V89: -94617.36 | W89: -60497.7 | X89: -85799.63 | Y89: -146156.35 | Z89: -84273.78 | AA89: -68738.48 | AB89: =SUM(P89:AA89) -> -1681417.7 | AC89: -27065.4 | AD89: -141668.67 | AE89: -82657.4 | AF89: -39629.47 | AG89: -122110.44 | AH89: -88843.57 | AI89: -291440.25 | AJ89: -161392.3 | AK89: -47485.09 | AL89: -47814.64 | AM89: -103869.18 | AN89: -80976.44 | AO89: =SUM(AC89:AN89) -> -1234952.8 | AP89: -124536.54 | AQ89: -138744.46 | AR89: =VLOOKUP(B89,'[1]Sheet1 (2)'!$B$2:$C$397,2,0) -> -64861.7 | AS89: =VLOOKUP(B89,'[2]Sheet1 (2)'!$B$2:$C$404,2,0) -> -83280.15 | AT89: -63991.32 | AU89: -106131.91 | AV89: -73343.24 | AW89: -25488.81 | AX89: -68850.9 | AY89: -71858.49 | AZ89: -95237.98 | BA89: -2570.64 | BB89: =SUM(AP89:BA89) -> -918896.14 | BC89: -77735.52 | BD89: 131781.07 | BE89: -181900.73 | BF89: -147020 | BG89: -47971.49 | BH89: -223266.86 | BI89: -130512.44 | BO89: =SUM(BC89:BN89) -> -676625.97
B90: 5020600303 COGS Parts Adjustment PO Buy Back | E90: 31726.73 | F90: 131862.56 | G90: 21295.97 | H90: 219616.47 | I90: 80511.05 | J90: 279097.42 | K90: 183736.07 | L90: 10368.91 | M90: 12146.18 | N90: 149474.35 | O90: =SUBTOTAL(9,C90:N90) -> 1119835.7 | P90: 331451.16 | Q90: 116373.91 | R90: 16951.94 | S90: 104371.58 | T90: 17330.91 | U90: 481841.55 | V90: 405477.21 | W90: 19997.87 | X90: 338305.67 | Y90: 59357.75 | Z90: 5307.48 | AA90: 53161.53 | AB90: =SUM(P90:AA90) -> 1949928.6 | AC90: 21684.71 | AD90: 5978.01 | AE90: 21 | AF90: 1506.51 | AG90: 1199.76 | AH90: 38.9 | AI90: 1269.13 | AJ90: 1765.73 | AK90: 885.11 | AL90: 938.02 | AM90: 19.85 | AN90: 0 | AO90: =SUM(AC90:AN90) -> 35306.73 | AP90: 0 | AQ90: 291.45 | AR90: =VLOOKUP(B90,'[1]Sheet1 (2)'!$B$2:$C$397,2,0) -> 445.55 | AS90: =VLOOKUP(B90,'[2]Sheet1 (2)'!$B$2:$C$404,2,0) -> 102.26 | AT90: 97.93 | AU90: 0 | AV90: 0 | AW90: 0 | AX90: 0 | AY90: 123.08 | AZ90: -79.06 | BA90: 0 | BB90: =SUM(AP90:BA90) -> 981.21 | BC90: 0 | BD90: 0 | BE90: 0 | BF90: 0 | BG90: 0 | BH90: 0 | BI90: 0 | BO90: =SUM(BC90:BN90) -> 0
B91: 5020800101 COGS Parts Through Counter PEX Parts | C91: 0 | D91: 75321.83 | E91: 93112.04 | F91: 0 | G91: 21166.16 | H91: 52658.88 | I91: 705.91 | J91: 58256.27 | K91: 33836.81 | L91: 0 | M91: 0 | N91: 101180.44 | O91: =SUBTOTAL(9,C91:N91) -> 436238.34 | P91: 57409.34 | Q91: 22957.76 | R91: 88882.25 | S91: 0 | T91: 30307.87 | U91: 85058.06 | V91: 183256.14 | W91: 184911.05 | X91: 83978.7 | Y91: -6565.28 | Z91: 0 | AA91: 0 | AB91: =SUM(P91:AA91) -> 730195.89 | AC91: 0 | AD91: 1079.55 | AE91: 0 | AF91: 0 | AG91: 0 | AH91: 0 | AI91: 0 | AJ91: 0 | AK91: 0 | AL91: 0 | AM91: 0 | AN91: 0 | AO91: =SUM(AC91:AN91) -> 1079.55 | AP91: 0 | AQ91: 0 | AR91: 0 | AS91: 0 | AT91: 0 | AU91: 0 | AV91: 0 | AW91: 87264.37 | AX91: 0 | AY91: 93478.84 | AZ91: 29516.03 | BA91: 36392.18 | BB91: =SUM(AP91:BA91) -> 246651.42 | BC91: 28017.29 | BD91: 244202.33 | BE91: 87563.53 | BF91: 0 | BG91: 0 | BH91: 82763.47 | BI91: 72925.52 | BO91: =SUM(BC91:BN91) -> 515472.14
B92: 5020800102 COGS Parts Through Counter PEX Parts Core | E92: 1465.22 | F92: 0 | G92: 289.39 | H92: 1606.56 | I92: 34.31 | J92: 1681.1 | K92: 1391.71 | L92: 0 | M92: 0 | N92: 1279.6 | O92: =SUBTOTAL(9,C92:N92) -> 7747.89 | P92: 1681.1 | Q92: 289.39 | R92: 939.34 | S92: 0 | T92: 460.02 | U92: 3481.86 | V92: 2519.5 | W92: 1931.31 | X92: 1033.15 | Y92: 505.33 | Z92: 0 | AA92: 0 | AB92: =SUM(P92:AA92) -> 12841 | AC92: 0 | AD92: 12.65 | AE92: 0 | AF92: 0 | AG92: 0 | AH92: 0 | AI92: 0 | AJ92: 0 | AK92: 0 | AL92: 0 | AM92: 0 | AN92: 0 | AO92: =SUM(AC92:AN92) -> 12.65 | AP92: 0 | AQ92: 0 | AR92: 0 | AS92: 0 | AT92: 0 | AU92: 0 | AV92: 0 | AW92: 914.74 | AX92: 76473.15 | AY92: 1151.89 | AZ92: 460.4 | BA92: 637.68 | BB92: =SUM(AP92:BA92) -> 79637.86 | BC92: 26522.8 | BD92: 536484.91 | BE92: 35468.02 | BF92: 0 | BG92: 0 | BH92: 169471.84 | BI92: 979.33 | BO92: =SUM(BC92:BN92) -> 768926.9
B93: 5020800301 COGS Parts PEX Cross Charging CRC to Branch | J93: 132094.58 | K93: 0 | L93: 31261.11 | M93: 25518.39 | N93: 22054.65 | O93: =SUBTOTAL(9,C93:N93) -> 210928.73 | P93: 19891.22 | Q93: 24561.82 | R93: 0 | S93: 0 | T93: 1322.46 | U93: 0 | V93: 8398.81 | W93: 34215.38 | X93: 17034.26 | Y93: 13494.75 | Z93: 32445.72 | AA93: 20049.81 | AB93: =SUM(P93:AA93) -> 171414.23 | AC93: -11964.59 | AD93: 39414.65 | AE93: 0 | AF93: 527 | AG93: 56.94 | AH93: 0 | AI93: 0 | AJ93: 18739.92 | AK93: 1128.12 | AL93: 0 | AM93: 8363.96 | AN93: 12699.46 | AO93: =SUM(AC93:AN93) -> 68965.46 | AP93: 1243.55 | AQ93: 0 | AR93: =VLOOKUP(B93,'[1]Sheet1 (2)'!$B$2:$C$397,2,0) -> 21332.37 | AS93: =VLOOKUP(B93,'[2]Sheet1 (2)'!$B$2:$C$404,2,0) -> 21333.68 | AT93: 0 | AU93: 0 | AV93: -23821.13 | AW93: 123.08 | AX93: 0 | AY93: 0 | AZ93: 27079.24 | BA93: 6506.86 | BB93: =SUM(AP93:BA93) -> 53797.65 | BC93: 20566.54 | BD93: 5243.87 | BE93: 22781.13 | BF93: -649.55 | BG93: 0 | BH93: 0 | BI93: 0 | BO93: =SUM(BC93:BN93) -> 47941.99
B94: 5021400102 COGS Parts PEX Warranty | C94: -1015.33 | D94: 2281.96 | E94: -576.5 | F94: -1006.22 | G94: -629.36 | H94: 45.75 | I94: -631.96 | J94: 855.79 | K94: 496.94 | L94: -1662.88 | M94: 0 | N94: 1486.83 | O94: =SUBTOTAL(9,C94:N94) -> -354.98 | P94: 843.33 | Q94: -1944.6 | R94: -445.96 | S94: 0 | T94: 134.32 | U94: 475.7 | V94: 2682.5 | W94: 1861.55 | X94: 737.07 | Y94: 362.78 | Z94: 0 | AA94: -1486.83 | AB94: =SUM(P94:AA94) -> 3219.86 | AC94: -843.33 | AD94: -34.07 | AE94: -1593.27 | AF94: 0 | AG94: -445.35 | AH94: -1249.23 | AI94: -2692.87 | AJ94: -2717.34 | AK94: -1234.01 | AL94: -362.78 | AM94: 0 | AN94: 0 | AO94: =SUM(AC94:AN94) -> -11172.25 | AP94: 0 | AQ94: -16.19 | AR94: =VLOOKUP(B94,'[1]Sheet1 (2)'!$B$2:$C$397,2,0) -> 0 | AS94: =VLOOKUP(B94,'[2]Sheet1 (2)'!$B$2:$C$404,2,0) -> 0 | AT94: 0 | AU94: 0 | AV94: 0 | AW94: 1308.97 | AX94: 0 | AY94: 1409.77 | AZ94: 442.74 | BA94: 545.89 | BB94: =SUM(AP94:BA94) -> 3691.18 | BC94: 420.26 | BD94: 3663.03 | BE94: 1313.45 | BF94: 0 | BG94: 0 | BH94: 1241.45 | BI94: 1093.88 | BO94: =SUM(BC94:BN94) -> 7732.07
B95: 5021500002 IFRS 15 COGS PS-Parts Marketing Program Prev Maint | AP95: 0 | AQ95: 0 | AR95: =VLOOKUP(B95,'[1]Sheet1 (2)'!$B$2:$C$397,2,0) -> 1514.26 | AS95: =VLOOKUP(B95,'[2]Sheet1 (2)'!$B$2:$C$404,2,0) -> 0 | AT95: 0 | AU95: 0 | AV95: 0 | AW95: 0 | AX95: 0 | AY95: 0 | AZ95: 0 | BA95: 0 | BB95: =SUM(AP95:BA95) -> 1514.26 | BC95: 0 | BD95: 0 | BE95: 0 | BF95: 0 | BG95: 777.14 | BH95: 0 | BI95: 307.35 | BO95: =SUM(BC95:BN95) -> 1084.49
B96: COS PARTS | C96: =SUM(C82:C94) -> 3098375.3 | D96: =SUM(D82:D94) -> 3300649.3 | E96: =SUM(E82:E94) -> 3753742.4 | F96: =SUM(F82:F94) -> 3295556.1 | G96: =SUM(G82:G94) -> 3750716.3 | H96: =SUM(H82:H94) -> 5114042.6 | I96: =SUM(I82:I94) -> 3681174.5 | J96: =SUM(J82:J94) -> 2611853.7 | ... N96: =SUM(N82:N94) -> 8082875.1 | O96: =SUM(C96:N96) -> 54758978 | P96: =SUM(P82:P94) -> 4787454.7 | Q96: =SUM(Q82:Q94) -> 3342436.6 | R96: =SUM(R82:R94) -> 6929413.4 | S96: =SUM(S82:S94) -> 3882622.2 | T96: =SUM(T82:T94) -> 5198316.6 | U96: =SUM(U82:U94) -> 5123114.3 | V96: =SUM(V82:V94) -> 4301390.4 | W96: =SUM(W82:W94) -> 4571777.1 | ... AO96: =SUM(AO82:AO94) -> 46186863 | AP96: =SUM(AP82:AP95) -> 2919207.9 | AQ96: =SUM(AQ82:AQ95) -> 3053359.3 | AR96: =SUM(AR82:AR95) -> 2201583.6 | AS96: =SUM(AS82:AS95) -> 1937380.4 | AT96: =SUM(AT82:AT95) -> 2860174.7 | AU96: =SUM(AU82:AU95) -> 2528184.3 | AV96: =SUM(AV82:AV95) -> 2013168.2 | AW96: =SUM(AW82:AW95) -> 2439929.9 | ... BO96: =SUM(BO82:BO95) -> 19007884
B97: 5030100103 COGS Service Actual LPO | N97: -572.18 | O97: =SUBTOTAL(9,C97:N97) -> -572.18 | P97: 0 | Q97: 0 | R97: 0 | S97: 0 | T97: 0 | U97: 0 | V97: 0 | W97: 0 | X97: 0 | Y97: 0 | Z97: 13948.18 | AA97: 0 | AB97: =SUM(P97:AA97) -> 13948.18 | AC97: 0 | AD97: 0 | AE97: 0 | AF97: 0 | AG97: 0 | AH97: 0 | AI97: 0 | AJ97: 0 | AK97: 0 | AL97: 0 | AM97: 0 | AN97: 0 | AO97: =SUM(AC97:AN97) -> 0 | AP97: 0 | AQ97: 0 | AR97: 0 | AS97: 0 | AT97: 0 | AU97: 0 | AV97: 0 | AW97: 0 | AX97: 0 | AY97: 0 | AZ97: 0 | BA97: 0 | BB97: =SUM(AP97:BA97) -> 0 | BC97: 0 | BD97: 0 | BE97: 0 | BF97: 0 | BG97: 0 | BH97: 0 | BI97: 0 | BO97: =SUM(BC97:BN97) -> 0
B98: 5030100105 COGS Service Field Adjustment | C98: 0 | D98: 0 | E98: 0 | F98: 0 | G98: 0 | H98: 0 | I98: 1308.42 | J98: 0 | K98: 0 | L98: 0 | M98: 0 | N98: 0 | O98: =SUBTOTAL(9,C98:N98) -> 1308.42 | P98: 0 | Q98: 0 | R98: 0 | S98: 0 | T98: 0 | U98: 0 | V98: 0 | W98: 0 | X98: 0 | Y98: 0 | Z98: 0 | AA98: 0 | AB98: =SUM(P98:AA98) -> 0 | AC98: 0 | AD98: 0 | AE98: 0 | AF98: 0 | AG98: 0 | AH98: 0 | AI98: 0 | AJ98: 0 | AK98: 0 | AL98: 0 | AM98: 0 | AN98: 0 | AO98: =SUM(AC98:AN98) -> 0 | AP98: 0 | AQ98: 0 | AR98: 0 | AS98: 0 | AT98: 0 | AU98: 0 | AV98: 0 | AW98: 0 | AX98: 0 | AY98: 0 | AZ98: 0 | BA98: 0 | BB98: =SUM(AP98:BA98) -> 0 | BC98: 0 | BD98: 0 | BE98: 0 | BF98: 0 | BG98: 0 | BH98: 0 | BI98: 0 | BO98: =SUM(BC98:BN98) -> 0
B99: 5030100203 COGS Service Flat Rate PO | C99: 28187.67 | D99: 21234.72 | E99: 49253.49 | F99: 10955.63 | G99: 19561.52 | H99: 27801.31 | I99: 18983.81 | J99: 19149.03 | K99: 22847.35 | L99: 13578.6 | M99: 30257.98 | N99: 21284.91 | O99: =SUBTOTAL(9,C99:N99) -> 283096.02 | P99: 34268.6 | Q99: 13043.07 | R99: 15536.63 | S99: 13234.04 | T99: 52327.6 | U99: 28142.13 | V99: 38516.02 | W99: 49663.55 | X99: 184536.63 | Y99: 59271.82 | Z99: 315493.47 | AA99: 138665.96 | AB99: =SUM(P99:AA99) -> 942699.52 | AC99: 153801.66 | AD99: 101433.46 | AE99: 245323.09 | AF99: 55179.73 | AG99: 125423.64 | AH99: 35217.04 | AI99: 140266.06 | AJ99: 44102.38 | AK99: 30566.9 | AL99: 94632.25 | AM99: 66614.04 | AN99: -29504.53 | AO99: =SUM(AC99:AN99) -> 1063055.7 | AP99: 43377.62 | AQ99: 40415.17 | AR99: =VLOOKUP(B99,'[1]Sheet1 (2)'!$B$2:$C$397,2,0) -> 33958.1 | AS99: =VLOOKUP(B99,'[2]Sheet1 (2)'!$B$2:$C$404,2,0) -> 18235.59 | AT99: 22614.92 | AU99: 39181.02 | AV99: 14135.44 | AW99: 27712.12 | AX99: 17568.29 | AY99: 25967.43 | AZ99: 5267.81 | BA99: 10931.1 | BB99: =SUM(AP99:BA99) -> 299364.61 | BC99: 24945.59 | BD99: 5776.73 | BE99: 11955.84 | BF99: 9708.18 | BG99: 22433.32 | BH99: 52979.7 | BI99: 14430.58 | BO99: =SUM(BC99:BN99) -> 142229.94
B100: 5030100207 COGS Service Flat Rate Labor | C100: 111346.46 | D100: 125958.41 | E100: 169524.85 | F100: 154507.01 | G100: 171662.08 | H100: 187777.29 | I100: 158948.96 | J100: 188518.54 | K100: 186395.75 | L100: 187077.65 | M100: 198768.75 | N100: 240213.28 | O100: =SUBTOTAL(9,C100:N100) -> 2080699 | P100: 120787.89 | Q100: 313370.68 | R100: 210058.89 | S100: 143449.13 | T100: 274158.14 | U100: 77399.61 | V100: 164538.36 | W100: 141176.57 | X100: 162222.41 | Y100: 215441.28 | Z100: 187999.45 | AA100: 246265.06 | AB100: =SUM(P100:AA100) -> 2256867.5 | AC100: 132350.4 | AD100: 114259.04 | AE100: 232190.27 | AF100: 114555.2 | AG100: 143411.62 | AH100: 129664.12 | AI100: 147954.93 | AJ100: 221958.05 | AK100: 140536.83 | AL100: 152955.04 | AM100: 112836.43 | AN100: 175462.33 | AO100: =SUM(AC100:AN100) -> 1818134.3 | AP100: 78242.03 | AQ100: 109915.06 | AR100: =VLOOKUP(B100,'[1]Sheet1 (2)'!$B$2:$C$397,2,0) -> 96003.14 | AS100: =VLOOKUP(B100,'[2]Sheet1 (2)'!$B$2:$C$404,2,0) -> 52892.15 | AT100: 128940.8 | AU100: 104982.39 | AV100: 152243.32 | AW100: 136992.46 | AX100: 103796.94 | AY100: 146983.28 | AZ100: 116727.11 | BA100: 116486.6 | BB100: =SUM(AP100:BA100) -> 1344205.3 | BC100: 74906.62 | BD100: 119923.58 | BE100: 98573.18 | BF100: 118607.64 | BG100: 108584.1 | BH100: 84597.24 | BI100: 143118.79 | BO100: =SUM(BC100:BN100) -> 748311.15
B101: 5030500100 COGS Service SOS Lab | E101: 286.14 | F101: 16.81 | G101: 0 | H101: 82.28 | I101: 136.75 | J101: 212.1 | K101: 177.41 | L101: 159.33 | M101: 348.73 | N101: 359.84 | O101: =SUBTOTAL(9,C101:N101) -> 1779.39 | P101: 232.33 | Q101: 216.19 | R101: 518.87 | S101: 0 | T101: 246.46 | U101: 358.01 | V101: 520.74 | W101: 308.43 | X101: 0 | Y101: 244.56 | Z101: 106.96 | AA101: 32.25 | AB101: =SUM(P101:AA101) -> 2784.8 | AC101: 16.4 | AD101: 511.89 | AE101: 42.35 | AF101: 320.01 | AG101: 253.1 | AH101: 8.05 | AI101: 42.41 | AJ101: 0 | AK101: 0 | AL101: 68.94 | AM101: 8.25 | AN101: 0 | AO101: =SUM(AC101:AN101) -> 1271.4 | AP101: 0 | AQ101: 177.65 | AR101: =VLOOKUP(B101,'[1]Sheet1 (2)'!$B$2:$C$397,2,0) -> 503.1 | AS101: =VLOOKUP(B101,'[2]Sheet1 (2)'!$B$2:$C$404,2,0) -> 244.13 | AT101: 177.97 | AU101: 106.56 | AV101: 554.96 | AW101: 10.92 | AX101: 85.79 | AY101: 228.16 | AZ101: 1466.9 | BA101: 306.29 | BB101: =SUM(AP101:BA101) -> 3862.43 | BC101: 296.61 | BD101: 269.39 | BE101: 20.29 | BF101: 88.78 | BG101: 88.07 | BH101: 113.26 | BI101: 50.08 | BO101: =SUM(BC101:BN101) -> 926.48
...

Sheet JAN 22
A1: Financial Statement Item | B1: Text for B/S P&L item | C1: Total of reporting period | D1: Total of the comparison period | E1: Absolute difference | F1: Percentage difference
A2: 1000000 | B2: A S S E T S | C2: 0 | D2: 0 | E2: 0 | F2: =VLOOKUP(B2,'Balance Sheet'!#REF!,2,0) -> #REF!
A3: 1000000 | B3: = = = = = = | C3: 0 | D3: 0 | E3: 0 | F3: =VLOOKUP(B3,'Balance Sheet'!#REF!,2,0) -> #REF!
A4: 10101 | B4: 1011100380 PettyCash IDR SANGATTA | C4: 329.08 | D4: 329.08 | E4: 0 | F4: =VLOOKUP(B4,'Balance Sheet'!#REF!,2,0) -> #REF!
A5: 10101 | B5: 1016109751 Bank IDR Mandiri 1480004169325 MB-SANGATA_COL | C5: 610.44 | D5: 610.44 | E5: 0 | F5: =VLOOKUP(B5,'Balance Sheet'!#REF!,2,0) -> #REF!
A6: 10101 | B6: 1016109761 Bank IDR Mandiri 1480004169309 MB-SANGATA_OPR | C6: 27542.03 | D6: 27542.03 | E6: 0 | F6: =VLOOKUP(B6,'Balance Sheet'!#REF!,2,0) -> #REF!
A7: 10101 | B7: 1016109769 Bank IDR Mandiri 1480004169309 FxV-SANGATA_OPR | C7: -23245.09 | D7: -23245.09 | E7: 0 | F7: =VLOOKUP(B7,'Balance Sheet'!#REF!,2,0) -> #REF!
A8: 10101 | B8: 1016162071 Bank IDR Mandiri 148-001-687266-8 MB SGT | C8: 68.59 | D8: 68.59 | E8: 0 | F8: =VLOOKUP(B8,'Balance Sheet'!#REF!,2,0) -> #REF!
A9: 10101 | B9: 1016162079 Bank IDR Mandiri 148-001-687266-8 FxV SGT | C9: 2.69 | D9: 2.69 | E9: 0 | F9: =VLOOKUP(B9,'Balance Sheet'!#REF!,2,0) -> #REF!
A10: 10101 | C10: 5307.74 | D10: 5307.74 | E10: 0 | F10: =VLOOKUP(B10,'Balance Sheet'!#REF!,2,0) -> #REF!
A11: 101 | C11: 5307.74 | D11: 5307.74 | E11: 0 | F11: =VLOOKUP(B11,'Balance Sheet'!#REF!,2,0) -> #REF!
A12: 10201 | B12: 1110101000 AR Gross Trade 3rd Party | C12: 13061995 | D12: 13061995 | E12: 0 | F12: =VLOOKUP(B12,'Balance Sheet'!#REF!,2,0) -> #REF!
A13: 10201 | B13: 1110101009 AR Gross Trade 3rd Party FxV | C13: -65935.64 | D13: -65935.64 | E13: 0 | F13: =VLOOKUP(B13,'Balance Sheet'!#REF!,2,0) -> #REF!
A14: 10201 | B14: 1110102000 AR Gross Trade Rel Party | C14: 1608482 | D14: 1608482 | E14: 0 | F14: =VLOOKUP(B14,'Balance Sheet'!#REF!,2,0) -> #REF!
A15: 10201 | B15: 1110102009 AR Gross Trade Rel Party FxV | C15: -100611.35 | D15: -100611.35 | E15: 0 | F15: =VLOOKUP(B15,'Balance Sheet'!#REF!,2,0) -> #REF!
A16: 10201 | C16: 14503930 | D16: 14503930 | E16: 0 | F16: =VLOOKUP(B16,'Balance Sheet'!#REF!,2,0) -> #REF!
A17: 10202 | B17: 1120101000 AR Gross Trade 3rd Party Allowance | C17: -38389.61 | D17: -38389.61 | E17: 0 | F17: =VLOOKUP(B17,'Balance Sheet'!#REF!,2,0) -> #REF!
A18: 10202 | C18: -38389.61 | D18: -38389.61 | E18: 0 | F18: =VLOOKUP(B18,'Balance Sheet'!#REF!,2,0) -> #REF!
A19: 102 | C19: 14465541 | D19: 14465541 | E19: 0 | F19: =VLOOKUP(B19,'Balance Sheet'!#REF!,2,0) -> #REF!
A20: 10301 | B20: 1211101000 AR Claim Warranty Pending 3rd Party | C20: 0.01 | D20: 0.01 | E20: 0 | F20: =VLOOKUP(B20,'Balance Sheet'!#REF!,2,0) -> #REF!
A21: 10301 | B21: 1211201311 AR Claim TWLBR | C21: 2588.06 | D21: 2588.06 | E21: 0 | F21: =VLOOKUP(B21,'Balance Sheet'!#REF!,2,0) -> #REF!
A22: 10301 | B22: 1211301000 AR Claim Warranty Claim 3rd Party | C22: 0.01 | D22: 0.01 | E22: 0 | F22: =VLOOKUP(B22,'Balance Sheet'!#REF!,2,0) -> #REF!
A23: 10301 | B23: 1211301001 AR Claim Warranty Claim 3rd Party New | C23: 25403.68 | D23: 25403.68 | E23: 0 | F23: =VLOOKUP(B23,'Balance Sheet'!#REF!,2,0) -> #REF!
A24: 10301 | B24: 1211401001 AR Claim 3rd Party Goodwill (New Acct) | C24: 10538.29 | D24: 10538.29 | E24: 0 | F24: =VLOOKUP(B24,'Balance Sheet'!#REF!,2,0) -> #REF!
A25: 10301 | B25: 1211401310 AR Claim Warranty Claim-Goodwill 3rd Party OEM | C25: 19.35 | D25: 19.35 | E25: 0 | F25: =VLOOKUP(B25,'Balance Sheet'!#REF!,2,0) -> #REF!
A26: 10301 | C26: 38549.4 | D26: 38549.4 | E26: 0 | F26: =VLOOKUP(B26,'Balance Sheet'!#REF!,2,0) -> #REF!
A27: 10302 | B27: 1212001010 AR Claim 3rd Party CAT Parts Core | C27: 17751.83 | D27: 17751.83 | E27: 0 | F27: =VLOOKUP(B27,'Balance Sheet'!#REF!,2,0) -> #REF!
A28: 10302 | C28: 17751.83 | D28: 17751.83 | E28: 0 | F28: =VLOOKUP(B28,'Balance Sheet'!#REF!,2,0) -> #REF!
A29: 10306 | B29: 1110101230 AR Gross Trade 3rd Party Art23 | C29: 55428.1 | D29: 55428.1 | E29: 0 | F29: =VLOOKUP(B29,'Balance Sheet'!#REF!,2,0) -> #REF!
A30: 10306 | B30: 1110101239 AR Gross Trade 3rd Party Art23 FxV | C30: -238.21 | D30: -238.21 | E30: 0 | F30: =VLOOKUP(B30,'Balance Sheet'!#REF!,2,0) -> #REF!
A31: 10306 | B31: 1110102230 AR Gross Trade Rel Party Art23 | C31: 601.35 | D31: 601.35 | E31: 0 | F31: =VLOOKUP(B31,'Balance Sheet'!#REF!,2,0) -> #REF!
A32: 10306 | B32: 1110102239 AR Gross Trade Rel Party Art23 FxV | C32: -4.27 | D32: -4.27 | E32: 0 | F32: =VLOOKUP(B32,'Balance Sheet'!#REF!,2,0) -> #REF!
A33: 10306 | B33: 1110181000 AR Gross Others Project System Over Under | C33: 2597.52 | D33: 2597.52 | E33: 0 | F33: =VLOOKUP(B33,'Balance Sheet'!#REF!,2,0) -> #REF!
A34: 10306 | B34: 1110202000 AR Gross Non Trade Rel Party | C34: 2611.46 | D34: 2611.46 | E34: 0 | F34: =VLOOKUP(B34,'Balance Sheet'!#REF!,2,0) -> #REF!
A35: 10306 | B35: 1110202009 AR Gross Non Trade Rel Party FxV | C35: -5.3 | D35: -5.3 | E35: 0 | F35: =VLOOKUP(B35,'Balance Sheet'!#REF!,2,0) -> #REF!
A36: 10306 | B36: 1216001020 AR Claim 3rd Party CAT PSDN | C36: 7323.97 | D36: 7323.97 | E36: 0 | F36: =VLOOKUP(B36,'Balance Sheet'!#REF!,2,0) -> #REF!
A37: 10306 | B37: 1219301000 AR Claim Others 3rd Party | C37: 2618.36 | D37: 2618.36 | E37: 0 | F37: =VLOOKUP(B37,'Balance Sheet'!#REF!,2,0) -> #REF!
A38: 10306 | B38: 1219302070 AR Claim Others Rel Party CKB | C38: 40.38 | D38: 40.38 | E38: 0 | F38: =VLOOKUP(B38,'Balance Sheet'!#REF!,2,0) -> #REF!
A39: 10306 | C39: 70973.36 | D39: 70973.36 | E39: 0 | F39: =VLOOKUP(B39,'Balance Sheet'!#REF!,2,0) -> #REF!
A40: 103 | C40: 127274.59 | D40: 127274.59 | E40: 0 | F40: =VLOOKUP(B40,'Balance Sheet'!#REF!,2,0) -> #REF!
A41: 10501 | B41: 1411191200 Inventory PP Freight & Handling (CLEARING) | C41: -0.1 | D41: -0.1 | E41: 0 | F41: =VLOOKUP(B41,'Balance Sheet'!#REF!,2,0) -> #REF!
A42: 10501 | B42: 1411198000 Inventory PP Non CAT Accessories | C42: 13388.01 | D42: 13388.01 | E42: 0 | F42: =VLOOKUP(B42,'Balance Sheet'!#REF!,2,0) -> #REF!
A43: 10501 | B43: 1460200000 Inventory PP GIT Non Trade | C43: 1668.98 | D43: 1668.98 | E43: 0 | F43: =VLOOKUP(B43,'Balance Sheet'!#REF!,2,0) -> #REF!
A44: 10501 | C44: 15056.89 | D44: 15056.89 | E44: 0 | F44: =VLOOKUP(B44,'Balance Sheet'!#REF!,2,0) -> #REF!
A45: 10502 | B45: 1415101000 Inventory Parts Stock On Hand | C45: 12826014 | D45: 12826014 | E45: 0 | F45: =VLOOKUP(B45,'Balance Sheet'!#REF!,2,0) -> #REF!
A46: 10502 | B46: 1415141000 Inventory Parts PVRG | C46: -1140.94 | D46: -1140.94 | E46: 0 | F46: =VLOOKUP(B46,'Balance Sheet'!#REF!,2,0) -> #REF!
A47: 10502 | B47: 1415141666 Inventory Parts PVRG SPM - SOA | C47: 36331.37 | D47: 36331.37 | E47: 0 | F47: =VLOOKUP(B47,'Balance Sheet'!#REF!,2,0) -> #REF!
A48: 10502 | B48: 1415192000 Inventory Parts Gross Hub Turn Over | C48: 909825 | D48: 909825 | E48: 0 | F48: =VLOOKUP(B48,'Balance Sheet'!#REF!,2,0) -> #REF!
A49: 10502 | B49: 1461001210 Inventory Parts GINI | C49: 1970301.9 | D49: 1970301.9 | E49: 0 | F49: =VLOOKUP(B49,'Balance Sheet'!#REF!,2,0) -> #REF!
A50: 10502 | B50: 1465011000 Inventory Parts GIT | C50: 2830113.3 | D50: 2830113.3 | E50: 0 | F50: =VLOOKUP(B50,'Balance Sheet'!#REF!,2,0) -> #REF!
A51: 10502 | B51: 1465011002 Inventory Parts Freight & Handling (CLEARING) | C51: 24644.4 | D51: 24644.4 | E51: 0 | F51: =VLOOKUP(B51,'Balance Sheet'!#REF!,2,0) -> #REF!
A52: 10502 | B52: 1515001213 Landed Cost - Parts FH ITL Inbound Actual | C52: -1502250.4 | D52: -1502250.4 | E52: 0 | F52: =VLOOKUP(B52,'Balance Sheet'!#REF!,2,0) -> #REF!
A53: 10502 | B53: 1515001214 Landed Cost - Parts FH LCL Inbound Actual | C53: 10841.15 | D53: 10841.15 | E53: 0 | F53: =VLOOKUP(B53,'Balance Sheet'!#REF!,2,0) -> #REF!
A54: 10502 | B54: 1515001215 Landed Cost - Parts FH LCL Outbound Actual | C54: -17336.18 | D54: -17336.18 | E54: 0 | F54: =VLOOKUP(B54,'Balance Sheet'!#REF!,2,0) -> #REF!
A55: 10502 | B55: 1515001216 Landed Cost - Parts FH ITL Outbound Actual | C55: -1022.65 | D55: -1022.65 | E55: 0 | F55: =VLOOKUP(B55,'Balance Sheet'!#REF!,2,0) -> #REF!
A56: 10502 | C56: 17086321 | D56: 17086321 | E56: 0 | F56: =VLOOKUP(B56,'Balance Sheet'!#REF!,2,0) -> #REF!
A57: 10503 | B57: 1565000000 WIP Parts | C57: 247348.17 | D57: 247348.17 | E57: 0 | F57: =VLOOKUP(B57,'Balance Sheet'!#REF!,2,0) -> #REF!
A58: 10503 | B58: 1565000010 WIP Parts Salvage | C58: -4793.88 | D58: -4793.88 | E58: 0 | F58: =VLOOKUP(B58,'Balance Sheet'!#REF!,2,0) -> #REF!
A60: 10503 | B60: 1565000016 WIP Parts Minor Component (MICRC) | C60: 946.22 | D60: 946.22 | E60: 0 | F60: =VLOOKUP(B60,'Balance Sheet'!#REF!,2,0) -> #REF!
A61: 10503 | B61: 1565000511 WIP Parts S.O.S. | C61: 56.04 | D61: 56.04 | E61: 0 | F61: =VLOOKUP(B61,'Balance Sheet'!#REF!,2,0) -> #REF!
A62: 10503 | B62: 1566000010 WIP Service Labor | C62: 235157.63 | D62: 235157.63 | E62: 0 | F62: =VLOOKUP(B62,'Balance Sheet'!#REF!,2,0) -> #REF!
A63: 10503 | B63: 1566000020 WIP Service LPO | C63: 8563.98 | D63: 8563.98 | E63: 0 | F63: =VLOOKUP(B63,'Balance Sheet'!#REF!,2,0) -> #REF!
A64: 10503 | B64: 1566000050 WIP Service Travel | C64: 588.54 | D64: 588.54 | E64: 0 | F64: =VLOOKUP(B64,'Balance Sheet'!#REF!,2,0) -> #REF!
A65: 10503 | C65: 487866.7 | D65: 487866.7 | E65: 0 | F65: =VLOOKUP(B65,'Balance Sheet'!#REF!,2,0) -> #REF!
A66: 105 | C66: 17589245 | D66: 17589245 | E66: 0 | F66: =VLOOKUP(B66,'Balance Sheet'!#REF!,2,0) -> #REF!
A67: 10601 | B67: 1661023000 Prepaid Tax ART 23 | C67: 14166.64 | D67: 14166.64 | E67: 0 | F67: =VLOOKUP(B67,'Balance Sheet'!#REF!,2,0) -> #REF!
A68: 10601 | C68: 14166.64 | D68: 14166.64 | E68: 0 | F68: =VLOOKUP(B68,'Balance Sheet'!#REF!,2,0) -> #REF!
A69: 106 | C69: 14166.64 | D69: 14166.64 | E69: 0 | F69: =VLOOKUP(B69,'Balance Sheet'!#REF!,2,0) -> #REF!
A70: 10701 | B70: 1612001010 Prepayment 3rd Party Office Rent | C70: -6135.39 | D70: -6135.39 | E70: 0 | F70: =VLOOKUP(B70,'Balance Sheet'!#REF!,2,0) -> #REF!
A71: 10701 | B71: 1612001020 Prepayment 3rd Party Office Rent Imp (LHI) | C71: 11470.46 | D71: 11470.46 | E71: 0 | F71: =VLOOKUP(B71,'Balance Sheet'!#REF!,2,0) -> #REF!
A72: 10701 | B72: 1612002000 Prepayment Related Party | C72: 6329.17 | D72: 6329.17 | E72: 0 | F72: =VLOOKUP(B72,'Balance Sheet'!#REF!,2,0) -> #REF!
A73: 10701 | B73: 1630000010 Advance To Employee PC Advance | C73: 104.73 | D73: 104.73 | E73: 0 | F73: =VLOOKUP(B73,'Balance Sheet'!#REF!,2,0) -> #REF!
A74: 10701 | B74: 1630000019 Advance To Employee PC Advance FxV | C74: -0.42 | D74: -0.42 | E74: 0 | F74: =VLOOKUP(B74,'Balance Sheet'!#REF!,2,0) -> #REF!
A75: 10701 | B75: 1630000110 Advance To Employee Travel | C75: 53.4 | D75: 53.4 | E75: 0 | F75: =VLOOKUP(B75,'Balance Sheet'!#REF!,2,0) -> #REF!
A76: 10701 | B76: 1630000119 Advance To Employee Travel Adv FxV | C76: 0.01 | D76: 0.01 | E76: 0 | F76: =VLOOKUP(B76,'Balance Sheet'!#REF!,2,0) -> #REF!
A77: 10701 | C77: 11821.96 | D77: 11821.96 | E77: 0 | F77: =VLOOKUP(B77,'Balance Sheet'!#REF!,2,0) -> #REF!
A78: 107 | C78: 11821.96 | D78: 11821.96 | E78: 0 | F78: =VLOOKUP(B78,'Balance Sheet'!#REF!,2,0) -> #REF!
A79: 11001 | B79: 1811102000 FA Acquisition Owned Self Usage Building | C79: 359163.46 | D79: 359163.46 | E79: 0 | F79: =VLOOKUP(B79,'Balance Sheet'!#REF!,2,0) -> #REF!
A80: 11001 | B80: 1821102000 FA Accumulated Depreciation Owned Building | C80: -257037.48 | D80: -257037.48 | E80: 0 | F80: =VLOOKUP(B80,'Balance Sheet'!#REF!,2,0) -> #REF!
A81: 11001 | C81: 102125.98 | D81: 102125.98 | E81: 0 | F81: =VLOOKUP(B81,'Balance Sheet'!#REF!,2,0) -> #REF!
A82: 11003 | B82: 1811115000 FA Acquisition Owned Warehouse Equip | C82: 132848.63 | D82: 132848.63 | E82: 0 | F82: =VLOOKUP(B82,'Balance Sheet'!#REF!,2,0) -> #REF!
A83: 11003 | B83: 1811116000 FA Acquisition Owned Workshop Equip | C83: 476214.59 | D83: 476214.59 | E83: 0 | F83: =VLOOKUP(B83,'Balance Sheet'!#REF!,2,0) -> #REF!
A84: 11003 | B84: 1811117000 FA Acquisition Owned Service Tool | C84: 380546.51 | D84: 380546.51 | E84: 0 | F84: =VLOOKUP(B84,'Balance Sheet'!#REF!,2,0) -> #REF!
A85: 11003 | B85: 1811119000 FA Acquisition Owned Training Center Equipment | C85: 495.24 | D85: 495.24 | E85: 0 | F85: =VLOOKUP(B85,'Balance Sheet'!#REF!,2,0) -> #REF!
A86: 11003 | B86: 1811140000 FA Acquisition Owned Office Equipment | C86: 242483.73 | D86: 242483.73 | E86: 0 | F86: =VLOOKUP(B86,'Balance Sheet'!#REF!,2,0) -> #REF!
A87: 11003 | B87: 1821115000 FA Accumulated Depreciation Owned Warehouse Equip | C87: -125271.34 | D87: -125271.34 | E87: 0 | F87: =VLOOKUP(B87,'Balance Sheet'!#REF!,2,0) -> #REF!
A88: 11003 | B88: 1821116000 FA Accumulated Depreciation Owned Workshop Equip | C88: -291532.8 | D88: -291532.8 | E88: 0 | F88: =VLOOKUP(B88,'Balance Sheet'!#REF!,2,0) -> #REF!
A89: 11003 | B89: 1821117000 FA Accumulated Depreciation Owned Service Tool | C89: -312519.36 | D89: -312519.36 | E89: 0 | F89: =VLOOKUP(B89,'Balance Sheet'!#REF!,2,0) -> #REF!
A90: 11003 | B90: 1821119000 FA Accumulated Depreciation Owned TC Equip | C90: -470.48 | D90: -470.48 | E90: 0 | F90: =VLOOKUP(B90,'Balance Sheet'!#REF!,2,0) -> #REF!
A91: 11003 | B91: 1821140000 FA Accumulated Depreciation Owned Office Equipment | C91: -207242.29 | D91: -207242.29 | E91: 0 | F91: =VLOOKUP(B91,'Balance Sheet'!#REF!,2,0) -> #REF!
A92: 11003 | C92: 295552.43 | D92: 295552.43 | E92: 0 | F92: =VLOOKUP(B92,'Balance Sheet'!#REF!,2,0) -> #REF!
A93: 11004 | B93: 1811301000 FA Acquisition Owned Rental Fleet Machine | C93: 12614053 | D93: 12614053 | E93: 0 | F93: =VLOOKUP(B93,'Balance Sheet'!#REF!,2,0) -> #REF!
A94: 11004 | B94: 1821301000 FA Accumulated Depreciation Owned Rental Fleet Mac | C94: -5009729.1 | D94: -5009729.1 | E94: 0 | F94: =VLOOKUP(B94,'Balance Sheet'!#REF!,2,0) -> #REF!
A95: 11004 | C95: 7604323.8 | D95: 7604323.8 | E95: 0 | F95: =VLOOKUP(B95,'Balance Sheet'!#REF!,2,0) -> #REF!
A96: 11005 | B96: 1811130000 FA Acquisition Owned Vehicle Sedan | C96: 138093.67 | D96: 138093.67 | E96: 0 | F96: =VLOOKUP(B96,'Balance Sheet'!#REF!,2,0) -> #REF!
A97: 11005 | B97: 1811131000 FA Acquisition Owned Vehicle Truck | C97: 855138.11 | D97: 855138.11 | E97: 0 | F97: =VLOOKUP(B97,'Balance Sheet'!#REF!,2,0) -> #REF!
A98: 11005 | B98: 1821130000 FA Accumulated Depreciation Owned Vehicle Sedan | C98: -136815.24 | D98: -136815.24 | E98: 0 | F98: =VLOOKUP(B98,'Balance Sheet'!#REF!,2,0) -> #REF!
A99: 11005 | B99: 1821131000 FA Accumulated Depreciation Owned Vehicle Truck | C99: -865484.74 | D99: -865484.74 | E99: 0 | F99: =VLOOKUP(B99,'Balance Sheet'!#REF!,2,0) -> #REF!
A100: 11005 | C100: -9068.2 | D100: -9068.2 | E100: 0 | F100: =VLOOKUP(B100,'Balance Sheet'!#REF!,2,0) -> #REF!
A101: 11006 | B101: 1811160000 FA Acquisition Owned IT Devices Computer | C101: 3591.93 | D101: 3591.93 | E101: 0 | F101: =VLOOKUP(B101,'Balance Sheet'!#REF!,2,0) -> #REF!
...

Sheet FEB 22
A1: Financial Statement Item | B1: Text for B/S P&L item | C1: Total of reporting period | D1: Total of the comparison period | E1: Absolute difference | F1: Percentage difference | G1: A
A2: 1000000 | B2: A S S E T S | C2: 0 | D2: 0 | E2: 0
A3: 1000000 | B3: = = = = = = | C3: 0 | D3: 0 | E3: 0
A4: 10101 | B4: 1011100380 PettyCash IDR SANGATTA | C4: 329.08 | D4: 329.08 | E4: 0 | F4: 0.0 | G4: =VLOOKUP(B4,'Profit & Loss'!$B$3:$C$390,2,0) -> #N/A
A5: 10101 | B5: 1016109751 Bank IDR Mandiri 1480004169325 MB-SANGATA_COL | C5: 610.44 | D5: 610.44 | E5: 0 | F5: 0.0 | G5: =VLOOKUP(B5,'Profit & Loss'!$B$3:$C$390,2,0) -> #N/A
A6: 10101 | B6: 1016109761 Bank IDR Mandiri 1480004169309 MB-SANGATA_OPR | C6: 27836.1 | D6: 27542.03 | E6: 294.07 | F6: 1.1 | G6: =VLOOKUP(B6,'Profit & Loss'!$B$3:$C$390,2,0) -> #N/A
A7: 10101 | B7: 1016109769 Bank IDR Mandiri 1480004169309 FxV-SANGATA_OPR | C7: -23238.24 | D7: -23245.09 | E7: 6.85 | F7: 0.0 | G7: =VLOOKUP(B7,'Profit & Loss'!$B$3:$C$390,2,0) -> #N/A
A8: 10101 | B8: 1016162071 Bank IDR Mandiri 148-001-687266-8 MB SGT | C8: 68.59 | D8: 68.59 | E8: 0 | F8: 0.0 | G8: =VLOOKUP(B8,'Profit & Loss'!$B$3:$C$390,2,0) -> #N/A
A9: 10101 | B9: 1016162079 Bank IDR Mandiri 148-001-687266-8 FxV SGT | C9: 2.73 | D9: 2.69 | E9: 0.04 | F9: 1.5 | G9: =VLOOKUP(B9,'Profit & Loss'!$B$3:$C$390,2,0) -> #N/A
A10: 10101 | C10: 5608.7 | D10: 5307.74 | E10: 300.96 | F10: 5.7
A11: 101 | C11: 5608.7 | D11: 5307.74 | E11: 300.96 | F11: 5.7
A12: 10201 | B12: 1110101000 AR Gross Trade 3rd Party | C12: 14048204 | D12: 13061995 | E12: 986208.62 | F12: 7.6 | G12: =VLOOKUP(B12,'Profit & Loss'!$B$3:$C$390,2,0) -> #N/A
A13: 10201 | B13: 1110101009 AR Gross Trade 3rd Party FxV | C13: -25280.23 | D13: -65935.64 | E13: 40655.41 | F13: 61.7 | G13: =VLOOKUP(B13,'Profit & Loss'!$B$3:$C$390,2,0) -> #N/A
A14: 10201 | B14: 1110102000 AR Gross Trade Rel Party | C14: 1608482 | D14: 1608482 | E14: 0 | F14: 0.0 | G14: =VLOOKUP(B14,'Profit & Loss'!$B$3:$C$390,2,0) -> #N/A
A15: 10201 | B15: 1110102009 AR Gross Trade Rel Party FxV | C15: -99743.94 | D15: -100611.35 | E15: 867.41 | F15: 0.9 | G15: =VLOOKUP(B15,'Profit & Loss'!$B$3:$C$390,2,0) -> #N/A
A16: 10201 | C16: 15531662 | D16: 14503930 | E16: 1027731.4 | F16: 7.1
A17: 10202 | B17: 1120101000 AR Gross Trade 3rd Party Allowance | C17: -41048.25 | D17: -38389.61 | E17: -2658.64 | F17: 6.9- | G17: =VLOOKUP(B17,'Profit & Loss'!$B$3:$C$390,2,0) -> #N/A
A18: 10202 | C18: -41048.25 | D18: -38389.61 | E18: -2658.64 | F18: 6.9-
A19: 102 | C19: 15490614 | D19: 14465541 | E19: 1025072.8 | F19: 7.1
A20: 10301 | B20: 1211101000 AR Claim Warranty Pending 3rd Party | C20: 0.01 | D20: 0.01 | E20: 0 | F20: 0.0 | G20: =VLOOKUP(B20,'Profit & Loss'!$B$3:$C$390,2,0) -> #N/A
A21: 10301 | B21: 1211201311 AR Claim TWLBR | C21: 6118.96 | D21: 2588.06 | E21: 3530.9 | F21: 136.4 | G21: =VLOOKUP(B21,'Profit & Loss'!$B$3:$C$390,2,0) -> #N/A
A22: 10301 | B22: 1211301000 AR Claim Warranty Claim 3rd Party | C22: 0.01 | D22: 0.01 | E22: 0 | F22: 0.0 | G22: =VLOOKUP(B22,'Profit & Loss'!$B$3:$C$390,2,0) -> #N/A
A23: 10301 | B23: 1211301001 AR Claim Warranty Claim 3rd Party New | C23: 10131.29 | D23: 25403.68 | E23: -15272.39 | F23: 60.1- | G23: =VLOOKUP(B23,'Profit & Loss'!$B$3:$C$390,2,0) -> #N/A
A24: 10301 | B24: 1211401001 AR Claim 3rd Party Goodwill (New Acct) | C24: 14529.03 | D24: 10538.29 | E24: 3990.74 | F24: 37.9 | G24: =VLOOKUP(B24,'Profit & Loss'!$B$3:$C$390,2,0) -> #N/A
A25: 10301 | B25: 1211401310 AR Claim Warranty Claim-Goodwill 3rd Party OEM | C25: 19.35 | D25: 19.35 | E25: 0 | F25: 0.0 | G25: =VLOOKUP(B25,'Profit & Loss'!$B$3:$C$390,2,0) -> #N/A
A26: 10301 | C26: 30798.65 | D26: 38549.4 | E26: -7750.75 | F26: 20.1-
A27: 10302 | B27: 1212001010 AR Claim 3rd Party CAT Parts Core | C27: 6663.53 | D27: 17751.83 | E27: -11088.3 | F27: 62.5- | G27: =VLOOKUP(B27,'Profit & Loss'!$B$3:$C$390,2,0) -> #N/A
A28: 10302 | C28: 6663.53 | D28: 17751.83 | E28: -11088.3 | F28: 62.5-
A29: 10306 | B29: 1110101230 AR Gross Trade 3rd Party Art23 | C29: 51364.45 | D29: 55428.1 | E29: -4063.65 | F29: 7.3- | G29: =VLOOKUP(B29,'Profit & Loss'!$B$3:$C$390,2,0) -> #N/A
A30: 10306 | B30: 1110101239 AR Gross Trade 3rd Party Art23 FxV | C30: -95.7 | D30: -238.21 | E30: 142.51 | F30: 59.8 | G30: =VLOOKUP(B30,'Profit & Loss'!$B$3:$C$390,2,0) -> #N/A
A31: 10306 | B31: 1110102230 AR Gross Trade Rel Party Art23 | C31: 0 | D31: 601.35 | E31: -601.35 | F31: 100.0- | G31: =VLOOKUP(B31,'Profit & Loss'!$B$3:$C$390,2,0) -> #N/A
A32: 10306 | B32: 1110102239 AR Gross Trade Rel Party Art23 FxV | C32: 0 | D32: -4.27 | E32: 4.27 | F32: 100.0 | G32: =VLOOKUP(B32,'Profit & Loss'!$B$3:$C$390,2,0) -> #N/A
A33: 10306 | B33: 1110181000 AR Gross Others Project System Over Under | C33: 2597.52 | D33: 2597.52 | E33: 0 | F33: 0.0 | G33: =VLOOKUP(B33,'Profit & Loss'!$B$3:$C$390,2,0) -> #N/A
A34: 10306 | B34: 1110201000 AR Gross Non Trade 3rd Party | C34: -216227.47 | D34: 0 | E34: -216227.47 | G34: =VLOOKUP(B34,'Profit & Loss'!$B$3:$C$390,2,0) -> #N/A
A35: 10306 | B35: 1110201009 AR Gross Non Trade 3rd Party FxV | C35: 149.64 | D35: 0 | E35: 149.64 | G35: =VLOOKUP(B35,'Profit & Loss'!$B$3:$C$390,2,0) -> #N/A
A36: 10306 | B36: 1110202000 AR Gross Non Trade Rel Party | C36: 0 | D36: 2611.46 | E36: -2611.46 | F36: 100.0- | G36: =VLOOKUP(B36,'Profit & Loss'!$B$3:$C$390,2,0) -> #N/A
A37: 10306 | B37: 1110202009 AR Gross Non Trade Rel Party FxV | C37: 0 | D37: -5.3 | E37: 5.3 | F37: 100.0 | G37: =VLOOKUP(B37,'Profit & Loss'!$B$3:$C$390,2,0) -> #N/A
A38: 10306 | B38: 1216001020 AR Claim 3rd Party CAT PSDN | C38: -1319.57 | D38: 7323.97 | E38: -8643.54 | F38: 118.0- | G38: =VLOOKUP(B38,'Profit & Loss'!$B$3:$C$390,2,0) -> #N/A
A39: 10306 | B39: 1219301000 AR Claim Others 3rd Party | C39: 2971.13 | D39: 2618.36 | E39: 352.77 | F39: 13.5 | G39: =VLOOKUP(B39,'Profit & Loss'!$B$3:$C$390,2,0) -> #N/A
A40: 10306 | B40: 1219302070 AR Claim Others Rel Party CKB | C40: 40.25 | D40: 40.38 | E40: -0.13 | F40: 0.3- | G40: =VLOOKUP(B40,'Profit & Loss'!$B$3:$C$390,2,0) -> #N/A
A41: 10306 | C41: -160519.75 | D41: 70973.36 | E41: -231493.11 | F41: 326.2-
A42: 103 | C42: -123057.57 | D42: 127274.59 | E42: -250332.16 | F42: 196.7-
A43: 10501 | B43: 1411191200 Inventory PP Freight & Handling (CLEARING) | C43: -0.1 | D43: -0.1 | E43: 0 | F43: 0.0 | G43: =VLOOKUP(B43,'Profit & Loss'!$B$3:$C$390,2,0) -> #N/A
A44: 10501 | B44: 1411198000 Inventory PP Non CAT Accessories | C44: -33464.48 | D44: 13388.01 | E44: -46852.49 | F44: 350.0- | G44: =VLOOKUP(B44,'Profit & Loss'!$B$3:$C$390,2,0) -> #N/A
A45: 10501 | B45: 1460200000 Inventory PP GIT Non Trade | C45: 1668.98 | D45: 1668.98 | E45: 0 | F45: 0.0 | G45: =VLOOKUP(B45,'Profit & Loss'!$B$3:$C$390,2,0) -> #N/A
A46: 10501 | C46: -31795.6 | D46: 15056.89 | E46: -46852.49 | F46: 311.2-
A47: 10502 | B47: 1415101000 Inventory Parts Stock On Hand | C47: 10866254 | D47: 12826014 | E47: -1959760.3 | F47: 15.3- | G47: =VLOOKUP(B47,'Profit & Loss'!$B$3:$C$390,2,0) -> #N/A
A48: 10502 | B48: 1415141000 Inventory Parts PVRG | C48: 0 | D48: -1140.94 | E48: 1140.94 | F48: 100.0 | G48: =VLOOKUP(B48,'Profit & Loss'!$B$3:$C$390,2,0) -> #N/A
A49: 10502 | B49: 1415141666 Inventory Parts PVRG SPM - SOA | C49: 175592.08 | D49: 36331.37 | E49: 139260.71 | F49: 383.3 | G49: =VLOOKUP(B49,'Profit & Loss'!$B$3:$C$390,2,0) -> #N/A
A50: 10502 | B50: 1415192000 Inventory Parts Gross Hub Turn Over | C50: 1033498.6 | D50: 909825 | E50: 123673.64 | F50: 13.6 | G50: =VLOOKUP(B50,'Profit & Loss'!$B$3:$C$390,2,0) -> #N/A
A51: 10502 | B51: 1461001210 Inventory Parts GINI | C51: 2040396.8 | D51: 1970301.9 | E51: 70094.95 | F51: 3.6 | G51: =VLOOKUP(B51,'Profit & Loss'!$B$3:$C$390,2,0) -> #N/A
A52: 10502 | B52: 1465011000 Inventory Parts GIT | C52: 3211252.8 | D52: 2830113.3 | E52: 381139.5 | F52: 13.5 | G52: =VLOOKUP(B52,'Profit & Loss'!$B$3:$C$390,2,0) -> #N/A
A53: 10502 | B53: 1465011002 Inventory Parts Freight & Handling (CLEARING) | C53: 29295.38 | D53: 24644.4 | E53: 4650.98 | F53: 18.9 | G53: =VLOOKUP(B53,'Profit & Loss'!$B$3:$C$390,2,0) -> #N/A
A54: 10502 | B54: 1515001213 Landed Cost - Parts FH ITL Inbound Actual | C54: -1498165.6 | D54: -1502250.4 | E54: 4084.77 | F54: 0.3 | G54: =VLOOKUP(B54,'Profit & Loss'!$B$3:$C$390,2,0) -> #N/A
A55: 10502 | B55: 1515001214 Landed Cost - Parts FH LCL Inbound Actual | C55: 12096.12 | D55: 10841.15 | E55: 1254.97 | F55: 11.6 | G55: =VLOOKUP(B55,'Profit & Loss'!$B$3:$C$390,2,0) -> #N/A
A56: 10502 | B56: 1515001215 Landed Cost - Parts FH LCL Outbound Actual | C56: -17464.92 | D56: -17336.18 | E56: -128.74 | F56: 0.7- | G56: =VLOOKUP(B56,'Profit & Loss'!$B$3:$C$390,2,0) -> #N/A
A57: 10502 | B57: 1515001216 Landed Cost - Parts FH ITL Outbound Actual | C57: -1693.06 | D57: -1022.65 | E57: -670.41 | F57: 65.6- | G57: =VLOOKUP(B57,'Profit & Loss'!$B$3:$C$390,2,0) -> #N/A
A58: 10502 | C58: 15851062 | D58: 17086321 | E58: -1235259 | F58: 7.2-
A59: 10503 | B59: 1565000000 WIP Parts | C59: 464607.53 | D59: 247348.17 | E59: 217259.36 | F59: 87.8 | G59: =VLOOKUP(B59,'Profit & Loss'!$B$3:$C$390,2,0) -> #N/A
A60: 10503 | B60: 1565000010 WIP Parts Salvage | C60: -4793.88 | D60: -4793.88 | E60: 0 | F60: 0.0 | G60: =VLOOKUP(B60,'Profit & Loss'!$B$3:$C$390,2,0) -> #N/A
A61: 10503 | B61: 1565000016 WIP Parts Minor Component (MICRC) | C61: 946.22 | D61: 946.22 | E61: 0 | F61: 0.0 | G61: =VLOOKUP(B61,'Profit & Loss'!$B$3:$C$390,2,0) -> #N/A
A62: 10503 | B62: 1565000511 WIP Parts S.O.S. | C62: 94.38 | D62: 56.04 | E62: 38.34 | F62: 68.4 | G62: =VLOOKUP(B62,'Profit & Loss'!$B$3:$C$390,2,0) -> #N/A
A63: 10503 | B63: 1566000010 WIP Service Labor | C63: 249658.84 | D63: 235157.63 | E63: 14501.21 | F63: 6.2 | G63: =VLOOKUP(B63,'Profit & Loss'!$B$3:$C$390,2,0) -> #N/A
A64: 10503 | B64: 1566000020 WIP Service LPO | C64: 29970.55 | D64: 8563.98 | E64: 21406.57 | F64: 250.0 | G64: =VLOOKUP(B64,'Profit & Loss'!$B$3:$C$390,2,0) -> #N/A
A65: 10503 | B65: 1566000050 WIP Service Travel | C65: 432.91 | D65: 588.54 | E65: -155.63 | F65: 26.4- | G65: =VLOOKUP(B65,'Profit & Loss'!$B$3:$C$390,2,0) -> #N/A
A66: 10503 | C66: 740916.55 | D66: 487866.7 | E66: 253049.85 | F66: 51.9
A67: 105 | C67: 16560183 | D67: 17589245 | E67: -1029061.7 | F67: 5.9-
A68: 10601 | B68: 1661023000 Prepaid Tax ART 23 | C68: 14166.64 | D68: 14166.64 | E68: 0 | F68: 0.0 | G68: =VLOOKUP(B68,'Profit & Loss'!$B$3:$C$390,2,0) -> #N/A
A69: 10601 | C69: 14166.64 | D69: 14166.64 | E69: 0 | F69: 0.0
A70: 106 | C70: 14166.64 | D70: 14166.64 | E70: 0 | F70: 0.0
A71: 10701 | B71: 1612001010 Prepayment 3rd Party Office Rent | C71: -6135.39 | D71: -6135.39 | E71: 0 | F71: 0.0 | G71: =VLOOKUP(B71,'Profit & Loss'!$B$3:$C$390,2,0) -> #N/A
A72: 10701 | B72: 1612001020 Prepayment 3rd Party Office Rent Imp (LHI) | C72: 10893.75 | D72: 11470.46 | E72: -576.71 | F72: 5.0- | G72: =VLOOKUP(B72,'Profit & Loss'!$B$3:$C$390,2,0) -> #N/A
A73: 10701 | B73: 1612002000 Prepayment Related Party | C73: 6329.17 | D73: 6329.17 | E73: 0 | F73: 0.0 | G73: =VLOOKUP(B73,'Profit & Loss'!$B$3:$C$390,2,0) -> #N/A
A74: 10701 | B74: 1630000010 Advance To Employee PC Advance | C74: 558.74 | D74: 104.73 | E74: 454.01 | F74: 433.5 | G74: =VLOOKUP(B74,'Profit & Loss'!$B$3:$C$390,2,0) -> #N/A
A75: 10701 | B75: 1630000019 Advance To Employee PC Advance FxV | C75: -2.1 | D75: -0.42 | E75: -1.68 | F75: 400.0- | G75: =VLOOKUP(B75,'Profit & Loss'!$B$3:$C$390,2,0) -> #N/A
A76: 10701 | B76: 1630000110 Advance To Employee Travel | C76: -85.94 | D76: 53.4 | E76: -139.34 | F76: 260.9- | G76: =VLOOKUP(B76,'Profit & Loss'!$B$3:$C$390,2,0) -> #N/A
A77: 10701 | B77: 1630000119 Advance To Employee Travel Adv FxV | C77: -0.44 | D77: 0.01 | E77: -0.45 | F77: 4,500.0- | G77: =VLOOKUP(B77,'Profit & Loss'!$B$3:$C$390,2,0) -> #N/A
A78: 10701 | C78: 11557.79 | D78: 11821.96 | E78: -264.17 | F78: 2.2-
A79: 107 | C79: 11557.79 | D79: 11821.96 | E79: -264.17 | F79: 2.2-
A80: 11001 | B80: 1811102000 FA Acquisition Owned Self Usage Building | C80: 359163.46 | D80: 359163.46 | E80: 0 | F80: 0.0 | G80: =VLOOKUP(B80,'Profit & Loss'!$B$3:$C$390,2,0) -> #N/A
A81: 11001 | B81: 1821102000 FA Accumulated Depreciation Owned Building | C81: -258152.24 | D81: -257037.48 | E81: -1114.76 | F81: 0.4- | G81: =VLOOKUP(B81,'Profit & Loss'!$B$3:$C$390,2,0) -> #N/A
A82: 11001 | C82: 101011.22 | D82: 102125.98 | E82: -1114.76 | F82: 1.1-
A83: 11003 | B83: 1811115000 FA Acquisition Owned Warehouse Equip | C83: 132848.63 | D83: 132848.63 | E83: 0 | F83: 0.0 | G83: =VLOOKUP(B83,'Profit & Loss'!$B$3:$C$390,2,0) -> #N/A
A84: 11003 | B84: 1811116000 FA Acquisition Owned Workshop Equip | C84: 476214.59 | D84: 476214.59 | E84: 0 | F84: 0.0 | G84: =VLOOKUP(B84,'Profit & Loss'!$B$3:$C$390,2,0) -> #N/A
A85: 11003 | B85: 1811117000 FA Acquisition Owned Service Tool | C85: 390466.49 | D85: 380546.51 | E85: 9919.98 | F85: 2.6 | G85: =VLOOKUP(B85,'Profit & Loss'!$B$3:$C$390,2,0) -> #N/A
A86: 11003 | B86: 1811119000 FA Acquisition Owned Training Center Equipment | C86: 495.24 | D86: 495.24 | E86: 0 | F86: 0.0 | G86: =VLOOKUP(B86,'Profit & Loss'!$B$3:$C$390,2,0) -> #N/A
A87: 11003 | B87: 1811140000 FA Acquisition Owned Office Equipment | C87: 242483.73 | D87: 242483.73 | E87: 0 | F87: 0.0 | G87: =VLOOKUP(B87,'Profit & Loss'!$B$3:$C$390,2,0) -> #N/A
A88: 11003 | B88: 1821115000 FA Accumulated Depreciation Owned Warehouse Equip | C88: -125545.89 | D88: -125271.34 | E88: -274.55 | F88: 0.2- | G88: =VLOOKUP(B88,'Profit & Loss'!$B$3:$C$390,2,0) -> #N/A
A89: 11003 | B89: 1821116000 FA Accumulated Depreciation Owned Workshop Equip | C89: -295037.25 | D89: -291532.8 | E89: -3504.45 | F89: 1.2- | G89: =VLOOKUP(B89,'Profit & Loss'!$B$3:$C$390,2,0) -> #N/A
A90: 11003 | B90: 1821117000 FA Accumulated Depreciation Owned Service Tool | C90: -314663.27 | D90: -312519.36 | E90: -2143.91 | F90: 0.7- | G90: =VLOOKUP(B90,'Profit & Loss'!$B$3:$C$390,2,0) -> #N/A
A91: 11003 | B91: 1821119000 FA Accumulated Depreciation Owned TC Equip | C91: -478.74 | D91: -470.48 | E91: -8.26 | F91: 1.8- | G91: =VLOOKUP(B91,'Profit & Loss'!$B$3:$C$390,2,0) -> #N/A
A92: 11003 | B92: 1821140000 FA Accumulated Depreciation Owned Office Equipment | C92: -208362.78 | D92: -207242.29 | E92: -1120.49 | F92: 0.5- | G92: =VLOOKUP(B92,'Profit & Loss'!$B$3:$C$390,2,0) -> #N/A
A93: 11003 | C93: 298420.75 | D93: 295552.43 | E93: 2868.32 | F93: 1.0
A94: 11004 | B94: 1811301000 FA Acquisition Owned Rental Fleet Machine | C94: 13606620 | D94: 12614053 | E94: 992566.88 | F94: 7.9 | G94: =VLOOKUP(B94,'Profit & Loss'!$B$3:$C$390,2,0) -> #N/A
A95: 11004 | B95: 1821301000 FA Accumulated Depreciation Owned Rental Fleet Mac | C95: -5175179.6 | D95: -5009729.1 | E95: -165450.48 | F95: 3.3- | G95: =VLOOKUP(B95,'Profit & Loss'!$B$3:$C$390,2,0) -> #N/A
A96: 11004 | C96: 8431440.2 | D96: 7604323.8 | E96: 827116.4 | F96: 10.9
A97: 11005 | B97: 1811130000 FA Acquisition Owned Vehicle Sedan | C97: 138093.67 | D97: 138093.67 | E97: 0 | F97: 0.0 | G97: =VLOOKUP(B97,'Profit & Loss'!$B$3:$C$390,2,0) -> #N/A
A98: 11005 | B98: 1811131000 FA Acquisition Owned Vehicle Truck | C98: 855138.11 | D98: 855138.11 | E98: 0 | F98: 0.0 | G98: =VLOOKUP(B98,'Profit & Loss'!$B$3:$C$390,2,0) -> #N/A
A99: 11005 | B99: 1821130000 FA Accumulated Depreciation Owned Vehicle Sedan | C99: -136870.83 | D99: -136815.24 | E99: -55.59 | F99: 0.0 | G99: =VLOOKUP(B99,'Profit & Loss'!$B$3:$C$390,2,0) -> #N/A
A100: 11005 | B100: 1821131000 FA Accumulated Depreciation Owned Vehicle Truck | C100: -867914.9 | D100: -865484.74 | E100: -2430.16 | F100: 0.3- | G100: =VLOOKUP(B100,'Profit & Loss'!$B$3:$C$390,2,0) -> #N/A
...

Sheet MAR 22
A1: Financial Statement Item | B1: Text for B/S P&L item | C1: Total of reporting period | D1: Total of the comparison period | E1: Absolute difference | F1: Percentage difference | G1: A
A2: 1000000 | B2: A S S E T S | C2: 0 | D2: 0 | E2: 0 | G2: =VLOOKUP(B2,'Profit & Loss'!$B$3:$C$390,2,0) -> #N/A
A3: 1000000 | B3: = = = = = = | C3: 0 | D3: 0 | E3: 0 | G3: =VLOOKUP(B3,'Profit & Loss'!$B$3:$C$390,2,0) -> #N/A
A4: 10101 | B4: 1011100380 PettyCash IDR SANGATTA | C4: 329.08 | D4: 329.08 | E4: 0 | F4: 0.0 | G4: =VLOOKUP(B4,'Profit & Loss'!$B$3:$C$390,2,0) -> #N/A
A5: 10101 | B5: 1016109751 Bank IDR Mandiri 1480004169325 MB-SANGATA_COL | C5: 610.44 | D5: 610.44 | E5: 0 | F5: 0.0 | G5: =VLOOKUP(B5,'Profit & Loss'!$B$3:$C$390,2,0) -> #N/A
A6: 10101 | B6: 1016109761 Bank IDR Mandiri 1480004169309 MB-SANGATA_OPR | C6: 26519.23 | D6: 27836.1 | E6: -1316.87 | F6: 4.7- | G6: =VLOOKUP(B6,'Profit & Loss'!$B$3:$C$390,2,0) -> #N/A
A7: 10101 | B7: 1016109769 Bank IDR Mandiri 1480004169309 FxV-SANGATA_OPR | C7: -23252.66 | D7: -23238.24 | E7: -14.42 | F7: 0.1- | G7: =VLOOKUP(B7,'Profit & Loss'!$B$3:$C$390,2,0) -> #N/A
A8: 10101 | B8: 1016162071 Bank IDR Mandiri 148-001-687266-8 MB SGT | C8: 68.59 | D8: 68.59 | E8: 0 | F8: 0.0 | G8: =VLOOKUP(B8,'Profit & Loss'!$B$3:$C$390,2,0) -> #N/A
A9: 10101 | B9: 1016162079 Bank IDR Mandiri 148-001-687266-8 FxV SGT | C9: 2.84 | D9: 2.73 | E9: 0.11 | F9: 4.0 | G9: =VLOOKUP(B9,'Profit & Loss'!$B$3:$C$390,2,0) -> #N/A
A10: 10101 | C10: 4277.52 | D10: 5608.7 | E10: -1331.18 | F10: 23.7- | G10: =VLOOKUP(B10,'Profit & Loss'!$B$3:$C$390,2,0) -> #N/A
A11: 101 | C11: 4277.52 | D11: 5608.7 | E11: -1331.18 | F11: 23.7- | G11: =VLOOKUP(B11,'Profit & Loss'!$B$3:$C$390,2,0) -> #N/A
A12: 10201 | B12: 1110101000 AR Gross Trade 3rd Party | C12: 13924123 | D12: 14048204 | E12: -124080.96 | F12: 0.9- | G12: =VLOOKUP(B12,'Profit & Loss'!$B$3:$C$390,2,0) -> #N/A
A13: 10201 | B13: 1110101009 AR Gross Trade 3rd Party FxV | C13: 10113.67 | D13: -25280.23 | E13: 35393.9 | F13: 140.0 | G13: =VLOOKUP(B13,'Profit & Loss'!$B$3:$C$390,2,0) -> #N/A
A14: 10201 | B14: 1110102000 AR Gross Trade Rel Party | C14: 1601828.4 | D14: 1608482 | E14: -6653.55 | F14: 0.4- | G14: =VLOOKUP(B14,'Profit & Loss'!$B$3:$C$390,2,0) -> #N/A
A15: 10201 | B15: 1110102009 AR Gross Trade Rel Party FxV | C15: -97348.32 | D15: -99743.94 | E15: 2395.62 | F15: 2.4 | G15: =VLOOKUP(B15,'Profit & Loss'!$B$3:$C$390,2,0) -> #N/A
A16: 10201 | C16: 15438717 | D16: 15531662 | E16: -92944.99 | F16: 0.6- | G16: =VLOOKUP(B16,'Profit & Loss'!$B$3:$C$390,2,0) -> #N/A
A17: 10202 | B17: 1120101000 AR Gross Trade 3rd Party Allowance | C17: -40127.62 | D17: -41048.25 | E17: 920.63 | F17: 2.2 | G17: =VLOOKUP(B17,'Profit & Loss'!$B$3:$C$390,2,0) -> #N/A
A18: 10202 | C18: -40127.62 | D18: -41048.25 | E18: 920.63 | F18: 2.2 | G18: =VLOOKUP(B18,'Profit & Loss'!$B$3:$C$390,2,0) -> #N/A
A19: 102 | C19: 15398589 | D19: 15490614 | E19: -92024.36 | F19: 0.6- | G19: =VLOOKUP(B19,'Profit & Loss'!$B$3:$C$390,2,0) -> #N/A
A20: 10301 | B20: 1211101000 AR Claim Warranty Pending 3rd Party | C20: 0.01 | D20: 0.01 | E20: 0 | F20: 0.0 | G20: =VLOOKUP(B20,'Profit & Loss'!$B$3:$C$390,2,0) -> #N/A
A21: 10301 | B21: 1211201311 AR Claim TWLBR | C21: 42291.62 | D21: 6118.96 | E21: 36172.66 | F21: 591.2 | G21: =VLOOKUP(B21,'Profit & Loss'!$B$3:$C$390,2,0) -> #N/A
A22: 10301 | B22: 1211301000 AR Claim Warranty Claim 3rd Party | C22: 0.01 | D22: 0.01 | E22: 0 | F22: 0.0 | G22: =VLOOKUP(B22,'Profit & Loss'!$B$3:$C$390,2,0) -> #N/A
A23: 10301 | B23: 1211301001 AR Claim Warranty Claim 3rd Party New | C23: 27128.57 | D23: 10131.29 | E23: 16997.28 | F23: 167.8 | G23: =VLOOKUP(B23,'Profit & Loss'!$B$3:$C$390,2,0) -> #N/A
A24: 10301 | B24: 1211401001 AR Claim 3rd Party Goodwill (New Acct) | C24: 46253.61 | D24: 14529.03 | E24: 31724.58 | F24: 218.4 | G24: =VLOOKUP(B24,'Profit & Loss'!$B$3:$C$390,2,0) -> #N/A
A25: 10301 | B25: 1211401310 AR Claim Warranty Claim-Goodwill 3rd Party OEM | C25: 19.35 | D25: 19.35 | E25: 0 | F25: 0.0 | G25: =VLOOKUP(B25,'Profit & Loss'!$B$3:$C$390,2,0) -> #N/A
A26: 10301 | C26: 115693.17 | D26: 30798.65 | E26: 84894.52 | F26: 275.6 | G26: =VLOOKUP(B26,'Profit & Loss'!$B$3:$C$390,2,0) -> #N/A
A27: 10302 | B27: 1212001010 AR Claim 3rd Party CAT Parts Core | C27: -7566.42 | D27: 6663.53 | E27: -14229.95 | F27: 213.5- | G27: =VLOOKUP(B27,'Profit & Loss'!$B$3:$C$390,2,0) -> #N/A
A28: 10302 | C28: -7566.42 | D28: 6663.53 | E28: -14229.95 | F28: 213.5- | G28: =VLOOKUP(B28,'Profit & Loss'!$B$3:$C$390,2,0) -> #N/A
A29: 10306 | B29: 1110101230 AR Gross Trade 3rd Party Art23 | C29: 67008.31 | D29: 51364.45 | E29: 15643.86 | F29: 30.5 | G29: =VLOOKUP(B29,'Profit & Loss'!$B$3:$C$390,2,0) -> #N/A
A30: 10306 | B30: 1110101239 AR Gross Trade 3rd Party Art23 FxV | C30: 14.94 | D30: -95.7 | E30: 110.64 | F30: 115.6 | G30: =VLOOKUP(B30,'Profit & Loss'!$B$3:$C$390,2,0) -> #N/A
A31: 10306 | B31: 1110102230 AR Gross Trade Rel Party Art23 | C31: 277.08 | D31: 0 | E31: 277.08 | G31: =VLOOKUP(B31,'Profit & Loss'!$B$3:$C$390,2,0) -> #N/A
A32: 10306 | B32: 1110102239 AR Gross Trade Rel Party Art23 FxV | C32: 1.19 | D32: 0 | E32: 1.19 | G32: =VLOOKUP(B32,'Profit & Loss'!$B$3:$C$390,2,0) -> #N/A
A33: 10306 | B33: 1110181000 AR Gross Others Project System Over Under | C33: 2597.52 | D33: 2597.52 | E33: 0 | F33: 0.0 | G33: =VLOOKUP(B33,'Profit & Loss'!$B$3:$C$390,2,0) -> #N/A
A34: 10306 | B34: 1110201000 AR Gross Non Trade 3rd Party | C34: 0 | D34: -216227.47 | E34: 216227.47 | F34: 100.0 | G34: =VLOOKUP(B34,'Profit & Loss'!$B$3:$C$390,2,0) -> #N/A
A35: 10306 | B35: 1110201009 AR Gross Non Trade 3rd Party FxV | C35: 0 | D35: 149.64 | E35: -149.64 | F35: 100.0- | G35: =VLOOKUP(B35,'Profit & Loss'!$B$3:$C$390,2,0) -> #N/A
A36: 10306 | B36: 1216001020 AR Claim 3rd Party CAT PSDN | C36: 348.54 | D36: -1319.57 | E36: 1668.11 | F36: 126.4 | G36: =VLOOKUP(B36,'Profit & Loss'!$B$3:$C$390,2,0) -> #N/A
A37: 10306 | B37: 1219301000 AR Claim Others 3rd Party | C37: 2821.42 | D37: 2971.13 | E37: -149.71 | F37: 5.0- | G37: =VLOOKUP(B37,'Profit & Loss'!$B$3:$C$390,2,0) -> #N/A
A38: 10306 | B38: 1219301009 AR Claim Others 3rd Party FxV | C38: -0.35 | D38: 0 | E38: -0.35 | G38: =VLOOKUP(B38,'Profit & Loss'!$B$3:$C$390,2,0) -> #N/A
A39: 10306 | B39: 1219302070 AR Claim Others Rel Party CKB | C39: 39.9 | D39: 40.25 | E39: -0.35 | F39: 0.9- | G39: =VLOOKUP(B39,'Profit & Loss'!$B$3:$C$390,2,0) -> #N/A
A40: 10306 | C40: 73108.55 | D40: -160519.75 | E40: 233628.3 | F40: 145.5 | G40: =VLOOKUP(B40,'Profit & Loss'!$B$3:$C$390,2,0) -> #N/A
A41: 103 | C41: 181235.3 | D41: -123057.57 | E41: 304292.87 | F41: 247.3 | G41: =VLOOKUP(B41,'Profit & Loss'!$B$3:$C$390,2,0) -> #N/A
A42: 10501 | B42: 1411191200 Inventory PP Freight & Handling (CLEARING) | C42: -0.1 | D42: -0.1 | E42: 0 | F42: 0.0 | G42: =VLOOKUP(B42,'Profit & Loss'!$B$3:$C$390,2,0) -> #N/A
A43: 10501 | B43: 1411198000 Inventory PP Non CAT Accessories | C43: -33464.48 | D43: -33464.48 | E43: 0 | F43: 0.0 | G43: =VLOOKUP(B43,'Profit & Loss'!$B$3:$C$390,2,0) -> #N/A
A44: 10501 | B44: 1460200000 Inventory PP GIT Non Trade | C44: 1668.98 | D44: 1668.98 | E44: 0 | F44: 0.0 | G44: =VLOOKUP(B44,'Profit & Loss'!$B$3:$C$390,2,0) -> #N/A
A45: 10501 | C45: -31795.6 | D45: -31795.6 | E45: 0 | F45: 0.0 | G45: =VLOOKUP(B45,'Profit & Loss'!$B$3:$C$390,2,0) -> #N/A
A46: 10502 | B46: 1415101000 Inventory Parts Stock On Hand | C46: 11629217 | D46: 10866254 | E46: 762963.1 | F46: 7.0 | G46: =VLOOKUP(B46,'Profit & Loss'!$B$3:$C$390,2,0) -> #N/A
A47: 10502 | B47: 1415111800 Inventory Parts PEX Core Raw Material | C47: 836.37 | D47: 0 | E47: 836.37 | G47: =VLOOKUP(B47,'Profit & Loss'!$B$3:$C$390,2,0) -> #N/A
A48: 10502 | B48: 1415141666 Inventory Parts PVRG SPM - SOA | C48: 273943.08 | D48: 175592.08 | E48: 98351 | F48: 56.0 | G48: =VLOOKUP(B48,'Profit & Loss'!$B$3:$C$390,2,0) -> #N/A
A49: 10502 | B49: 1415192000 Inventory Parts Gross Hub Turn Over | C49: 1525955.1 | D49: 1033498.6 | E49: 492456.47 | F49: 47.6 | G49: =VLOOKUP(B49,'Profit & Loss'!$B$3:$C$390,2,0) -> #N/A
A50: 10502 | B50: 1461001210 Inventory Parts GINI | C50: 1713481.5 | D50: 2040396.8 | E50: -326915.3 | F50: 16.0- | G50: =VLOOKUP(B50,'Profit & Loss'!$B$3:$C$390,2,0) -> #N/A
A51: 10502 | B51: 1465011000 Inventory Parts GIT | C51: 3762968.1 | D51: 3211252.8 | E51: 551715.34 | F51: 17.2 | G51: =VLOOKUP(B51,'Profit & Loss'!$B$3:$C$390,2,0) -> #N/A
A52: 10502 | B52: 1465011002 Inventory Parts Freight & Handling (CLEARING) | C52: 18980.04 | D52: 29295.38 | E52: -10315.34 | F52: 35.2- | G52: =VLOOKUP(B52,'Profit & Loss'!$B$3:$C$390,2,0) -> #N/A
A53: 10502 | B53: 1515001213 Landed Cost - Parts FH ITL Inbound Actual | C53: -1413605.4 | D53: -1498165.6 | E53: 84560.28 | F53: 5.6 | G53: =VLOOKUP(B53,'Profit & Loss'!$B$3:$C$390,2,0) -> #N/A
A54: 10502 | B54: 1515001214 Landed Cost - Parts FH LCL Inbound Actual | C54: 14874.62 | D54: 12096.12 | E54: 2778.5 | F54: 23.0 | G54: =VLOOKUP(B54,'Profit & Loss'!$B$3:$C$390,2,0) -> #N/A
A55: 10502 | B55: 1515001215 Landed Cost - Parts FH LCL Outbound Actual | C55: -19907.25 | D55: -17464.92 | E55: -2442.33 | F55: 14.0- | G55: =VLOOKUP(B55,'Profit & Loss'!$B$3:$C$390,2,0) -> #N/A
A56: 10502 | B56: 1515001216 Landed Cost - Parts FH ITL Outbound Actual | C56: 335.4 | D56: -1693.06 | E56: 2028.46 | F56: 119.8 | G56: =VLOOKUP(B56,'Profit & Loss'!$B$3:$C$390,2,0) -> #N/A
A57: 10502 | C57: 17507079 | D57: 15851062 | E57: 1656016.6 | F57: 10.4 | G57: =VLOOKUP(B57,'Profit & Loss'!$B$3:$C$390,2,0) -> #N/A
A58: 10503 | B58: 1565000000 WIP Parts | C58: 275669.67 | D58: 464607.53 | E58: -188937.86 | F58: 40.7- | G58: =VLOOKUP(B58,'Profit & Loss'!$B$3:$C$390,2,0) -> #N/A
A59: 10503 | B59: 1565000010 WIP Parts Salvage | C59: -4793.88 | D59: -4793.88 | E59: 0 | F59: 0.0 | G59: =VLOOKUP(B59,'Profit & Loss'!$B$3:$C$390,2,0) -> #N/A
A60: 10503 | B60: 1565000016 WIP Parts Minor Component (MICRC) | C60: 946.22 | D60: 946.22 | E60: 0 | F60: 0.0 | G60: =VLOOKUP(B60,'Profit & Loss'!$B$3:$C$390,2,0) -> #N/A
A61: 10503 | B61: 1565000511 WIP Parts S.O.S. | C61: 238.46 | D61: 94.38 | E61: 144.08 | F61: 152.7 | G61: =VLOOKUP(B61,'Profit & Loss'!$B$3:$C$390,2,0) -> #N/A
A62: 10503 | B62: 1566000010 WIP Service Labor | C62: 226446.67 | D62: 249658.84 | E62: -23212.17 | F62: 9.3- | G62: =VLOOKUP(B62,'Profit & Loss'!$B$3:$C$390,2,0) -> #N/A
A63: 10503 | B63: 1566000020 WIP Service LPO | C63: 59012.47 | D63: 29970.55 | E63: 29041.92 | F63: 96.9 | G63: =VLOOKUP(B63,'Profit & Loss'!$B$3:$C$390,2,0) -> #N/A
A64: 10503 | B64: 1566000050 WIP Service Travel | C64: 420.63 | D64: 432.91 | E64: -12.28 | F64: 2.8- | G64: =VLOOKUP(B64,'Profit & Loss'!$B$3:$C$390,2,0) -> #N/A
A65: 10503 | C65: 557940.24 | D65: 740916.55 | E65: -182976.31 | F65: 24.7- | G65: =VLOOKUP(B65,'Profit & Loss'!$B$3:$C$390,2,0) -> #N/A
A66: 105 | C66: 18033223 | D66: 16560183 | E66: 1473040.2 | F66: 8.9 | G66: =VLOOKUP(B66,'Profit & Loss'!$B$3:$C$390,2,0) -> #N/A
A67: 10601 | B67: 1661023000 Prepaid Tax ART 23 | C67: 14166.64 | D67: 14166.64 | E67: 0 | F67: 0.0 | G67: =VLOOKUP(B67,'Profit & Loss'!$B$3:$C$390,2,0) -> #N/A
A68: 10601 | C68: 14166.64 | D68: 14166.64 | E68: 0 | F68: 0.0 | G68: =VLOOKUP(B68,'Profit & Loss'!$B$3:$C$390,2,0) -> #N/A
A69: 106 | C69: 14166.64 | D69: 14166.64 | E69: 0 | F69: 0.0 | G69: =VLOOKUP(B69,'Profit & Loss'!$B$3:$C$390,2,0) -> #N/A
A70: 10701 | B70: 1612001010 Prepayment 3rd Party Office Rent | C70: -6135.39 | D70: -6135.39 | E70: 0 | F70: 0.0 | G70: =VLOOKUP(B70,'Profit & Loss'!$B$3:$C$390,2,0) -> #N/A
A71: 10701 | B71: 1612001020 Prepayment 3rd Party Office Rent Imp (LHI) | C71: 10317.04 | D71: 10893.75 | E71: -576.71 | F71: 5.3- | G71: =VLOOKUP(B71,'Profit & Loss'!$B$3:$C$390,2,0) -> #N/A
A72: 10701 | B72: 1612002000 Prepayment Related Party | C72: 6329.17 | D72: 6329.17 | E72: 0 | F72: 0.0 | G72: =VLOOKUP(B72,'Profit & Loss'!$B$3:$C$390,2,0) -> #N/A
A73: 10701 | B73: 1630000010 Advance To Employee PC Advance | C73: 0 | D73: 558.74 | E73: -558.74 | F73: 100.0- | G73: =VLOOKUP(B73,'Profit & Loss'!$B$3:$C$390,2,0) -> #N/A
A74: 10701 | B74: 1630000019 Advance To Employee PC Advance FxV | C74: 0 | D74: -2.1 | E74: 2.1 | F74: 100.0 | G74: =VLOOKUP(B74,'Profit & Loss'!$B$3:$C$390,2,0) -> #N/A
A75: 10701 | B75: 1630000110 Advance To Employee Travel | C75: -2.25 | D75: -85.94 | E75: 83.69 | F75: 97.4 | G75: =VLOOKUP(B75,'Profit & Loss'!$B$3:$C$390,2,0) -> #N/A
A76: 10701 | B76: 1630000119 Advance To Employee Travel Adv FxV | C76: 0.02 | D76: -0.44 | E76: 0.46 | F76: 104.5 | G76: =VLOOKUP(B76,'Profit & Loss'!$B$3:$C$390,2,0) -> #N/A
A77: 10701 | C77: 10508.59 | D77: 11557.79 | E77: -1049.2 | F77: 9.1- | G77: =VLOOKUP(B77,'Profit & Loss'!$B$3:$C$390,2,0) -> #N/A
A78: 107 | C78: 10508.59 | D78: 11557.79 | E78: -1049.2 | F78: 9.1- | G78: =VLOOKUP(B78,'Profit & Loss'!$B$3:$C$390,2,0) -> #N/A
A79: 11001 | B79: 1811102000 FA Acquisition Owned Self Usage Building | C79: 359163.46 | D79: 359163.46 | E79: 0 | F79: 0.0 | G79: =VLOOKUP(B79,'Profit & Loss'!$B$3:$C$390,2,0) -> #N/A
A80: 11001 | B80: 1821102000 FA Accumulated Depreciation Owned Building | C80: -259267.02 | D80: -258152.24 | E80: -1114.78 | F80: 0.4- | G80: =VLOOKUP(B80,'Profit & Loss'!$B$3:$C$390,2,0) -> #N/A
A81: 11001 | C81: 99896.44 | D81: 101011.22 | E81: -1114.78 | F81: 1.1- | G81: =VLOOKUP(B81,'Profit & Loss'!$B$3:$C$390,2,0) -> #N/A
A82: 11003 | B82: 1811115000 FA Acquisition Owned Warehouse Equip | C82: 132848.63 | D82: 132848.63 | E82: 0 | F82: 0.0 | G82: =VLOOKUP(B82,'Profit & Loss'!$B$3:$C$390,2,0) -> #N/A
A83: 11003 | B83: 1811116000 FA Acquisition Owned Workshop Equip | C83: 476913.35 | D83: 476214.59 | E83: 698.76 | F83: 0.1 | G83: =VLOOKUP(B83,'Profit & Loss'!$B$3:$C$390,2,0) -> #N/A
A84: 11003 | B84: 1811117000 FA Acquisition Owned Service Tool | C84: 380820.83 | D84: 390466.49 | E84: -9645.66 | F84: 2.5- | G84: =VLOOKUP(B84,'Profit & Loss'!$B$3:$C$390,2,0) -> #N/A
A85: 11003 | B85: 1811119000 FA Acquisition Owned Training Center Equipment | C85: 495.24 | D85: 495.24 | E85: 0 | F85: 0.0 | G85: =VLOOKUP(B85,'Profit & Loss'!$B$3:$C$390,2,0) -> #N/A
A86: 11003 | B86: 1811140000 FA Acquisition Owned Office Equipment | C86: 245275.31 | D86: 242483.73 | E86: 2791.58 | F86: 1.2 | G86: =VLOOKUP(B86,'Profit & Loss'!$B$3:$C$390,2,0) -> #N/A
A87: 11003 | B87: 1821115000 FA Accumulated Depreciation Owned Warehouse Equip | C87: -125820.4 | D87: -125545.89 | E87: -274.51 | F87: 0.2- | G87: =VLOOKUP(B87,'Profit & Loss'!$B$3:$C$390,2,0) -> #N/A
A88: 11003 | B88: 1821116000 FA Accumulated Depreciation Owned Workshop Equip | C88: -298528.29 | D88: -295037.25 | E88: -3491.04 | F88: 1.2- | G88: =VLOOKUP(B88,'Profit & Loss'!$B$3:$C$390,2,0) -> #N/A
A89: 11003 | B89: 1821117000 FA Accumulated Depreciation Owned Service Tool | C89: -302132.39 | D89: -314663.27 | E89: 12530.88 | F89: 4.0 | G89: =VLOOKUP(B89,'Profit & Loss'!$B$3:$C$390,2,0) -> #N/A
A90: 11003 | B90: 1821119000 FA Accumulated Depreciation Owned TC Equip | C90: -486.99 | D90: -478.74 | E90: -8.25 | F90: 1.7- | G90: =VLOOKUP(B90,'Profit & Loss'!$B$3:$C$390,2,0) -> #N/A
A91: 11003 | B91: 1821140000 FA Accumulated Depreciation Owned Office Equipment | C91: -209527.28 | D91: -208362.78 | E91: -1164.5 | F91: 0.6- | G91: =VLOOKUP(B91,'Profit & Loss'!$B$3:$C$390,2,0) -> #N/A
A92: 11003 | C92: 299858.01 | D92: 298420.75 | E92: 1437.26 | F92: 0.5 | G92: =VLOOKUP(B92,'Profit & Loss'!$B$3:$C$390,2,0) -> #N/A
A93: 11004 | B93: 1811301000 FA Acquisition Owned Rental Fleet Machine | C93: 15647519 | D93: 13606620 | E93: 2040899.1 | F93: 15.0 | G93: =VLOOKUP(B93,'Profit & Loss'!$B$3:$C$390,2,0) -> #N/A
A94: 11004 | B94: 1821301000 FA Accumulated Depreciation Owned Rental Fleet Mac | C94: -5357668.2 | D94: -5175179.6 | E94: -182488.6 | F94: 3.5- | G94: =VLOOKUP(B94,'Profit & Loss'!$B$3:$C$390,2,0) -> #N/A
A95: 11004 | C95: 10289851 | D95: 8431440.2 | E95: 1858410.5 | F95: 22.0 | G95: =VLOOKUP(B95,'Profit & Loss'!$B$3:$C$390,2,0) -> #N/A
A96: 11005 | B96: 1811130000 FA Acquisition Owned Vehicle Sedan | C96: 152624.47 | D96: 138093.67 | E96: 14530.8 | F96: 10.5 | G96: =VLOOKUP(B96,'Profit & Loss'!$B$3:$C$390,2,0) -> #N/A
A97: 11005 | B97: 1811131000 FA Acquisition Owned Vehicle Truck | C97: 733771.45 | D97: 855138.11 | E97: -121366.66 | F97: 14.2- | G97: =VLOOKUP(B97,'Profit & Loss'!$B$3:$C$390,2,0) -> #N/A
A98: 11005 | B98: 1821130000 FA Accumulated Depreciation Owned Vehicle Sedan | C98: -151457.21 | D98: -136870.83 | E98: -14586.38 | F98: 10.7- | G98: =VLOOKUP(B98,'Profit & Loss'!$B$3:$C$390,2,0) -> #N/A
A99: 11005 | B99: 1821131000 FA Accumulated Depreciation Owned Vehicle Truck | C99: -748249.16 | D99: -867914.9 | E99: 119665.74 | F99: 13.8 | G99: =VLOOKUP(B99,'Profit & Loss'!$B$3:$C$390,2,0) -> #N/A
A100: 11005 | C100: -13310.45 | D100: -11553.95 | E100: -1756.5 | F100: 15.2- | G100: =VLOOKUP(B100,'Profit & Loss'!$B$3:$C$390,2,0) -> #N/A
...

Sheet APR 22
A1: Financial Statement Item | B1: Text for B/S P&L item | C1: Total of reporting period | D1: Total of the comparison period | E1: Absolute difference | F1: Percentage difference | G1: A
A2: 1000000 | B2: A S S E T S | C2: 0 | D2: 0 | E2: 0 | G2: =VLOOKUP(B2,'Profit & Loss'!$B$3:$C$390,2,0) -> #N/A
A3: 1000000 | B3: = = = = = = | C3: 0 | D3: 0 | E3: 0 | G3: =VLOOKUP(B3,'Profit & Loss'!$B$3:$C$390,2,0) -> #N/A
A4: 10101 | B4: 1011100380 PettyCash IDR SANGATTA | C4: 329.08 | D4: 329.08 | E4: 0 | F4: 0.0 | G4: =VLOOKUP(B4,'Profit & Loss'!$B$3:$C$390,2,0) -> #N/A
A5: 10101 | B5: 1016109751 Bank IDR Mandiri 1480004169325 MB-SANGATA_COL | C5: 610.44 | D5: 610.44 | E5: 0 | F5: 0.0 | G5: =VLOOKUP(B5,'Profit & Loss'!$B$3:$C$390,2,0) -> #N/A
A6: 10101 | B6: 1016109761 Bank IDR Mandiri 1480004169309 MB-SANGATA_OPR | C6: 23494.19 | D6: 26519.23 | E6: -3025.04 | F6: 11.4- | G6: =VLOOKUP(B6,'Profit & Loss'!$B$3:$C$390,2,0) -> #N/A
A7: 10101 | B7: 1016109769 Bank IDR Mandiri 1480004169309 FxV-SANGATA_OPR | C7: -23412.73 | D7: -23252.66 | E7: -160.07 | F7: 0.7- | G7: =VLOOKUP(B7,'Profit & Loss'!$B$3:$C$390,2,0) -> #N/A
A8: 10101 | B8: 1016162071 Bank IDR Mandiri 148-001-687266-8 MB SGT | C8: 68.6 | D8: 68.59 | E8: 0.01 | F8: 0.0 | G8: =VLOOKUP(B8,'Profit & Loss'!$B$3:$C$390,2,0) -> #N/A
A9: 10101 | B9: 1016162079 Bank IDR Mandiri 148-001-687266-8 FxV SGT | C9: 2.49 | D9: 2.84 | E9: -0.35 | F9: 12.3- | G9: =VLOOKUP(B9,'Profit & Loss'!$B$3:$C$390,2,0) -> #N/A
A10: 10101 | C10: 1092.07 | D10: 4277.52 | E10: -3185.45 | F10: 74.5- | G10: =VLOOKUP(B10,'Profit & Loss'!$B$3:$C$390,2,0) -> #N/A
A11: 101 | C11: 1092.07 | D11: 4277.52 | E11: -3185.45 | F11: 74.5- | G11: =VLOOKUP(B11,'Profit & Loss'!$B$3:$C$390,2,0) -> #N/A
A12: 10201 | B12: 1110101000 AR Gross Trade 3rd Party | C12: 13702348 | D12: 13924123 | E12: -221775.23 | F12: 1.6- | G12: =VLOOKUP(B12,'Profit & Loss'!$B$3:$C$390,2,0) -> #N/A
A13: 10201 | B13: 1110101009 AR Gross Trade 3rd Party FxV | C13: -35312.69 | D13: 10113.67 | E13: -45426.36 | F13: 449.2- | G13: =VLOOKUP(B13,'Profit & Loss'!$B$3:$C$390,2,0) -> #N/A
A14: 10201 | B14: 1110102000 AR Gross Trade Rel Party | C14: 1601828.4 | D14: 1601828.4 | E14: 0 | F14: 0.0 | G14: =VLOOKUP(B14,'Profit & Loss'!$B$3:$C$390,2,0) -> #N/A
A15: 10201 | B15: 1110102009 AR Gross Trade Rel Party FxV | C15: -104472.47 | D15: -97348.32 | E15: -7124.15 | F15: 7.3- | G15: =VLOOKUP(B15,'Profit & Loss'!$B$3:$C$390,2,0) -> #N/A
A16: 10201 | C16: 15164391 | D16: 15438717 | E16: -274325.74 | F16: 1.8- | G16: =VLOOKUP(B16,'Profit & Loss'!$B$3:$C$390,2,0) -> #N/A
A17: 10202 | B17: 1120101000 AR Gross Trade 3rd Party Allowance | C17: -42841.18 | D17: -40127.62 | E17: -2713.56 | F17: 6.8- | G17: =VLOOKUP(B17,'Profit & Loss'!$B$3:$C$390,2,0) -> #N/A
A18: 10202 | C18: -42841.18 | D18: -40127.62 | E18: -2713.56 | F18: 6.8- | G18: =VLOOKUP(B18,'Profit & Loss'!$B$3:$C$390,2,0) -> #N/A
A19: 102 | C19: 15121550 | D19: 15398589 | E19: -277039.3 | F19: 1.8- | G19: =VLOOKUP(B19,'Profit & Loss'!$B$3:$C$390,2,0) -> #N/A
A20: 10301 | B20: 1211101000 AR Claim Warranty Pending 3rd Party | C20: 0.01 | D20: 0.01 | E20: 0 | F20: 0.0 | G20: =VLOOKUP(B20,'Profit & Loss'!$B$3:$C$390,2,0) -> #N/A
A21: 10301 | B21: 1211101001 AR Claim Warranty Pend Claim 3rd Party New Acct | C21: 507.48 | D21: 0 | E21: 507.48 | G21: =VLOOKUP(B21,'Profit & Loss'!$B$3:$C$390,2,0) -> #N/A
A22: 10301 | B22: 1211201311 AR Claim TWLBR | C22: 51850.32 | D22: 42291.62 | E22: 9558.7 | F22: 22.6 | G22: =VLOOKUP(B22,'Profit & Loss'!$B$3:$C$390,2,0) -> #N/A
A23: 10301 | B23: 1211301000 AR Claim Warranty Claim 3rd Party | C23: 0.01 | D23: 0.01 | E23: 0 | F23: 0.0 | G23: =VLOOKUP(B23,'Profit & Loss'!$B$3:$C$390,2,0) -> #N/A
A24: 10301 | B24: 1211301001 AR Claim Warranty Claim 3rd Party New | C24: 118453.57 | D24: 27128.57 | E24: 91325 | F24: 336.6 | G24: =VLOOKUP(B24,'Profit & Loss'!$B$3:$C$390,2,0) -> #N/A
A25: 10301 | B25: 1211401001 AR Claim 3rd Party Goodwill (New Acct) | C25: 22605.02 | D25: 46253.61 | E25: -23648.59 | F25: 51.1- | G25: =VLOOKUP(B25,'Profit & Loss'!$B$3:$C$390,2,0) -> #N/A
A26: 10301 | B26: 1211401310 AR Claim Warranty Claim-Goodwill 3rd Party OEM | C26: 19.35 | D26: 19.35 | E26: 0 | F26: 0.0 | G26: =VLOOKUP(B26,'Profit & Loss'!$B$3:$C$390,2,0) -> #N/A
A27: 10301 | C27: 193435.76 | D27: 115693.17 | E27: 77742.59 | F27: 67.2 | G27: =VLOOKUP(B27,'Profit & Loss'!$B$3:$C$390,2,0) -> #N/A
A28: 10302 | B28: 1212001010 AR Claim 3rd Party CAT Parts Core | C28: 103211.52 | D28: -7566.42 | E28: 110777.94 | F28: 1,464.1 | G28: =VLOOKUP(B28,'Profit & Loss'!$B$3:$C$390,2,0) -> #N/A
A29: 10302 | C29: 103211.52 | D29: -7566.42 | E29: 110777.94 | F29: 1,464.1 | G29: =VLOOKUP(B29,'Profit & Loss'!$B$3:$C$390,2,0) -> #N/A
A30: 10306 | B30: 1110101230 AR Gross Trade 3rd Party Art23 | C30: 49147.55 | D30: 67008.31 | E30: -17860.76 | F30: 26.7- | G30: =VLOOKUP(B30,'Profit & Loss'!$B$3:$C$390,2,0) -> #N/A
A31: 10306 | B31: 1110101239 AR Gross Trade 3rd Party Art23 FxV | C31: -107.47 | D31: 14.94 | E31: -122.41 | F31: 819.3- | G31: =VLOOKUP(B31,'Profit & Loss'!$B$3:$C$390,2,0) -> #N/A
A32: 10306 | B32: 1110102230 AR Gross Trade Rel Party Art23 | C32: 0 | D32: 277.08 | E32: -277.08 | F32: 100.0- | G32: =VLOOKUP(B32,'Profit & Loss'!$B$3:$C$390,2,0) -> #N/A
A33: 10306 | B33: 1110102239 AR Gross Trade Rel Party Art23 FxV | C33: 0 | D33: 1.19 | E33: -1.19 | F33: 100.0- | G33: =VLOOKUP(B33,'Profit & Loss'!$B$3:$C$390,2,0) -> #N/A
A34: 10306 | B34: 1110181000 AR Gross Others Project System Over Under | C34: 2597.52 | D34: 2597.52 | E34: 0 | F34: 0.0 | G34: =VLOOKUP(B34,'Profit & Loss'!$B$3:$C$390,2,0) -> #N/A
A35: 10306 | B35: 1110202000 AR Gross Non Trade Rel Party | C35: 7843.4 | D35: 0 | E35: 7843.4 | G35: =VLOOKUP(B35,'Profit & Loss'!$B$3:$C$390,2,0) -> #N/A
A36: 10306 | B36: 1110202009 AR Gross Non Trade Rel Party FxV | C36: -14.27 | D36: 0 | E36: -14.27 | G36: =VLOOKUP(B36,'Profit & Loss'!$B$3:$C$390,2,0) -> #N/A
A37: 10306 | B37: 1216001020 AR Claim 3rd Party CAT PSDN | C37: -7666.86 | D37: 348.54 | E37: -8015.4 | F37: 2,299.7- | G37: =VLOOKUP(B37,'Profit & Loss'!$B$3:$C$390,2,0) -> #N/A
A38: 10306 | B38: 1219301000 AR Claim Others 3rd Party | C38: 2694.7 | D38: 2821.42 | E38: -126.72 | F38: 4.5- | G38: =VLOOKUP(B38,'Profit & Loss'!$B$3:$C$390,2,0) -> #N/A
A39: 10306 | B39: 1219301009 AR Claim Others 3rd Party FxV | C39: 0 | D39: -0.35 | E39: 0.35 | F39: 100.0 | G39: =VLOOKUP(B39,'Profit & Loss'!$B$3:$C$390,2,0) -> #N/A
A40: 10306 | B40: 1219302070 AR Claim Others Rel Party CKB | C40: 40.97 | D40: 39.9 | E40: 1.07 | F40: 2.7 | G40: =VLOOKUP(B40,'Profit & Loss'!$B$3:$C$390,2,0) -> #N/A
A41: 10306 | C41: 54535.54 | D41: 73108.55 | E41: -18573.01 | F41: 25.4- | G41: =VLOOKUP(B41,'Profit & Loss'!$B$3:$C$390,2,0) -> #N/A
A42: 103 | C42: 351182.82 | D42: 181235.3 | E42: 169947.52 | F42: 93.8 | G42: =VLOOKUP(B42,'Profit & Loss'!$B$3:$C$390,2,0) -> #N/A
A43: 10501 | B43: 1411191200 Inventory PP Freight & Handling (CLEARING) | C43: -0.1 | D43: -0.1 | E43: 0 | F43: 0.0 | G43: =VLOOKUP(B43,'Profit & Loss'!$B$3:$C$390,2,0) -> #N/A
A44: 10501 | B44: 1411198000 Inventory PP Non CAT Accessories | C44: -33464.48 | D44: -33464.48 | E44: 0 | F44: 0.0 | G44: =VLOOKUP(B44,'Profit & Loss'!$B$3:$C$390,2,0) -> #N/A
A45: 10501 | B45: 1460200000 Inventory PP GIT Non Trade | C45: 1668.98 | D45: 1668.98 | E45: 0 | F45: 0.0 | G45: =VLOOKUP(B45,'Profit & Loss'!$B$3:$C$390,2,0) -> #N/A
A46: 10501 | C46: -31795.6 | D46: -31795.6 | E46: 0 | F46: 0.0 | G46: =VLOOKUP(B46,'Profit & Loss'!$B$3:$C$390,2,0) -> #N/A
A47: 10502 | B47: 1415101000 Inventory Parts Stock On Hand | C47: 12269741 | D47: 11629217 | E47: 640523.8 | F47: 5.5 | G47: =VLOOKUP(B47,'Profit & Loss'!$B$3:$C$390,2,0) -> #N/A
A48: 10502 | B48: 1415111800 Inventory Parts PEX Core Raw Material | C48: 1057.78 | D48: 836.37 | E48: 221.41 | F48: 26.5 | G48: =VLOOKUP(B48,'Profit & Loss'!$B$3:$C$390,2,0) -> #N/A
A49: 10502 | B49: 1415141666 Inventory Parts PVRG SPM - SOA | C49: 664099.21 | D49: 273943.08 | E49: 390156.13 | F49: 142.4 | G49: =VLOOKUP(B49,'Profit & Loss'!$B$3:$C$390,2,0) -> #N/A
A50: 10502 | B50: 1415192000 Inventory Parts Gross Hub Turn Over | C50: 1613360.7 | D50: 1525955.1 | E50: 87405.63 | F50: 5.7 | G50: =VLOOKUP(B50,'Profit & Loss'!$B$3:$C$390,2,0) -> #N/A
A51: 10502 | B51: 1461001210 Inventory Parts GINI | C51: 2390236.6 | D51: 1713481.5 | E51: 676755.11 | F51: 39.5 | G51: =VLOOKUP(B51,'Profit & Loss'!$B$3:$C$390,2,0) -> #N/A
A52: 10502 | B52: 1465011000 Inventory Parts GIT | C52: 2883934.1 | D52: 3762968.1 | E52: -879033.99 | F52: 23.4- | G52: =VLOOKUP(B52,'Profit & Loss'!$B$3:$C$390,2,0) -> #N/A
A53: 10502 | B53: 1465011002 Inventory Parts Freight & Handling (CLEARING) | C53: 40964.07 | D53: 18980.04 | E53: 21984.03 | F53: 115.8 | G53: =VLOOKUP(B53,'Profit & Loss'!$B$3:$C$390,2,0) -> #N/A
A54: 10502 | B54: 1515001213 Landed Cost - Parts FH ITL Inbound Actual | C54: -1499398.5 | D54: -1413605.4 | E54: -85793.11 | F54: 6.1- | G54: =VLOOKUP(B54,'Profit & Loss'!$B$3:$C$390,2,0) -> #N/A
A55: 10502 | B55: 1515001214 Landed Cost - Parts FH LCL Inbound Actual | C55: 11851.35 | D55: 14874.62 | E55: -3023.27 | F55: 20.3- | G55: =VLOOKUP(B55,'Profit & Loss'!$B$3:$C$390,2,0) -> #N/A
A56: 10502 | B56: 1515001215 Landed Cost - Parts FH LCL Outbound Actual | C56: -18605.45 | D56: -19907.25 | E56: 1301.8 | F56: 6.5 | G56: =VLOOKUP(B56,'Profit & Loss'!$B$3:$C$390,2,0) -> #N/A
A57: 10502 | B57: 1515001216 Landed Cost - Parts FH ITL Outbound Actual | C57: -14261.14 | D57: 335.4 | E57: -14596.54 | F57: 4,352.0- | G57: =VLOOKUP(B57,'Profit & Loss'!$B$3:$C$390,2,0) -> #N/A
A58: 10502 | C58: 18342980 | D58: 17507079 | E58: 835901 | F58: 4.8 | G58: =VLOOKUP(B58,'Profit & Loss'!$B$3:$C$390,2,0) -> #N/A
A59: 10503 | B59: 1565000000 WIP Parts | C59: 278291.8 | D59: 275669.67 | E59: 2622.13 | F59: 1.0 | G59: =VLOOKUP(B59,'Profit & Loss'!$B$3:$C$390,2,0) -> #N/A
A60: 10503 | B60: 1565000010 WIP Parts Salvage | C60: -4793.88 | D60: -4793.88 | E60: 0 | F60: 0.0 | G60: =VLOOKUP(B60,'Profit & Loss'!$B$3:$C$390,2,0) -> #N/A
A61: 10503 | B61: 1565000016 WIP Parts Minor Component (MICRC) | C61: 946.22 | D61: 946.22 | E61: 0 | F61: 0.0 | G61: =VLOOKUP(B61,'Profit & Loss'!$B$3:$C$390,2,0) -> #N/A
A62: 10503 | B62: 1565000511 WIP Parts S.O.S. | C62: 418.21 | D62: 238.46 | E62: 179.75 | F62: 75.4 | G62: =VLOOKUP(B62,'Profit & Loss'!$B$3:$C$390,2,0) -> #N/A
A63: 10503 | B63: 1566000010 WIP Service Labor | C63: 245192.53 | D63: 226446.67 | E63: 18745.86 | F63: 8.3 | G63: =VLOOKUP(B63,'Profit & Loss'!$B$3:$C$390,2,0) -> #N/A
A64: 10503 | B64: 1566000020 WIP Service LPO | C64: 146477.68 | D64: 59012.47 | E64: 87465.21 | F64: 148.2 | G64: =VLOOKUP(B64,'Profit & Loss'!$B$3:$C$390,2,0) -> #N/A
A65: 10503 | B65: 1566000050 WIP Service Travel | C65: 420.63 | D65: 420.63 | E65: 0 | F65: 0.0 | G65: =VLOOKUP(B65,'Profit & Loss'!$B$3:$C$390,2,0) -> #N/A
A66: 10503 | C66: 666953.19 | D66: 557940.24 | E66: 109012.95 | F66: 19.5 | G66: =VLOOKUP(B66,'Profit & Loss'!$B$3:$C$390,2,0) -> #N/A
A67: 105 | C67: 18978137 | D67: 18033223 | E67: 944913.95 | F67: 5.2 | G67: =VLOOKUP(B67,'Profit & Loss'!$B$3:$C$390,2,0) -> #N/A
A68: 10601 | B68: 1661023000 Prepaid Tax ART 23 | C68: 14166.64 | D68: 14166.64 | E68: 0 | F68: 0.0 | G68: =VLOOKUP(B68,'Profit & Loss'!$B$3:$C$390,2,0) -> #N/A
A69: 10601 | C69: 14166.64 | D69: 14166.64 | E69: 0 | F69: 0.0 | G69: =VLOOKUP(B69,'Profit & Loss'!$B$3:$C$390,2,0) -> #N/A
A70: 106 | C70: 14166.64 | D70: 14166.64 | E70: 0 | F70: 0.0 | G70: =VLOOKUP(B70,'Profit & Loss'!$B$3:$C$390,2,0) -> #N/A
A71: 10701 | B71: 1612001010 Prepayment 3rd Party Office Rent | C71: -6135.39 | D71: -6135.39 | E71: 0 | F71: 0.0 | G71: =VLOOKUP(B71,'Profit & Loss'!$B$3:$C$390,2,0) -> #N/A
A72: 10701 | B72: 1612001020 Prepayment 3rd Party Office Rent Imp (LHI) | C72: 9740.33 | D72: 10317.04 | E72: -576.71 | F72: 5.6- | G72: =VLOOKUP(B72,'Profit & Loss'!$B$3:$C$390,2,0) -> #N/A
A73: 10701 | B73: 1612002000 Prepayment Related Party | C73: 6329.17 | D73: 6329.17 | E73: 0 | F73: 0.0 | G73: =VLOOKUP(B73,'Profit & Loss'!$B$3:$C$390,2,0) -> #N/A
A74: 10701 | B74: 1630000010 Advance To Employee PC Advance | C74: 346.79 | D74: 0 | E74: 346.79 | G74: =VLOOKUP(B74,'Profit & Loss'!$B$3:$C$390,2,0) -> #N/A
A75: 10701 | B75: 1630000019 Advance To Employee PC Advance FxV | C75: 0.01 | D75: 0 | E75: 0.01 | G75: =VLOOKUP(B75,'Profit & Loss'!$B$3:$C$390,2,0) -> #N/A
A76: 10701 | B76: 1630000110 Advance To Employee Travel | C76: 41.66 | D76: -2.25 | E76: 43.91 | F76: 1,951.6 | G76: =VLOOKUP(B76,'Profit & Loss'!$B$3:$C$390,2,0) -> #N/A
A77: 10701 | B77: 1630000119 Advance To Employee Travel Adv FxV | C77: -0.25 | D77: 0.02 | E77: -0.27 | F77: 1,350.0- | G77: =VLOOKUP(B77,'Profit & Loss'!$B$3:$C$390,2,0) -> #N/A
A78: 10701 | C78: 10322.32 | D78: 10508.59 | E78: -186.27 | F78: 1.8- | G78: =VLOOKUP(B78,'Profit & Loss'!$B$3:$C$390,2,0) -> #N/A
A79: 107 | C79: 10322.32 | D79: 10508.59 | E79: -186.27 | F79: 1.8- | G79: =VLOOKUP(B79,'Profit & Loss'!$B$3:$C$390,2,0) -> #N/A
A80: 11001 | B80: 1811102000 FA Acquisition Owned Self Usage Building | C80: 359163.46 | D80: 359163.46 | E80: 0 | F80: 0.0 | G80: =VLOOKUP(B80,'Profit & Loss'!$B$3:$C$390,2,0) -> #N/A
A81: 11001 | B81: 1821102000 FA Accumulated Depreciation Owned Building | C81: -260381.8 | D81: -259267.02 | E81: -1114.78 | F81: 0.4- | G81: =VLOOKUP(B81,'Profit & Loss'!$B$3:$C$390,2,0) -> #N/A
A82: 11001 | C82: 98781.66 | D82: 99896.44 | E82: -1114.78 | F82: 1.1- | G82: =VLOOKUP(B82,'Profit & Loss'!$B$3:$C$390,2,0) -> #N/A
A83: 11003 | B83: 1811115000 FA Acquisition Owned Warehouse Equip | C83: 132848.63 | D83: 132848.63 | E83: 0 | F83: 0.0 | G83: =VLOOKUP(B83,'Profit & Loss'!$B$3:$C$390,2,0) -> #N/A
A84: 11003 | B84: 1811116000 FA Acquisition Owned Workshop Equip | C84: 516712.36 | D84: 476913.35 | E84: 39799.01 | F84: 8.3 | G84: =VLOOKUP(B84,'Profit & Loss'!$B$3:$C$390,2,0) -> #N/A
A85: 11003 | B85: 1811117000 FA Acquisition Owned Service Tool | C85: 380820.83 | D85: 380820.83 | E85: 0 | F85: 0.0 | G85: =VLOOKUP(B85,'Profit & Loss'!$B$3:$C$390,2,0) -> #N/A
A86: 11003 | B86: 1811119000 FA Acquisition Owned Training Center Equipment | C86: 495.24 | D86: 495.24 | E86: 0 | F86: 0.0 | G86: =VLOOKUP(B86,'Profit & Loss'!$B$3:$C$390,2,0) -> #N/A
A87: 11003 | B87: 1811140000 FA Acquisition Owned Office Equipment | C87: 247441.57 | D87: 245275.31 | E87: 2166.26 | F87: 0.9 | G87: =VLOOKUP(B87,'Profit & Loss'!$B$3:$C$390,2,0) -> #N/A
A88: 11003 | B88: 1821115000 FA Accumulated Depreciation Owned Warehouse Equip | C88: -126094.93 | D88: -125820.4 | E88: -274.53 | F88: 0.2- | G88: =VLOOKUP(B88,'Profit & Loss'!$B$3:$C$390,2,0) -> #N/A
A89: 11003 | B89: 1821116000 FA Accumulated Depreciation Owned Workshop Equip | C89: -302441.43 | D89: -298528.29 | E89: -3913.14 | F89: 1.3- | G89: =VLOOKUP(B89,'Profit & Loss'!$B$3:$C$390,2,0) -> #N/A
A90: 11003 | B90: 1821117000 FA Accumulated Depreciation Owned Service Tool | C90: -304346.77 | D90: -302132.39 | E90: -2214.38 | F90: 0.7- | G90: =VLOOKUP(B90,'Profit & Loss'!$B$3:$C$390,2,0) -> #N/A
A91: 11003 | B91: 1821119000 FA Accumulated Depreciation Owned TC Equip | C91: -495.24 | D91: -486.99 | E91: -8.25 | F91: 1.7- | G91: =VLOOKUP(B91,'Profit & Loss'!$B$3:$C$390,2,0) -> #N/A
A92: 11003 | B92: 1821140000 FA Accumulated Depreciation Owned Office Equipment | C92: -210688.98 | D92: -209527.28 | E92: -1161.7 | F92: 0.6- | G92: =VLOOKUP(B92,'Profit & Loss'!$B$3:$C$390,2,0) -> #N/A
A93: 11003 | C93: 334251.28 | D93: 299858.01 | E93: 34393.27 | F93: 11.5 | G93: =VLOOKUP(B93,'Profit & Loss'!$B$3:$C$390,2,0) -> #N/A
A94: 11004 | B94: 1811301000 FA Acquisition Owned Rental Fleet Machine | C94: 17497670 | D94: 15647519 | E94: 1850150.8 | F94: 11.8 | G94: =VLOOKUP(B94,'Profit & Loss'!$B$3:$C$390,2,0) -> #N/A
A95: 11004 | B95: 1821301000 FA Accumulated Depreciation Owned Rental Fleet Mac | C95: -5584939.9 | D95: -5357668.2 | E95: -227271.73 | F95: 4.2- | G95: =VLOOKUP(B95,'Profit & Loss'!$B$3:$C$390,2,0) -> #N/A
A96: 11004 | C96: 11912730 | D96: 10289851 | E96: 1622879.1 | F96: 15.8 | G96: =VLOOKUP(B96,'Profit & Loss'!$B$3:$C$390,2,0) -> #N/A
A97: 11005 | B97: 1811130000 FA Acquisition Owned Vehicle Sedan | C97: 152624.47 | D97: 152624.47 | E97: 0 | F97: 0.0 | G97: =VLOOKUP(B97,'Profit & Loss'!$B$3:$C$390,2,0) -> #N/A
A98: 11005 | B98: 1811131000 FA Acquisition Owned Vehicle Truck | C98: 655044.08 | D98: 733771.45 | E98: -78727.37 | F98: 10.7- | G98: =VLOOKUP(B98,'Profit & Loss'!$B$3:$C$390,2,0) -> #N/A
A99: 11005 | B99: 1821130000 FA Accumulated Depreciation Owned Vehicle Sedan | C99: -151512.8 | D99: -151457.21 | E99: -55.59 | F99: 0.0 | G99: =VLOOKUP(B99,'Profit & Loss'!$B$3:$C$390,2,0) -> #N/A
A100: 11005 | B100: 1821131000 FA Accumulated Depreciation Owned Vehicle Truck | C100: -671222.72 | D100: -748249.16 | E100: 77026.44 | F100: 10.3 | G100: =VLOOKUP(B100,'Profit & Loss'!$B$3:$C$390,2,0) -> #N/A
...

Sheet MAY 22
A1: Financial Statement Item | B1: Text for B/S P&L item | C1: Total of reporting period | D1: Total of the comparison period | E1: Absolute difference | F1: A
A2: 1000000 | B2: A S S E T S | C2: 0 | D2: 0 | E2: 0 | F2: =VLOOKUP(B2,'Profit & Loss'!$B$2:$C$390,2,0) -> #N/A
A3: 1000000 | B3: = = = = = = | C3: 0 | D3: 0 | E3: 0 | F3: =VLOOKUP(B3,'Profit & Loss'!$B$2:$C$390,2,0) -> #N/A
A4: 10101 | B4: 1011100380 PettyCash IDR SANGATTA | C4: 329.08 | D4: 329.08 | E4: 0 | F4: =VLOOKUP(B4,'Profit & Loss'!$B$2:$C$390,2,0) -> #N/A
A5: 10101 | B5: 1016109751 Bank IDR Mandiri 1480004169325 MB-SANGATA_COL | C5: 610.44 | D5: 610.44 | E5: 0 | F5: =VLOOKUP(B5,'Profit & Loss'!$B$2:$C$390,2,0) -> #N/A
A6: 10101 | B6: 1016109761 Bank IDR Mandiri 1480004169309 MB-SANGATA_OPR | C6: 27965.02 | D6: 23494.19 | E6: 4470.83 | F6: =VLOOKUP(B6,'Profit & Loss'!$B$2:$C$390,2,0) -> #N/A
A7: 10101 | B7: 1016109769 Bank IDR Mandiri 1480004169309 FxV-SANGATA_OPR | C7: -23414.15 | D7: -23412.73 | E7: -1.42 | F7: =VLOOKUP(B7,'Profit & Loss'!$B$2:$C$390,2,0) -> #N/A
A8: 10101 | B8: 1016162071 Bank IDR Mandiri 148-001-687266-8 MB SGT | C8: 68.61 | D8: 68.6 | E8: 0.01 | F8: =VLOOKUP(B8,'Profit & Loss'!$B$2:$C$390,2,0) -> #N/A
A9: 10101 | B9: 1016162079 Bank IDR Mandiri 148-001-687266-8 FxV SGT | C9: 1.87 | D9: 2.49 | E9: -0.62 | F9: =VLOOKUP(B9,'Profit & Loss'!$B$2:$C$390,2,0) -> #N/A
A10: 10101 | C10: 5560.87 | D10: 1092.07 | E10: 4468.8 | F10: =VLOOKUP(B10,'Profit & Loss'!$B$2:$C$390,2,0) -> #N/A
A11: 101 | C11: 5560.87 | D11: 1092.07 | E11: 4468.8 | F11: =VLOOKUP(B11,'Profit & Loss'!$B$2:$C$390,2,0) -> #N/A
A12: 10201 | B12: 1110101000 AR Gross Trade 3rd Party | C12: 15592930 | D12: 13702348 | E12: 1890582.1 | F12: =VLOOKUP(B12,'Profit & Loss'!$B$2:$C$390,2,0) -> #N/A
A13: 10201 | B13: 1110101009 AR Gross Trade 3rd Party FxV | C13: -42604.13 | D13: -35312.69 | E13: -7291.44 | F13: =VLOOKUP(B13,'Profit & Loss'!$B$2:$C$390,2,0) -> #N/A
A14: 10201 | B14: 1110102000 AR Gross Trade Rel Party | C14: 1601828.4 | D14: 1601828.4 | E14: 0 | F14: =VLOOKUP(B14,'Profit & Loss'!$B$2:$C$390,2,0) -> #N/A
A15: 10201 | B15: 1110102009 AR Gross Trade Rel Party FxV | C15: -117425.53 | D15: -104472.47 | E15: -12953.06 | F15: =VLOOKUP(B15,'Profit & Loss'!$B$2:$C$390,2,0) -> #N/A
A16: 10201 | C16: 17034729 | D16: 15164391 | E16: 1870337.6 | F16: =VLOOKUP(B16,'Profit & Loss'!$B$2:$C$390,2,0) -> #N/A
A17: 10202 | B17: 1120101000 AR Gross Trade 3rd Party Allowance | C17: -44390.62 | D17: -42841.18 | E17: -1549.44 | F17: =VLOOKUP(B17,'Profit & Loss'!$B$2:$C$390,2,0) -> #N/A
A18: 10202 | C18: -44390.62 | D18: -42841.18 | E18: -1549.44 | F18: =VLOOKUP(B18,'Profit & Loss'!$B$2:$C$390,2,0) -> #N/A
A19: 102 | C19: 16990338 | D19: 15121550 | E19: 1868788.1 | F19: =VLOOKUP(B19,'Profit & Loss'!$B$2:$C$390,2,0) -> #N/A
A20: 10301 | B20: 1211101000 AR Claim Warranty Pending 3rd Party | C20: 0.01 | D20: 0.01 | E20: 0 | F20: =VLOOKUP(B20,'Profit & Loss'!$B$2:$C$390,2,0) -> #N/A
A21: 10301 | B21: 1211101001 AR Claim Warranty Pend Claim 3rd Party New Acct | C21: 3868.21 | D21: 507.48 | E21: 3360.73 | F21: =VLOOKUP(B21,'Profit & Loss'!$B$2:$C$390,2,0) -> #N/A
A22: 10301 | B22: 1211201311 AR Claim TWLBR | C22: 64064.44 | D22: 51850.32 | E22: 12214.12 | F22: =VLOOKUP(B22,'Profit & Loss'!$B$2:$C$390,2,0) -> #N/A
A23: 10301 | B23: 1211301000 AR Claim Warranty Claim 3rd Party | C23: 0.01 | D23: 0.01 | E23: 0 | F23: =VLOOKUP(B23,'Profit & Loss'!$B$2:$C$390,2,0) -> #N/A
A24: 10301 | B24: 1211301001 AR Claim Warranty Claim 3rd Party New | C24: 15779.64 | D24: 118453.57 | E24: -102673.93 | F24: =VLOOKUP(B24,'Profit & Loss'!$B$2:$C$390,2,0) -> #N/A
A25: 10301 | B25: 1211401001 AR Claim 3rd Party Goodwill (New Acct) | C25: 25960.5 | D25: 22605.02 | E25: 3355.48 | F25: =VLOOKUP(B25,'Profit & Loss'!$B$2:$C$390,2,0) -> #N/A
A26: 10301 | B26: 1211401310 AR Claim Warranty Claim-Goodwill 3rd Party OEM | C26: 19.35 | D26: 19.35 | E26: 0 | F26: =VLOOKUP(B26,'Profit & Loss'!$B$2:$C$390,2,0) -> #N/A
A27: 10301 | C27: 109692.16 | D27: 193435.76 | E27: -83743.6 | F27: =VLOOKUP(B27,'Profit & Loss'!$B$2:$C$390,2,0) -> #N/A
A28: 10302 | B28: 1212001010 AR Claim 3rd Party CAT Parts Core | C28: -5282.2 | D28: 103211.52 | E28: -108493.72 | F28: =VLOOKUP(B28,'Profit & Loss'!$B$2:$C$390,2,0) -> #N/A
A29: 10302 | C29: -5282.2 | D29: 103211.52 | E29: -108493.72 | F29: =VLOOKUP(B29,'Profit & Loss'!$B$2:$C$390,2,0) -> #N/A
A30: 10306 | B30: 1110101230 AR Gross Trade 3rd Party Art23 | C30: 53215.46 | D30: 49147.55 | E30: 4067.91 | F30: =VLOOKUP(B30,'Profit & Loss'!$B$2:$C$390,2,0) -> #N/A
A31: 10306 | B31: 1110101239 AR Gross Trade 3rd Party Art23 FxV | C31: -41.52 | D31: -107.47 | E31: 65.95 | F31: =VLOOKUP(B31,'Profit & Loss'!$B$2:$C$390,2,0) -> #N/A
A32: 10306 | B32: 1110181000 AR Gross Others Project System Over Under | C32: 2597.52 | D32: 2597.52 | E32: 0 | F32: =VLOOKUP(B32,'Profit & Loss'!$B$2:$C$390,2,0) -> #N/A
A33: 10306 | B33: 1110202000 AR Gross Non Trade Rel Party | C33: 5352.52 | D33: 7843.4 | E33: -2490.88 | F33: =VLOOKUP(B33,'Profit & Loss'!$B$2:$C$390,2,0) -> #N/A
A34: 10306 | B34: 1110202009 AR Gross Non Trade Rel Party FxV | C34: -48.36 | D34: -14.27 | E34: -34.09 | F34: =VLOOKUP(B34,'Profit & Loss'!$B$2:$C$390,2,0) -> #N/A
A35: 10306 | B35: 1216001020 AR Claim 3rd Party CAT PSDN | C35: -9391.58 | D35: -7666.86 | E35: -1724.72 | F35: =VLOOKUP(B35,'Profit & Loss'!$B$2:$C$390,2,0) -> #N/A
A36: 10306 | B36: 1219301000 AR Claim Others 3rd Party | C36: 2138.75 | D36: 2694.7 | E36: -555.95 | F36: =VLOOKUP(B36,'Profit & Loss'!$B$2:$C$390,2,0) -> #N/A
A37: 10306 | B37: 1219302070 AR Claim Others Rel Party CKB | C37: 42.92 | D37: 40.97 | E37: 1.95 | F37: =VLOOKUP(B37,'Profit & Loss'!$B$2:$C$390,2,0) -> #N/A
A38: 10306 | C38: 53865.71 | D38: 54535.54 | E38: -669.83 | F38: =VLOOKUP(B38,'Profit & Loss'!$B$2:$C$390,2,0) -> #N/A
A39: 103 | C39: 158275.67 | D39: 351182.82 | E39: -192907.15 | F39: =VLOOKUP(B39,'Profit & Loss'!$B$2:$C$390,2,0) -> #N/A
A40: 10501 | B40: 1411191200 Inventory PP Freight & Handling (CLEARING) | C40: -0.1 | D40: -0.1 | E40: 0 | F40: =VLOOKUP(B40,'Profit & Loss'!$B$2:$C$390,2,0) -> #N/A
A41: 10501 | B41: 1411198000 Inventory PP Non CAT Accessories | C41: 0 | D41: -33464.48 | E41: 33464.48 | F41: =VLOOKUP(B41,'Profit & Loss'!$B$2:$C$390,2,0) -> #N/A
A42: 10501 | B42: 1460200000 Inventory PP GIT Non Trade | C42: 591.19 | D42: 1668.98 | E42: -1077.79 | F42: =VLOOKUP(B42,'Profit & Loss'!$B$2:$C$390,2,0) -> #N/A
A43: 10501 | C43: 591.09 | D43: -31795.6 | E43: 32386.69 | F43: =VLOOKUP(B43,'Profit & Loss'!$B$2:$C$390,2,0) -> #N/A
A44: 10502 | B44: 1415101000 Inventory Parts Stock On Hand | C44: 12765262 | D44: 12269741 | E44: 495521.19 | F44: =VLOOKUP(B44,'Profit & Loss'!$B$2:$C$390,2,0) -> #N/A
A45: 10502 | B45: 1415111800 Inventory Parts PEX Core Raw Material | C45: 1057.78 | D45: 1057.78 | E45: 0 | F45: =VLOOKUP(B45,'Profit & Loss'!$B$2:$C$390,2,0) -> #N/A
A46: 10502 | B46: 1415141666 Inventory Parts PVRG SPM - SOA | C46: -12898.85 | D46: 664099.21 | E46: -676998.06 | F46: =VLOOKUP(B46,'Profit & Loss'!$B$2:$C$390,2,0) -> #N/A
A47: 10502 | B47: 1415192000 Inventory Parts Gross Hub Turn Over | C47: 2147285.4 | D47: 1613360.7 | E47: 533924.63 | F47: =VLOOKUP(B47,'Profit & Loss'!$B$2:$C$390,2,0) -> #N/A
A48: 10502 | B48: 1461001210 Inventory Parts GINI | C48: 2183327.3 | D48: 2390236.6 | E48: -206909.32 | F48: =VLOOKUP(B48,'Profit & Loss'!$B$2:$C$390,2,0) -> #N/A
A49: 10502 | B49: 1465011000 Inventory Parts GIT | C49: 4721680.6 | D49: 2883934.1 | E49: 1837746.4 | F49: =VLOOKUP(B49,'Profit & Loss'!$B$2:$C$390,2,0) -> #N/A
A50: 10502 | B50: 1465011002 Inventory Parts Freight & Handling (CLEARING) | C50: 39169.49 | D50: 40964.07 | E50: -1794.58 | F50: =VLOOKUP(B50,'Profit & Loss'!$B$2:$C$390,2,0) -> #N/A
A51: 10502 | B51: 1515001213 Landed Cost - Parts FH ITL Inbound Actual | C51: -1500790.2 | D51: -1499398.5 | E51: -1391.7 | F51: =VLOOKUP(B51,'Profit & Loss'!$B$2:$C$390,2,0) -> #N/A
A52: 10502 | B52: 1515001214 Landed Cost - Parts FH LCL Inbound Actual | C52: 11016.55 | D52: 11851.35 | E52: -834.8 | F52: =VLOOKUP(B52,'Profit & Loss'!$B$2:$C$390,2,0) -> #N/A
A53: 10502 | B53: 1515001215 Landed Cost - Parts FH LCL Outbound Actual | C53: -20542.04 | D53: -18605.45 | E53: -1936.59 | F53: =VLOOKUP(B53,'Profit & Loss'!$B$2:$C$390,2,0) -> #N/A
A54: 10502 | B54: 1515001216 Landed Cost - Parts FH ITL Outbound Actual | C54: -14272.3 | D54: -14261.14 | E54: -11.16 | F54: =VLOOKUP(B54,'Profit & Loss'!$B$2:$C$390,2,0) -> #N/A
A55: 10502 | C55: 20320296 | D55: 18342980 | E55: 1977316.1 | F55: =VLOOKUP(B55,'Profit & Loss'!$B$2:$C$390,2,0) -> #N/A
A56: 10503 | B56: 1565000000 WIP Parts | C56: 208218.69 | D56: 278291.8 | E56: -70073.11 | F56: =VLOOKUP(B56,'Profit & Loss'!$B$2:$C$390,2,0) -> #N/A
A57: 10503 | B57: 1565000010 WIP Parts Salvage | C57: 111.28 | D57: -4793.88 | E57: 4905.16 | F57: =VLOOKUP(B57,'Profit & Loss'!$B$2:$C$390,2,0) -> #N/A
A58: 10503 | B58: 1565000016 WIP Parts Minor Component (MICRC) | C58: 946.22 | D58: 946.22 | E58: 0 | F58: =VLOOKUP(B58,'Profit & Loss'!$B$2:$C$390,2,0) -> #N/A
A59: 10503 | B59: 1565000511 WIP Parts S.O.S. | C59: 346.46 | D59: 418.21 | E59: -71.75 | F59: =VLOOKUP(B59,'Profit & Loss'!$B$2:$C$390,2,0) -> #N/A
A60: 10503 | B60: 1566000010 WIP Service Labor | C60: 296419.49 | D60: 245192.53 | E60: 51226.96 | F60: =VLOOKUP(B60,'Profit & Loss'!$B$2:$C$390,2,0) -> #N/A
A61: 10503 | B61: 1566000020 WIP Service LPO | C61: 22410.21 | D61: 146477.68 | E61: -124067.47 | F61: =VLOOKUP(B61,'Profit & Loss'!$B$2:$C$390,2,0) -> #N/A
A62: 10503 | B62: 1566000050 WIP Service Travel | C62: 421.02 | D62: 420.63 | E62: 0.39 | F62: =VLOOKUP(B62,'Profit & Loss'!$B$2:$C$390,2,0) -> #N/A
A63: 10503 | C63: 528873.37 | D63: 666953.19 | E63: -138079.82 | F63: =VLOOKUP(B63,'Profit & Loss'!$B$2:$C$390,2,0) -> #N/A
A64: 105 | C64: 20849760 | D64: 18978137 | E64: 1871622.9 | F64: =VLOOKUP(B64,'Profit & Loss'!$B$2:$C$390,2,0) -> #N/A
A65: 10601 | B65: 1661023000 Prepaid Tax ART 23 | C65: 14166.64 | D65: 14166.64 | E65: 0 | F65: =VLOOKUP(B65,'Profit & Loss'!$B$2:$C$390,2,0) -> #N/A
A66: 10601 | C66: 14166.64 | D66: 14166.64 | E66: 0 | F66: =VLOOKUP(B66,'Profit & Loss'!$B$2:$C$390,2,0) -> #N/A
A67: 106 | C67: 14166.64 | D67: 14166.64 | E67: 0 | F67: =VLOOKUP(B67,'Profit & Loss'!$B$2:$C$390,2,0) -> #N/A
A68: 10701 | B68: 1612001010 Prepayment 3rd Party Office Rent | C68: -6135.39 | D68: -6135.39 | E68: 0 | F68: =VLOOKUP(B68,'Profit & Loss'!$B$2:$C$390,2,0) -> #N/A
A69: 10701 | B69: 1612001020 Prepayment 3rd Party Office Rent Imp (LHI) | C69: 9178.06 | D69: 9740.33 | E69: -562.27 | F69: =VLOOKUP(B69,'Profit & Loss'!$B$2:$C$390,2,0) -> #N/A
A70: 10701 | B70: 1612002000 Prepayment Related Party | C70: 6329.17 | D70: 6329.17 | E70: 0 | F70: =VLOOKUP(B70,'Profit & Loss'!$B$2:$C$390,2,0) -> #N/A
A71: 10701 | B71: 1630000010 Advance To Employee PC Advance | C71: 443.72 | D71: 346.79 | E71: 96.93 | F71: =VLOOKUP(B71,'Profit & Loss'!$B$2:$C$390,2,0) -> #N/A
A72: 10701 | B72: 1630000019 Advance To Employee PC Advance FxV | C72: 3.22 | D72: 0.01 | E72: 3.21 | F72: =VLOOKUP(B72,'Profit & Loss'!$B$2:$C$390,2,0) -> #N/A
A73: 10701 | B73: 1630000110 Advance To Employee Travel | C73: 48.03 | D73: 41.66 | E73: 6.37 | F73: =VLOOKUP(B73,'Profit & Loss'!$B$2:$C$390,2,0) -> #N/A
A74: 10701 | B74: 1630000119 Advance To Employee Travel Adv FxV | C74: 0.1 | D74: -0.25 | E74: 0.35 | F74: =VLOOKUP(B74,'Profit & Loss'!$B$2:$C$390,2,0) -> #N/A
A75: 10701 | C75: 9866.91 | D75: 10322.32 | E75: -455.41 | F75: =VLOOKUP(B75,'Profit & Loss'!$B$2:$C$390,2,0) -> #N/A
A76: 107 | C76: 9866.91 | D76: 10322.32 | E76: -455.41 | F76: =VLOOKUP(B76,'Profit & Loss'!$B$2:$C$390,2,0) -> #N/A
A77: 11001 | B77: 1811102000 FA Acquisition Owned Self Usage Building | C77: 359163.46 | D77: 359163.46 | E77: 0 | F77: =VLOOKUP(B77,'Profit & Loss'!$B$2:$C$390,2,0) -> #N/A
A78: 11001 | B78: 1821102000 FA Accumulated Depreciation Owned Building | C78: -261496.57 | D78: -260381.8 | E78: -1114.77 | F78: =VLOOKUP(B78,'Profit & Loss'!$B$2:$C$390,2,0) -> #N/A
A79: 11001 | C79: 97666.89 | D79: 98781.66 | E79: -1114.77 | F79: =VLOOKUP(B79,'Profit & Loss'!$B$2:$C$390,2,0) -> #N/A
A80: 11003 | B80: 1811115000 FA Acquisition Owned Warehouse Equip | C80: 132848.63 | D80: 132848.63 | E80: 0 | F80: =VLOOKUP(B80,'Profit & Loss'!$B$2:$C$390,2,0) -> #N/A
A81: 11003 | B81: 1811116000 FA Acquisition Owned Workshop Equip | C81: 765167.23 | D81: 516712.36 | E81: 248454.87 | F81: =VLOOKUP(B81,'Profit & Loss'!$B$2:$C$390,2,0) -> #N/A
A82: 11003 | B82: 1811117000 FA Acquisition Owned Service Tool | C82: 387205.26 | D82: 380820.83 | E82: 6384.43 | F82: =VLOOKUP(B82,'Profit & Loss'!$B$2:$C$390,2,0) -> #N/A
A83: 11003 | B83: 1811119000 FA Acquisition Owned Training Center Equipment | C83: 495.24 | D83: 495.24 | E83: 0 | F83: =VLOOKUP(B83,'Profit & Loss'!$B$2:$C$390,2,0) -> #N/A
A84: 11003 | B84: 1811140000 FA Acquisition Owned Office Equipment | C84: 258667.78 | D84: 247441.57 | E84: 11226.21 | F84: =VLOOKUP(B84,'Profit & Loss'!$B$2:$C$390,2,0) -> #N/A
A85: 11003 | B85: 1821115000 FA Accumulated Depreciation Owned Warehouse Equip | C85: -126369.44 | D85: -126094.93 | E85: -274.51 | F85: =VLOOKUP(B85,'Profit & Loss'!$B$2:$C$390,2,0) -> #N/A
A86: 11003 | B86: 1821116000 FA Accumulated Depreciation Owned Workshop Equip | C86: -436989.81 | D86: -302441.43 | E86: -134548.38 | F86: =VLOOKUP(B86,'Profit & Loss'!$B$2:$C$390,2,0) -> #N/A
A87: 11003 | B87: 1821117000 FA Accumulated Depreciation Owned Service Tool | C87: -306714.58 | D87: -304346.77 | E87: -2367.81 | F87: =VLOOKUP(B87,'Profit & Loss'!$B$2:$C$390,2,0) -> #N/A
A88: 11003 | B88: 1821119000 FA Accumulated Depreciation Owned TC Equip | C88: -495.24 | D88: -495.24 | E88: 0 | F88: =VLOOKUP(B88,'Profit & Loss'!$B$2:$C$390,2,0) -> #N/A
A89: 11003 | B89: 1821140000 FA Accumulated Depreciation Owned Office Equipment | C89: -212415.19 | D89: -210688.98 | E89: -1726.21 | F89: =VLOOKUP(B89,'Profit & Loss'!$B$2:$C$390,2,0) -> #N/A
A90: 11003 | C90: 461399.88 | D90: 334251.28 | E90: 127148.6 | F90: =VLOOKUP(B90,'Profit & Loss'!$B$2:$C$390,2,0) -> #N/A
A91: 11004 | B91: 1811301000 FA Acquisition Owned Rental Fleet Machine | C91: 18066691 | D91: 17497670 | E91: 569021.47 | F91: =VLOOKUP(B91,'Profit & Loss'!$B$2:$C$390,2,0) -> #N/A
A92: 11004 | B92: 1821301000 FA Accumulated Depreciation Owned Rental Fleet Mac | C92: -5702743.6 | D92: -5584939.9 | E92: -117803.68 | F92: =VLOOKUP(B92,'Profit & Loss'!$B$2:$C$390,2,0) -> #N/A
A93: 11004 | C93: 12363948 | D93: 11912730 | E93: 451217.79 | F93: =VLOOKUP(B93,'Profit & Loss'!$B$2:$C$390,2,0) -> #N/A
A94: 11005 | B94: 1811130000 FA Acquisition Owned Vehicle Sedan | C94: 152624.47 | D94: 152624.47 | E94: 0 | F94: =VLOOKUP(B94,'Profit & Loss'!$B$2:$C$390,2,0) -> #N/A
A95: 11005 | B95: 1811131000 FA Acquisition Owned Vehicle Truck | C95: 655044.08 | D95: 655044.08 | E95: 0 | F95: =VLOOKUP(B95,'Profit & Loss'!$B$2:$C$390,2,0) -> #N/A
A96: 11005 | B96: 1821130000 FA Accumulated Depreciation Owned Vehicle Sedan | C96: -151568.38 | D96: -151512.8 | E96: -55.58 | F96: =VLOOKUP(B96,'Profit & Loss'!$B$2:$C$390,2,0) -> #N/A
A97: 11005 | B97: 1821131000 FA Accumulated Depreciation Owned Vehicle Truck | C97: -672923.66 | D97: -671222.72 | E97: -1700.94 | F97: =VLOOKUP(B97,'Profit & Loss'!$B$2:$C$390,2,0) -> #N/A
A98: 11005 | C98: -16823.49 | D98: -15066.97 | E98: -1756.52 | F98: =VLOOKUP(B98,'Profit & Loss'!$B$2:$C$390,2,0) -> #N/A
A99: 11006 | B99: 1811160000 FA Acquisition Owned IT Devices Computer | C99: 4903.31 | D99: 4903.31 | E99: 0 | F99: =VLOOKUP(B99,'Profit & Loss'!$B$2:$C$390,2,0) -> #N/A
A100: 11006 | B100: 1813103000 FA Acquisition Lease IT Device | C100: 247830.51 | D100: 247830.51 | E100: 0 | F100: =VLOOKUP(B100,'Profit & Loss'!$B$2:$C$390,2,0) -> #N/A
...

Sheet JUN 22
A1: Financial Statement Item | B1: Text for B/S P&L item | C1: Total of reporting period | D1: Total of the comparison period | E1: Absolute difference | F1: Percentage difference
A2: 1000000 | B2: A S S E T S | C2: 0 | D2: 0 | E2: 0 | F2: =VLOOKUP(B2,'Profit & Loss'!$B$3:$C$390,2,0) -> #N/A
A3: 1000000 | B3: = = = = = = | C3: 0 | D3: 0 | E3: 0 | F3: =VLOOKUP(B3,'Profit & Loss'!$B$3:$C$390,2,0) -> #N/A
A4: 10101 | B4: 1011100380 PettyCash IDR SANGATTA | C4: 329.08 | D4: 329.08 | E4: 0 | F4: =VLOOKUP(B4,'Profit & Loss'!$B$3:$C$390,2,0) -> #N/A
A5: 10101 | B5: 1016109751 Bank IDR Mandiri 1480004169325 MB-SANGATA_COL | C5: 610.44 | D5: 610.44 | E5: 0 | F5: =VLOOKUP(B5,'Profit & Loss'!$B$3:$C$390,2,0) -> #N/A
A6: 10101 | B6: 1016109761 Bank IDR Mandiri 1480004169309 MB-SANGATA_OPR | C6: 27333.65 | D6: 27965.02 | E6: -631.37 | F6: =VLOOKUP(B6,'Profit & Loss'!$B$3:$C$390,2,0) -> #N/A
A7: 10101 | B7: 1016109769 Bank IDR Mandiri 1480004169309 FxV-SANGATA_OPR | C7: -23475.58 | D7: -23414.15 | E7: -61.43 | F7: =VLOOKUP(B7,'Profit & Loss'!$B$3:$C$390,2,0) -> #N/A
A8: 10101 | B8: 1016162071 Bank IDR Mandiri 148-001-687266-8 MB SGT | C8: 68.65 | D8: 68.61 | E8: 0.04 | F8: =VLOOKUP(B8,'Profit & Loss'!$B$3:$C$390,2,0) -> #N/A
A9: 10101 | B9: 1016162079 Bank IDR Mandiri 148-001-687266-8 FxV SGT | C9: 0.38 | D9: 1.87 | E9: -1.49 | F9: =VLOOKUP(B9,'Profit & Loss'!$B$3:$C$390,2,0) -> #N/A
A10: 10101 | C10: 4866.62 | D10: 5560.87 | E10: -694.25 | F10: =VLOOKUP(B10,'Profit & Loss'!$B$3:$C$390,2,0) -> #N/A
A11: 101 | C11: 4866.62 | D11: 5560.87 | E11: -694.25 | F11: =VLOOKUP(B11,'Profit & Loss'!$B$3:$C$390,2,0) -> #N/A
A12: 10201 | B12: 1110101000 AR Gross Trade 3rd Party | C12: 17993761 | D12: 15592930 | E12: 2400831.4 | F12: =VLOOKUP(B12,'Profit & Loss'!$B$3:$C$390,2,0) -> #N/A
A13: 10201 | B13: 1110101009 AR Gross Trade 3rd Party FxV | C13: -210470.35 | D13: -42604.13 | E13: -167866.22 | F13: =VLOOKUP(B13,'Profit & Loss'!$B$3:$C$390,2,0) -> #N/A
A14: 10201 | B14: 1110102000 AR Gross Trade Rel Party | C14: 1601815.6 | D14: 1601828.4 | E14: -12.84 | F14: =VLOOKUP(B14,'Profit & Loss'!$B$3:$C$390,2,0) -> #N/A
A15: 10201 | B15: 1110102009 AR Gross Trade Rel Party FxV | C15: -147864.41 | D15: -117425.53 | E15: -30438.88 | F15: =VLOOKUP(B15,'Profit & Loss'!$B$3:$C$390,2,0) -> #N/A
A16: 10201 | C16: 19237242 | D16: 17034729 | E16: 2202513.5 | F16: =VLOOKUP(B16,'Profit & Loss'!$B$3:$C$390,2,0) -> #N/A
A17: 10202 | B17: 1120101000 AR Gross Trade 3rd Party Allowance | C17: -46603.57 | D17: -44390.62 | E17: -2212.95 | F17: =VLOOKUP(B17,'Profit & Loss'!$B$3:$C$390,2,0) -> #N/A
A18: 10202 | C18: -46603.57 | D18: -44390.62 | E18: -2212.95 | F18: =VLOOKUP(B18,'Profit & Loss'!$B$3:$C$390,2,0) -> #N/A
A19: 102 | C19: 19190639 | D19: 16990338 | E19: 2200300.5 | F19: =VLOOKUP(B19,'Profit & Loss'!$B$3:$C$390,2,0) -> #N/A
A20: 10301 | B20: 1211101000 AR Claim Warranty Pending 3rd Party | C20: 0.01 | D20: 0.01 | E20: 0 | F20: =VLOOKUP(B20,'Profit & Loss'!$B$3:$C$390,2,0) -> #N/A
A21: 10301 | B21: 1211101001 AR Claim Warranty Pend Claim 3rd Party New Acct | C21: 4240.69 | D21: 3868.21 | E21: 372.48 | F21: =VLOOKUP(B21,'Profit & Loss'!$B$3:$C$390,2,0) -> #N/A
A22: 10301 | B22: 1211201311 AR Claim TWLBR | C22: 64966.35 | D22: 64064.44 | E22: 901.91 | F22: =VLOOKUP(B22,'Profit & Loss'!$B$3:$C$390,2,0) -> #N/A
A23: 10301 | B23: 1211301000 AR Claim Warranty Claim 3rd Party | C23: 0.01 | D23: 0.01 | E23: 0 | F23: =VLOOKUP(B23,'Profit & Loss'!$B$3:$C$390,2,0) -> #N/A
A24: 10301 | B24: 1211301001 AR Claim Warranty Claim 3rd Party New | C24: 28368.56 | D24: 15779.64 | E24: 12588.92 | F24: =VLOOKUP(B24,'Profit & Loss'!$B$3:$C$390,2,0) -> #N/A
A25: 10301 | B25: 1211401001 AR Claim 3rd Party Goodwill (New Acct) | C25: 57645.23 | D25: 25960.5 | E25: 31684.73 | F25: =VLOOKUP(B25,'Profit & Loss'!$B$3:$C$390,2,0) -> #N/A
A26: 10301 | B26: 1211401310 AR Claim Warranty Claim-Goodwill 3rd Party OEM | C26: 19.35 | D26: 19.35 | E26: 0 | F26: =VLOOKUP(B26,'Profit & Loss'!$B$3:$C$390,2,0) -> #N/A
A27: 10301 | C27: 155240.2 | D27: 109692.16 | E27: 45548.04 | F27: =VLOOKUP(B27,'Profit & Loss'!$B$3:$C$390,2,0) -> #N/A
A28: 10302 | B28: 1212001010 AR Claim 3rd Party CAT Parts Core | C28: 130819.01 | D28: -5282.2 | E28: 136101.21 | F28: =VLOOKUP(B28,'Profit & Loss'!$B$3:$C$390,2,0) -> #N/A
A29: 10302 | C29: 130819.01 | D29: -5282.2 | E29: 136101.21 | F29: =VLOOKUP(B29,'Profit & Loss'!$B$3:$C$390,2,0) -> #N/A
A30: 10306 | B30: 1110101230 AR Gross Trade 3rd Party Art23 | C30: 56103.77 | D30: 53215.46 | E30: 2888.31 | F30: =VLOOKUP(B30,'Profit & Loss'!$B$3:$C$390,2,0) -> #N/A
A31: 10306 | B31: 1110101239 AR Gross Trade 3rd Party Art23 FxV | C31: -647.28 | D31: -41.52 | E31: -605.76 | F31: =VLOOKUP(B31,'Profit & Loss'!$B$3:$C$390,2,0) -> #N/A
A32: 10306 | B32: 1110181000 AR Gross Others Project System Over Under | C32: 2597.52 | D32: 2597.52 | E32: 0 | F32: =VLOOKUP(B32,'Profit & Loss'!$B$3:$C$390,2,0) -> #N/A
A33: 10306 | B33: 1110202000 AR Gross Non Trade Rel Party | C33: 5352.52 | D33: 5352.52 | E33: 0 | F33: =VLOOKUP(B33,'Profit & Loss'!$B$3:$C$390,2,0) -> #N/A
A34: 10306 | B34: 1110202009 AR Gross Non Trade Rel Party FxV | C34: -157.12 | D34: -48.36 | E34: -108.76 | F34: =VLOOKUP(B34,'Profit & Loss'!$B$3:$C$390,2,0) -> #N/A
A35: 10306 | B35: 1216001020 AR Claim 3rd Party CAT PSDN | C35: 64.12 | D35: -9391.58 | E35: 9455.7 | F35: =VLOOKUP(B35,'Profit & Loss'!$B$3:$C$390,2,0) -> #N/A
A36: 10306 | B36: 1219301000 AR Claim Others 3rd Party | C36: 3056.82 | D36: 2138.75 | E36: 918.07 | F36: =VLOOKUP(B36,'Profit & Loss'!$B$3:$C$390,2,0) -> #N/A
A37: 10306 | B37: 1219302070 AR Claim Others Rel Party CKB | C37: 47.5 | D37: 42.92 | E37: 4.58 | F37: =VLOOKUP(B37,'Profit & Loss'!$B$3:$C$390,2,0) -> #N/A
A38: 10306 | C38: 66417.85 | D38: 53865.71 | E38: 12552.14 | F38: =VLOOKUP(B38,'Profit & Loss'!$B$3:$C$390,2,0) -> #N/A
A39: 103 | C39: 352477.06 | D39: 158275.67 | E39: 194201.39 | F39: =VLOOKUP(B39,'Profit & Loss'!$B$3:$C$390,2,0) -> #N/A
A40: 10501 | B40: 1411191200 Inventory PP Freight & Handling (CLEARING) | C40: -0.1 | D40: -0.1 | E40: 0 | F40: =VLOOKUP(B40,'Profit & Loss'!$B$3:$C$390,2,0) -> #N/A
A41: 10501 | B41: 1460200000 Inventory PP GIT Non Trade | C41: -176.64 | D41: 591.19 | E41: -767.83 | F41: =VLOOKUP(B41,'Profit & Loss'!$B$3:$C$390,2,0) -> #N/A
A42: 10501 | C42: -176.74 | D42: 591.09 | E42: -767.83 | F42: =VLOOKUP(B42,'Profit & Loss'!$B$3:$C$390,2,0) -> #N/A
A43: 10502 | B43: 1415101000 Inventory Parts Stock On Hand | C43: 13391890 | D43: 12765262 | E43: 626627.95 | F43: =VLOOKUP(B43,'Profit & Loss'!$B$3:$C$390,2,0) -> #N/A
A44: 10502 | B44: 1415111800 Inventory Parts PEX Core Raw Material | C44: 0 | D44: 1057.78 | E44: -1057.78 | F44: =VLOOKUP(B44,'Profit & Loss'!$B$3:$C$390,2,0) -> #N/A
A45: 10502 | B45: 1415141666 Inventory Parts PVRG SPM - SOA | C45: -95877.43 | D45: -12898.85 | E45: -82978.58 | F45: =VLOOKUP(B45,'Profit & Loss'!$B$3:$C$390,2,0) -> #N/A
A46: 10502 | B46: 1415192000 Inventory Parts Gross Hub Turn Over | C46: 1689711.4 | D46: 2147285.4 | E46: -457574.01 | F46: =VLOOKUP(B46,'Profit & Loss'!$B$3:$C$390,2,0) -> #N/A
A47: 10502 | B47: 1461001210 Inventory Parts GINI | C47: 2477566.8 | D47: 2183327.3 | E47: 294239.5 | F47: =VLOOKUP(B47,'Profit & Loss'!$B$3:$C$390,2,0) -> #N/A
A48: 10502 | B48: 1465011000 Inventory Parts GIT | C48: 3969696.2 | D48: 4721680.6 | E48: -751984.37 | F48: =VLOOKUP(B48,'Profit & Loss'!$B$3:$C$390,2,0) -> #N/A
A49: 10502 | B49: 1465011002 Inventory Parts Freight & Handling (CLEARING) | C49: 25109.58 | D49: 39169.49 | E49: -14059.91 | F49: =VLOOKUP(B49,'Profit & Loss'!$B$3:$C$390,2,0) -> #N/A
A50: 10502 | B50: 1515001213 Landed Cost - Parts FH ITL Inbound Actual | C50: -1404046.2 | D50: -1500790.2 | E50: 96743.99 | F50: =VLOOKUP(B50,'Profit & Loss'!$B$3:$C$390,2,0) -> #N/A
A51: 10502 | B51: 1515001214 Landed Cost - Parts FH LCL Inbound Actual | C51: 11380.59 | D51: 11016.55 | E51: 364.04 | F51: =VLOOKUP(B51,'Profit & Loss'!$B$3:$C$390,2,0) -> #N/A
A52: 10502 | B52: 1515001215 Landed Cost - Parts FH LCL Outbound Actual | C52: -19272.73 | D52: -20542.04 | E52: 1269.31 | F52: =VLOOKUP(B52,'Profit & Loss'!$B$3:$C$390,2,0) -> #N/A
A53: 10502 | B53: 1515001216 Landed Cost - Parts FH ITL Outbound Actual | C53: -14059.92 | D53: -14272.3 | E53: 212.38 | F53: =VLOOKUP(B53,'Profit & Loss'!$B$3:$C$390,2,0) -> #N/A
A54: 10502 | C54: 20032098 | D54: 20320296 | E54: -288197.48 | F54: =VLOOKUP(B54,'Profit & Loss'!$B$3:$C$390,2,0) -> #N/A
A55: 10503 | B55: 1565000000 WIP Parts | C55: 220899.3 | D55: 208218.69 | E55: 12680.61 | F55: =VLOOKUP(B55,'Profit & Loss'!$B$3:$C$390,2,0) -> #N/A
A56: 10503 | B56: 1565000010 WIP Parts Salvage | C56: 100.78 | D56: 111.28 | E56: -10.5 | F56: =VLOOKUP(B56,'Profit & Loss'!$B$3:$C$390,2,0) -> #N/A
A57: 10503 | B57: 1565000016 WIP Parts Minor Component (MICRC) | C57: 946.22 | D57: 946.22 | E57: 0 | F57: =VLOOKUP(B57,'Profit & Loss'!$B$3:$C$390,2,0) -> #N/A
A58: 10503 | B58: 1565000511 WIP Parts S.O.S. | C58: 388.11 | D58: 346.46 | E58: 41.65 | F58: =VLOOKUP(B58,'Profit & Loss'!$B$3:$C$390,2,0) -> #N/A
A59: 10503 | B59: 1566000010 WIP Service Labor | C59: 217186.98 | D59: 296419.49 | E59: -79232.51 | F59: =VLOOKUP(B59,'Profit & Loss'!$B$3:$C$390,2,0) -> #N/A
A60: 10503 | B60: 1566000020 WIP Service LPO | C60: 58879.92 | D60: 22410.21 | E60: 36469.71 | F60: =VLOOKUP(B60,'Profit & Loss'!$B$3:$C$390,2,0) -> #N/A
A61: 10503 | B61: 1566000050 WIP Service Travel | C61: 375.36 | D61: 421.02 | E61: -45.66 | F61: =VLOOKUP(B61,'Profit & Loss'!$B$3:$C$390,2,0) -> #N/A
A62: 10503 | C62: 498776.67 | D62: 528873.37 | E62: -30096.7 | F62: =VLOOKUP(B62,'Profit & Loss'!$B$3:$C$390,2,0) -> #N/A
A63: 105 | C63: 20530698 | D63: 20849760 | E63: -319062.01 | F63: =VLOOKUP(B63,'Profit & Loss'!$B$3:$C$390,2,0) -> #N/A
A64: 10601 | B64: 1661023000 Prepaid Tax ART 23 | C64: 0 | D64: 14166.64 | E64: -14166.64 | F64: =VLOOKUP(B64,'Profit & Loss'!$B$3:$C$390,2,0) -> #N/A
A65: 10601 | C65: 0 | D65: 14166.64 | E65: -14166.64 | F65: =VLOOKUP(B65,'Profit & Loss'!$B$3:$C$390,2,0) -> #N/A
A66: 106 | C66: 0 | D66: 14166.64 | E66: -14166.64 | F66: =VLOOKUP(B66,'Profit & Loss'!$B$3:$C$390,2,0) -> #N/A
A67: 10701 | B67: 1612001010 Prepayment 3rd Party Office Rent | C67: -6135.39 | D67: -6135.39 | E67: 0 | F67: =VLOOKUP(B67,'Profit & Loss'!$B$3:$C$390,2,0) -> #N/A
A68: 10701 | B68: 1612001020 Prepayment 3rd Party Office Rent Imp (LHI) | C68: 8601.35 | D68: 9178.06 | E68: -576.71 | F68: =VLOOKUP(B68,'Profit & Loss'!$B$3:$C$390,2,0) -> #N/A
A69: 10701 | B69: 1612002000 Prepayment Related Party | C69: 6329.17 | D69: 6329.17 | E69: 0 | F69: =VLOOKUP(B69,'Profit & Loss'!$B$3:$C$390,2,0) -> #N/A
A70: 10701 | B70: 1630000010 Advance To Employee PC Advance | C70: 0 | D70: 443.72 | E70: -443.72 | F70: =VLOOKUP(B70,'Profit & Loss'!$B$3:$C$390,2,0) -> #N/A
A71: 10701 | B71: 1630000019 Advance To Employee PC Advance FxV | C71: 0 | D71: 3.22 | E71: -3.22 | F71: =VLOOKUP(B71,'Profit & Loss'!$B$3:$C$390,2,0) -> #N/A
A72: 10701 | B72: 1630000110 Advance To Employee Travel | C72: 886.17 | D72: 48.03 | E72: 838.14 | F72: =VLOOKUP(B72,'Profit & Loss'!$B$3:$C$390,2,0) -> #N/A
A73: 10701 | B73: 1630000119 Advance To Employee Travel Adv FxV | C73: -9.14 | D73: 0.1 | E73: -9.24 | F73: =VLOOKUP(B73,'Profit & Loss'!$B$3:$C$390,2,0) -> #N/A
A74: 10701 | C74: 9672.16 | D74: 9866.91 | E74: -194.75 | F74: =VLOOKUP(B74,'Profit & Loss'!$B$3:$C$390,2,0) -> #N/A
A75: 107 | C75: 9672.16 | D75: 9866.91 | E75: -194.75 | F75: =VLOOKUP(B75,'Profit & Loss'!$B$3:$C$390,2,0) -> #N/A
A76: 11001 | B76: 1811102000 FA Acquisition Owned Self Usage Building | C76: 359163.46 | D76: 359163.46 | E76: 0 | F76: =VLOOKUP(B76,'Profit & Loss'!$B$3:$C$390,2,0) -> #N/A
A77: 11001 | B77: 1821102000 FA Accumulated Depreciation Owned Building | C77: -262611.32 | D77: -261496.57 | E77: -1114.75 | F77: =VLOOKUP(B77,'Profit & Loss'!$B$3:$C$390,2,0) -> #N/A
A78: 11001 | C78: 96552.14 | D78: 97666.89 | E78: -1114.75 | F78: =VLOOKUP(B78,'Profit & Loss'!$B$3:$C$390,2,0) -> #N/A
A79: 11003 | B79: 1811115000 FA Acquisition Owned Warehouse Equip | C79: 132848.63 | D79: 132848.63 | E79: 0 | F79: =VLOOKUP(B79,'Profit & Loss'!$B$3:$C$390,2,0) -> #N/A
A80: 11003 | B80: 1811116000 FA Acquisition Owned Workshop Equip | C80: 767309.11 | D80: 765167.23 | E80: 2141.88 | F80: =VLOOKUP(B80,'Profit & Loss'!$B$3:$C$390,2,0) -> #N/A
A81: 11003 | B81: 1811117000 FA Acquisition Owned Service Tool | C81: 380496.66 | D81: 387205.26 | E81: -6708.6 | F81: =VLOOKUP(B81,'Profit & Loss'!$B$3:$C$390,2,0) -> #N/A
A82: 11003 | B82: 1811119000 FA Acquisition Owned Training Center Equipment | C82: 495.24 | D82: 495.24 | E82: 0 | F82: =VLOOKUP(B82,'Profit & Loss'!$B$3:$C$390,2,0) -> #N/A
A83: 11003 | B83: 1811140000 FA Acquisition Owned Office Equipment | C83: 263566.81 | D83: 258667.78 | E83: 4899.03 | F83: =VLOOKUP(B83,'Profit & Loss'!$B$3:$C$390,2,0) -> #N/A
A84: 11003 | B84: 1821115000 FA Accumulated Depreciation Owned Warehouse Equip | C84: -126644.01 | D84: -126369.44 | E84: -274.57 | F84: =VLOOKUP(B84,'Profit & Loss'!$B$3:$C$390,2,0) -> #N/A
A85: 11003 | B85: 1821116000 FA Accumulated Depreciation Owned Workshop Equip | C85: -442801.36 | D85: -436989.81 | E85: -5811.55 | F85: =VLOOKUP(B85,'Profit & Loss'!$B$3:$C$390,2,0) -> #N/A
A86: 11003 | B86: 1821117000 FA Accumulated Depreciation Owned Service Tool | C86: -302267.12 | D86: -306714.58 | E86: 4447.46 | F86: =VLOOKUP(B86,'Profit & Loss'!$B$3:$C$390,2,0) -> #N/A
A87: 11003 | B87: 1821119000 FA Accumulated Depreciation Owned TC Equip | C87: -495.24 | D87: -495.24 | E87: 0 | F87: =VLOOKUP(B87,'Profit & Loss'!$B$3:$C$390,2,0) -> #N/A
A88: 11003 | B88: 1821140000 FA Accumulated Depreciation Owned Office Equipment | C88: -214623.59 | D88: -212415.19 | E88: -2208.4 | F88: =VLOOKUP(B88,'Profit & Loss'!$B$3:$C$390,2,0) -> #N/A
A89: 11003 | C89: 457885.13 | D89: 461399.88 | E89: -3514.75 | F89: =VLOOKUP(B89,'Profit & Loss'!$B$3:$C$390,2,0) -> #N/A
A90: 11004 | B90: 1811301000 FA Acquisition Owned Rental Fleet Machine | C90: 18985572 | D90: 18066691 | E90: 918880.37 | F90: =VLOOKUP(B90,'Profit & Loss'!$B$3:$C$390,2,0) -> #N/A
A91: 11004 | B91: 1821301000 FA Accumulated Depreciation Owned Rental Fleet Mac | C91: -6307736.2 | D91: -5702743.6 | E91: -604992.63 | F91: =VLOOKUP(B91,'Profit & Loss'!$B$3:$C$390,2,0) -> #N/A
A92: 11004 | C92: 12677835 | D92: 12363948 | E92: 313887.74 | F92: =VLOOKUP(B92,'Profit & Loss'!$B$3:$C$390,2,0) -> #N/A
A93: 11005 | B93: 1811130000 FA Acquisition Owned Vehicle Sedan | C93: 103060.72 | D93: 152624.47 | E93: -49563.75 | F93: =VLOOKUP(B93,'Profit & Loss'!$B$3:$C$390,2,0) -> #N/A
A94: 11005 | B94: 1811131000 FA Acquisition Owned Vehicle Truck | C94: 655044.08 | D94: 655044.08 | E94: 0 | F94: =VLOOKUP(B94,'Profit & Loss'!$B$3:$C$390,2,0) -> #N/A
A95: 11005 | B95: 1821130000 FA Accumulated Depreciation Owned Vehicle Sedan | C95: -102060.21 | D95: -151568.38 | E95: 49508.17 | F95: =VLOOKUP(B95,'Profit & Loss'!$B$3:$C$390,2,0) -> #N/A
A96: 11005 | B96: 1821131000 FA Accumulated Depreciation Owned Vehicle Truck | C96: -674624.6 | D96: -672923.66 | E96: -1700.94 | F96: =VLOOKUP(B96,'Profit & Loss'!$B$3:$C$390,2,0) -> #N/A
A97: 11005 | C97: -18580.01 | D97: -16823.49 | E97: -1756.52 | F97: =VLOOKUP(B97,'Profit & Loss'!$B$3:$C$390,2,0) -> #N/A
A98: 11006 | B98: 1811160000 FA Acquisition Owned IT Devices Computer | C98: 4903.31 | D98: 4903.31 | E98: 0 | F98: =VLOOKUP(B98,'Profit & Loss'!$B$3:$C$390,2,0) -> #N/A
A99: 11006 | B99: 1813103000 FA Acquisition Lease IT Device | C99: 255044.67 | D99: 247830.51 | E99: 7214.16 | F99: =VLOOKUP(B99,'Profit & Loss'!$B$3:$C$390,2,0) -> #N/A
A100: 11006 | B100: 1821160000 FA Accumulated Depreciation Owned IT Devices Comp | C100: -3568.08 | D100: -3495.93 | E100: -72.15 | F100: =VLOOKUP(B100,'Profit & Loss'!$B$3:$C$390,2,0) -> #N/A
...

Sheet JUL 22
A1: Financial Statement Item | B1: Text for B/S P&L item | C1: Total of reporting period | D1: Total of the comparison period | E1: Absolute difference | F1: Percentage difference
A2: 1000000 | B2: A S S E T S | C2: 0 | D2: 0 | E2: 0 | F2: =VLOOKUP(B2,'Profit & Loss'!$B$3:$C$390,2,0) -> #N/A
A3: 1000000 | B3: = = = = = = | C3: 0 | D3: 0 | E3: 0 | F3: =VLOOKUP(B3,'Profit & Loss'!$B$3:$C$390,2,0) -> #N/A
A4: 10101 | B4: 1011100380 PettyCash IDR SANGATTA | C4: 329.08 | D4: 329.08 | E4: 0 | F4: =VLOOKUP(B4,'Profit & Loss'!$B$3:$C$390,2,0) -> #N/A
A5: 10101 | B5: 1016109751 Bank IDR Mandiri 1480004169325 MB-SANGATA_COL | C5: 610.44 | D5: 610.44 | E5: 0 | F5: =VLOOKUP(B5,'Profit & Loss'!$B$3:$C$390,2,0) -> #N/A
A6: 10101 | B6: 1016109761 Bank IDR Mandiri 1480004169309 MB-SANGATA_OPR | C6: 23570.12 | D6: 27333.65 | E6: -3763.53 | F6: =VLOOKUP(B6,'Profit & Loss'!$B$3:$C$390,2,0) -> #N/A
A7: 10101 | B7: 1016109769 Bank IDR Mandiri 1480004169309 FxV-SANGATA_OPR | C7: -23497.99 | D7: -23475.58 | E7: -22.41 | F7: =VLOOKUP(B7,'Profit & Loss'!$B$3:$C$390,2,0) -> #N/A
A8: 10101 | B8: 1016162071 Bank IDR Mandiri 148-001-687266-8 MB SGT | C8: 68.67 | D8: 68.65 | E8: 0.02 | F8: =VLOOKUP(B8,'Profit & Loss'!$B$3:$C$390,2,0) -> #N/A
A9: 10101 | B9: 1016162079 Bank IDR Mandiri 148-001-687266-8 FxV SGT | C9: -0.15 | D9: 0.38 | E9: -0.53 | F9: =VLOOKUP(B9,'Profit & Loss'!$B$3:$C$390,2,0) -> #N/A
A10: 10101 | C10: 1080.17 | D10: 4866.62 | E10: -3786.45 | F10: =VLOOKUP(B10,'Profit & Loss'!$B$3:$C$390,2,0) -> #N/A
A11: 101 | C11: 1080.17 | D11: 4866.62 | E11: -3786.45 | F11: =VLOOKUP(B11,'Profit & Loss'!$B$3:$C$390,2,0) -> #N/A
A12: 10201 | B12: 1110101000 AR Gross Trade 3rd Party | C12: 17667531 | D12: 17993761 | E12: -326230.09 | F12: =VLOOKUP(B12,'Profit & Loss'!$B$3:$C$390,2,0) -> #N/A
A13: 10201 | B13: 1110101009 AR Gross Trade 3rd Party FxV | C13: -132641.85 | D13: -210470.35 | E13: 77828.5 | F13: =VLOOKUP(B13,'Profit & Loss'!$B$3:$C$390,2,0) -> #N/A
A14: 10201 | B14: 1110102000 AR Gross Trade Rel Party | C14: 1601815.6 | D14: 1601815.6 | E14: 0 | F14: =VLOOKUP(B14,'Profit & Loss'!$B$3:$C$390,2,0) -> #N/A
A15: 10201 | B15: 1110102009 AR Gross Trade Rel Party FxV | C15: -158658.29 | D15: -147864.41 | E15: -10793.88 | F15: =VLOOKUP(B15,'Profit & Loss'!$B$3:$C$390,2,0) -> #N/A
A16: 10201 | C16: 18978047 | D16: 19237242 | E16: -259195.47 | F16: =VLOOKUP(B16,'Profit & Loss'!$B$3:$C$390,2,0) -> #N/A
A17: 10202 | B17: 1120101000 AR Gross Trade 3rd Party Allowance | C17: -45397.71 | D17: -46603.57 | E17: 1205.86 | F17: =VLOOKUP(B17,'Profit & Loss'!$B$3:$C$390,2,0) -> #N/A
A18: 10202 | C18: -45397.71 | D18: -46603.57 | E18: 1205.86 | F18: =VLOOKUP(B18,'Profit & Loss'!$B$3:$C$390,2,0) -> #N/A
A19: 102 | C19: 18932649 | D19: 19190639 | E19: -257989.61 | F19: =VLOOKUP(B19,'Profit & Loss'!$B$3:$C$390,2,0) -> #N/A
A20: 10301 | B20: 1211101000 AR Claim Warranty Pending 3rd Party | C20: 0.01 | D20: 0.01 | E20: 0 | F20: =VLOOKUP(B20,'Profit & Loss'!$B$3:$C$390,2,0) -> #N/A
A21: 10301 | B21: 1211101001 AR Claim Warranty Pend Claim 3rd Party New Acct | C21: 4240.69 | D21: 4240.69 | E21: 0 | F21: =VLOOKUP(B21,'Profit & Loss'!$B$3:$C$390,2,0) -> #N/A
A22: 10301 | B22: 1211201311 AR Claim TWLBR | C22: 65165.56 | D22: 64966.35 | E22: 199.21 | F22: =VLOOKUP(B22,'Profit & Loss'!$B$3:$C$390,2,0) -> #N/A
A23: 10301 | B23: 1211301000 AR Claim Warranty Claim 3rd Party | C23: 0.01 | D23: 0.01 | E23: 0 | F23: =VLOOKUP(B23,'Profit & Loss'!$B$3:$C$390,2,0) -> #N/A
A24: 10301 | B24: 1211301001 AR Claim Warranty Claim 3rd Party New | C24: 78877.12 | D24: 28368.56 | E24: 50508.56 | F24: =VLOOKUP(B24,'Profit & Loss'!$B$3:$C$390,2,0) -> #N/A
A25: 10301 | B25: 1211401001 AR Claim 3rd Party Goodwill (New Acct) | C25: 12137.87 | D25: 57645.23 | E25: -45507.36 | F25: =VLOOKUP(B25,'Profit & Loss'!$B$3:$C$390,2,0) -> #N/A
A26: 10301 | B26: 1211401310 AR Claim Warranty Claim-Goodwill 3rd Party OEM | C26: 19.35 | D26: 19.35 | E26: 0 | F26: =VLOOKUP(B26,'Profit & Loss'!$B$3:$C$390,2,0) -> #N/A
A27: 10301 | C27: 160440.61 | D27: 155240.2 | E27: 5200.41 | F27: =VLOOKUP(B27,'Profit & Loss'!$B$3:$C$390,2,0) -> #N/A
A28: 10302 | B28: 1212001010 AR Claim 3rd Party CAT Parts Core | C28: 119174.5 | D28: 130819.01 | E28: -11644.51 | F28: =VLOOKUP(B28,'Profit & Loss'!$B$3:$C$390,2,0) -> #N/A
A29: 10302 | C29: 119174.5 | D29: 130819.01 | E29: -11644.51 | F29: =VLOOKUP(B29,'Profit & Loss'!$B$3:$C$390,2,0) -> #N/A
A30: 10306 | B30: 1110101230 AR Gross Trade 3rd Party Art23 | C30: 60688.53 | D30: 56103.77 | E30: 4584.76 | F30: =VLOOKUP(B30,'Profit & Loss'!$B$3:$C$390,2,0) -> #N/A
A31: 10306 | B31: 1110101239 AR Gross Trade 3rd Party Art23 FxV | C31: -181.72 | D31: -647.28 | E31: 465.56 | F31: =VLOOKUP(B31,'Profit & Loss'!$B$3:$C$390,2,0) -> #N/A
A32: 10306 | B32: 1110181000 AR Gross Others Project System Over Under | C32: 2597.52 | D32: 2597.52 | E32: 0 | F32: =VLOOKUP(B32,'Profit & Loss'!$B$3:$C$390,2,0) -> #N/A
A33: 10306 | B33: 1110202000 AR Gross Non Trade Rel Party | C33: 0 | D33: 5352.52 | E33: -5352.52 | F33: =VLOOKUP(B33,'Profit & Loss'!$B$3:$C$390,2,0) -> #N/A
A34: 10306 | B34: 1110202009 AR Gross Non Trade Rel Party FxV | C34: 0 | D34: -157.12 | E34: 157.12 | F34: =VLOOKUP(B34,'Profit & Loss'!$B$3:$C$390,2,0) -> #N/A
A35: 10306 | B35: 1216001020 AR Claim 3rd Party CAT PSDN | C35: 851.34 | D35: 64.12 | E35: 787.22 | F35: =VLOOKUP(B35,'Profit & Loss'!$B$3:$C$390,2,0) -> #N/A
A36: 10306 | B36: 1219301000 AR Claim Others 3rd Party | C36: 18.22 | D36: 3056.82 | E36: -3038.6 | F36: =VLOOKUP(B36,'Profit & Loss'!$B$3:$C$390,2,0) -> #N/A
A37: 10306 | B37: 1219302070 AR Claim Others Rel Party CKB | C37: 49.13 | D37: 47.5 | E37: 1.63 | F37: =VLOOKUP(B37,'Profit & Loss'!$B$3:$C$390,2,0) -> #N/A
A38: 10306 | C38: 64023.02 | D38: 66417.85 | E38: -2394.83 | F38: =VLOOKUP(B38,'Profit & Loss'!$B$3:$C$390,2,0) -> #N/A
A39: 103 | C39: 343638.13 | D39: 352477.06 | E39: -8838.93 | F39: =VLOOKUP(B39,'Profit & Loss'!$B$3:$C$390,2,0) -> #N/A
A40: 10501 | B40: 1411101100 Inventory PP Unit | C40: 858469.17 | D40: 0 | E40: 858469.17 | F40: =VLOOKUP(B40,'Profit & Loss'!$B$3:$C$390,2,0) -> #N/A
A41: 10501 | B41: 1411191200 Inventory PP Freight & Handling (CLEARING) | C41: -0.1 | D41: -0.1 | E41: 0 | F41: =VLOOKUP(B41,'Profit & Loss'!$B$3:$C$390,2,0) -> #N/A
A42: 10501 | B42: 1460200000 Inventory PP GIT Non Trade | C42: 834.49 | D42: -176.64 | E42: 1011.13 | F42: =VLOOKUP(B42,'Profit & Loss'!$B$3:$C$390,2,0) -> #N/A
A43: 10501 | C43: 859303.56 | D43: -176.74 | E43: 859480.3 | F43: =VLOOKUP(B43,'Profit & Loss'!$B$3:$C$390,2,0) -> #N/A
A44: 10502 | B44: 1415101000 Inventory Parts Stock On Hand | C44: 14289776 | D44: 13391890 | E44: 897886.27 | F44: =VLOOKUP(B44,'Profit & Loss'!$B$3:$C$390,2,0) -> #N/A
A45: 10502 | B45: 1415141007 Inv Parts Gross PVRG PO BUY BACK | C45: -1331.92 | D45: 0 | E45: -1331.92 | F45: =VLOOKUP(B45,'Profit & Loss'!$B$3:$C$390,2,0) -> #N/A
A46: 10502 | B46: 1415141666 Inventory Parts PVRG SPM - SOA | C46: -102116.81 | D46: -95877.43 | E46: -6239.38 | F46: =VLOOKUP(B46,'Profit & Loss'!$B$3:$C$390,2,0) -> #N/A
A47: 10502 | B47: 1415192000 Inventory Parts Gross Hub Turn Over | C47: 2147331.5 | D47: 1689711.4 | E47: 457620.16 | F47: =VLOOKUP(B47,'Profit & Loss'!$B$3:$C$390,2,0) -> #N/A
A48: 10502 | B48: 1461001210 Inventory Parts GINI | C48: 2557589.6 | D48: 2477566.8 | E48: 80022.81 | F48: =VLOOKUP(B48,'Profit & Loss'!$B$3:$C$390,2,0) -> #N/A
A49: 10502 | B49: 1465011000 Inventory Parts GIT | C49: 7285841.3 | D49: 3969696.2 | E49: 3316145.1 | F49: =VLOOKUP(B49,'Profit & Loss'!$B$3:$C$390,2,0) -> #N/A
A50: 10502 | B50: 1465011001 Inventory Parts GIT - Parts Back Order | C50: -27.65 | D50: 0 | E50: -27.65 | F50: =VLOOKUP(B50,'Profit & Loss'!$B$3:$C$390,2,0) -> #N/A
A51: 10502 | B51: 1465011002 Inventory Parts Freight & Handling (CLEARING) | C51: 27592.92 | D51: 25109.58 | E51: 2483.34 | F51: =VLOOKUP(B51,'Profit & Loss'!$B$3:$C$390,2,0) -> #N/A
A52: 10502 | B52: 1515001213 Landed Cost - Parts FH ITL Inbound Actual | C52: -1501458.3 | D52: -1404046.2 | E52: -97412.14 | F52: =VLOOKUP(B52,'Profit & Loss'!$B$3:$C$390,2,0) -> #N/A
A53: 10502 | B53: 1515001214 Landed Cost - Parts FH LCL Inbound Actual | C53: 10841.26 | D53: 11380.59 | E53: -539.33 | F53: =VLOOKUP(B53,'Profit & Loss'!$B$3:$C$390,2,0) -> #N/A
A54: 10502 | B54: 1515001215 Landed Cost - Parts FH LCL Outbound Actual | C54: -21610.98 | D54: -19272.73 | E54: -2338.25 | F54: =VLOOKUP(B54,'Profit & Loss'!$B$3:$C$390,2,0) -> #N/A
A55: 10502 | B55: 1515001216 Landed Cost - Parts FH ITL Outbound Actual | C55: -14272.25 | D55: -14059.92 | E55: -212.33 | F55: =VLOOKUP(B55,'Profit & Loss'!$B$3:$C$390,2,0) -> #N/A
A56: 10502 | C56: 24678155 | D56: 20032098 | E56: 4646056.6 | F56: =VLOOKUP(B56,'Profit & Loss'!$B$3:$C$390,2,0) -> #N/A
A57: 10503 | B57: 1565000000 WIP Parts | C57: 247407.29 | D57: 220899.3 | E57: 26507.99 | F57: =VLOOKUP(B57,'Profit & Loss'!$B$3:$C$390,2,0) -> #N/A
A58: 10503 | B58: 1565000010 WIP Parts Salvage | C58: 100.78 | D58: 100.78 | E58: 0 | F58: =VLOOKUP(B58,'Profit & Loss'!$B$3:$C$390,2,0) -> #N/A
A59: 10503 | B59: 1565000016 WIP Parts Minor Component (MICRC) | C59: 946.22 | D59: 946.22 | E59: 0 | F59: =VLOOKUP(B59,'Profit & Loss'!$B$3:$C$390,2,0) -> #N/A
A60: 10503 | B60: 1565000511 WIP Parts S.O.S. | C60: 330.52 | D60: 388.11 | E60: -57.59 | F60: =VLOOKUP(B60,'Profit & Loss'!$B$3:$C$390,2,0) -> #N/A
A61: 10503 | B61: 1566000010 WIP Service Labor | C61: 211397.24 | D61: 217186.98 | E61: -5789.74 | F61: =VLOOKUP(B61,'Profit & Loss'!$B$3:$C$390,2,0) -> #N/A
A62: 10503 | B62: 1566000020 WIP Service LPO | C62: 45978.57 | D62: 58879.92 | E62: -12901.35 | F62: =VLOOKUP(B62,'Profit & Loss'!$B$3:$C$390,2,0) -> #N/A
A63: 10503 | B63: 1566000050 WIP Service Travel | C63: 361.42 | D63: 375.36 | E63: -13.94 | F63: =VLOOKUP(B63,'Profit & Loss'!$B$3:$C$390,2,0) -> #N/A
A64: 10503 | C64: 506522.04 | D64: 498776.67 | E64: 7745.37 | F64: =VLOOKUP(B64,'Profit & Loss'!$B$3:$C$390,2,0) -> #N/A
A65: 105 | C65: 26043981 | D65: 20530698 | E65: 5513282.3 | F65: =VLOOKUP(B65,'Profit & Loss'!$B$3:$C$390,2,0) -> #N/A
A66: 10701 | B66: 1612001010 Prepayment 3rd Party Office Rent | C66: -6135.39 | D66: -6135.39 | E66: 0 | F66: =VLOOKUP(B66,'Profit & Loss'!$B$3:$C$390,2,0) -> #N/A
A67: 10701 | B67: 1612001020 Prepayment 3rd Party Office Rent Imp (LHI) | C67: 8024.64 | D67: 8601.35 | E67: -576.71 | F67: =VLOOKUP(B67,'Profit & Loss'!$B$3:$C$390,2,0) -> #N/A
A68: 10701 | B68: 1612002000 Prepayment Related Party | C68: 6329.17 | D68: 6329.17 | E68: 0 | F68: =VLOOKUP(B68,'Profit & Loss'!$B$3:$C$390,2,0) -> #N/A
A69: 10701 | B69: 1630000110 Advance To Employee Travel | C69: 36.16 | D69: 886.17 | E69: -850.01 | F69: =VLOOKUP(B69,'Profit & Loss'!$B$3:$C$390,2,0) -> #N/A
A70: 10701 | B70: 1630000119 Advance To Employee Travel Adv FxV | C70: 0.07 | D70: -9.14 | E70: 9.21 | F70: =VLOOKUP(B70,'Profit & Loss'!$B$3:$C$390,2,0) -> #N/A
A71: 10701 | C71: 8254.65 | D71: 9672.16 | E71: -1417.51 | F71: =VLOOKUP(B71,'Profit & Loss'!$B$3:$C$390,2,0) -> #N/A
A72: 107 | C72: 8254.65 | D72: 9672.16 | E72: -1417.51 | F72: =VLOOKUP(B72,'Profit & Loss'!$B$3:$C$390,2,0) -> #N/A
A73: 11001 | B73: 1811102000 FA Acquisition Owned Self Usage Building | C73: 359163.46 | D73: 359163.46 | E73: 0 | F73: =VLOOKUP(B73,'Profit & Loss'!$B$3:$C$390,2,0) -> #N/A
A74: 11001 | B74: 1821102000 FA Accumulated Depreciation Owned Building | C74: -263726.11 | D74: -262611.32 | E74: -1114.79 | F74: =VLOOKUP(B74,'Profit & Loss'!$B$3:$C$390,2,0) -> #N/A
A75: 11001 | C75: 95437.35 | D75: 96552.14 | E75: -1114.79 | F75: =VLOOKUP(B75,'Profit & Loss'!$B$3:$C$390,2,0) -> #N/A
A76: 11003 | B76: 1811115000 FA Acquisition Owned Warehouse Equip | C76: 132848.63 | D76: 132848.63 | E76: 0 | F76: =VLOOKUP(B76,'Profit & Loss'!$B$3:$C$390,2,0) -> #N/A
A77: 11003 | B77: 1811116000 FA Acquisition Owned Workshop Equip | C77: 773272.12 | D77: 767309.11 | E77: 5963.01 | F77: =VLOOKUP(B77,'Profit & Loss'!$B$3:$C$390,2,0) -> #N/A
A78: 11003 | B78: 1811117000 FA Acquisition Owned Service Tool | C78: 390555.42 | D78: 380496.66 | E78: 10058.76 | F78: =VLOOKUP(B78,'Profit & Loss'!$B$3:$C$390,2,0) -> #N/A
A79: 11003 | B79: 1811119000 FA Acquisition Owned Training Center Equipment | C79: 495.24 | D79: 495.24 | E79: 0 | F79: =VLOOKUP(B79,'Profit & Loss'!$B$3:$C$390,2,0) -> #N/A
A80: 11003 | B80: 1811140000 FA Acquisition Owned Office Equipment | C80: 257728.68 | D80: 263566.81 | E80: -5838.13 | F80: =VLOOKUP(B80,'Profit & Loss'!$B$3:$C$390,2,0) -> #N/A
A81: 11003 | B81: 1821115000 FA Accumulated Depreciation Owned Warehouse Equip | C81: -126918.54 | D81: -126644.01 | E81: -274.53 | F81: =VLOOKUP(B81,'Profit & Loss'!$B$3:$C$390,2,0) -> #N/A
A82: 11003 | B82: 1821116000 FA Accumulated Depreciation Owned Workshop Equip | C82: -448598.02 | D82: -442801.36 | E82: -5796.66 | F82: =VLOOKUP(B82,'Profit & Loss'!$B$3:$C$390,2,0) -> #N/A
A83: 11003 | B83: 1821117000 FA Accumulated Depreciation Owned Service Tool | C83: -305017.97 | D83: -302267.12 | E83: -2750.85 | F83: =VLOOKUP(B83,'Profit & Loss'!$B$3:$C$390,2,0) -> #N/A
A84: 11003 | B84: 1821119000 FA Accumulated Depreciation Owned TC Equip | C84: -495.24 | D84: -495.24 | E84: 0 | F84: =VLOOKUP(B84,'Profit & Loss'!$B$3:$C$390,2,0) -> #N/A
A85: 11003 | B85: 1821140000 FA Accumulated Depreciation Owned Office Equipment | C85: -207342.47 | D85: -214623.59 | E85: 7281.12 | F85: =VLOOKUP(B85,'Profit & Loss'!$B$3:$C$390,2,0) -> #N/A
A86: 11003 | C86: 466527.85 | D86: 457885.13 | E86: 8642.72 | F86: =VLOOKUP(B86,'Profit & Loss'!$B$3:$C$390,2,0) -> #N/A
A87: 11004 | B87: 1811301000 FA Acquisition Owned Rental Fleet Machine | C87: 19105809 | D87: 18985572 | E87: 120237.68 | F87: =VLOOKUP(B87,'Profit & Loss'!$B$3:$C$390,2,0) -> #N/A
A88: 11004 | B88: 1821301000 FA Accumulated Depreciation Owned Rental Fleet Mac | C88: -6580113.7 | D88: -6307736.2 | E88: -272377.43 | F88: =VLOOKUP(B88,'Profit & Loss'!$B$3:$C$390,2,0) -> #N/A
A89: 11004 | C89: 12525696 | D89: 12677835 | E89: -152139.75 | F89: =VLOOKUP(B89,'Profit & Loss'!$B$3:$C$390,2,0) -> #N/A
A90: 11005 | B90: 1811130000 FA Acquisition Owned Vehicle Sedan | C90: 103060.72 | D90: 103060.72 | E90: 0 | F90: =VLOOKUP(B90,'Profit & Loss'!$B$3:$C$390,2,0) -> #N/A
A91: 11005 | B91: 1811131000 FA Acquisition Owned Vehicle Truck | C91: 655044.08 | D91: 655044.08 | E91: 0 | F91: =VLOOKUP(B91,'Profit & Loss'!$B$3:$C$390,2,0) -> #N/A
A92: 11005 | B92: 1821130000 FA Accumulated Depreciation Owned Vehicle Sedan | C92: -102115.8 | D92: -102060.21 | E92: -55.59 | F92: =VLOOKUP(B92,'Profit & Loss'!$B$3:$C$390,2,0) -> #N/A
A93: 11005 | B93: 1821131000 FA Accumulated Depreciation Owned Vehicle Truck | C93: -676325.54 | D93: -674624.6 | E93: -1700.94 | F93: =VLOOKUP(B93,'Profit & Loss'!$B$3:$C$390,2,0) -> #N/A
A94: 11005 | C94: -20336.54 | D94: -18580.01 | E94: -1756.53 | F94: =VLOOKUP(B94,'Profit & Loss'!$B$3:$C$390,2,0) -> #N/A
A95: 11006 | B95: 1811160000 FA Acquisition Owned IT Devices Computer | C95: 4903.31 | D95: 4903.31 | E95: 0 | F95: =VLOOKUP(B95,'Profit & Loss'!$B$3:$C$390,2,0) -> #N/A
A96: 11006 | B96: 1813103000 FA Acquisition Lease IT Device | C96: 255044.67 | D96: 255044.67 | E96: 0 | F96: =VLOOKUP(B96,'Profit & Loss'!$B$3:$C$390,2,0) -> #N/A
A97: 11006 | B97: 1821160000 FA Accumulated Depreciation Owned IT Devices Comp | C97: -3640.24 | D97: -3568.08 | E97: -72.16 | F97: =VLOOKUP(B97,'Profit & Loss'!$B$3:$C$390,2,0) -> #N/A
A98: 11006 | B98: 1823103000 FA Accumulated Depreciation IT Device | C98: -177899.54 | D98: -172634.68 | E98: -5264.86 | F98: =VLOOKUP(B98,'Profit & Loss'!$B$3:$C$390,2,0) -> #N/A
A99: 11006 | C99: 78408.2 | D99: 83745.22 | E99: -5337.02 | F99: =VLOOKUP(B99,'Profit & Loss'!$B$3:$C$390,2,0) -> #N/A
A100: 11007 | B100: 1811200010 FA Acquisition Owned Component | C100: 146144.09 | D100: 146144.09 | E100: 0 | F100: =VLOOKUP(B100,'Profit & Loss'!$B$3:$C$390,2,0) -> #N/A
...

Sheet AUG 22
A1: Financial Statement Item | B1: Text for B/S P&L item | C1: Total of reporting period | D1: Total of the comparison period | E1: Absolute difference | F1: Percentage difference
A2: 1000000 | B2: A S S E T S | C2: 0 | D2: 0 | E2: 0 | F2: =VLOOKUP(B2,'Profit & Loss'!$B$2:$C$390,2,0) -> #N/A
A3: 1000000 | B3: = = = = = = | C3: 0 | D3: 0 | E3: 0 | F3: =VLOOKUP(B3,'Profit & Loss'!$B$2:$C$390,2,0) -> #N/A
